Workbook
Name JobIDs: Jobs!$A$5:$A$44
Name ClientNames: Clients!$A$5:$A$104
Name CostCodes: Settings!$E$5:$E$28
Name CrewNames: 'Vendors & Crew'!$A$5:$A$34
Name VendorNames: 'Vendors & Crew'!$A$41:$A$140
Name InvoiceNumbers: Invoices!$A$5:$A$204
Name LibraryItems: 'Cost Library'!$A$5:$A$204
Name MarkupTable: Settings!$A$22:$B$27

Sheet Start Here
B1: Contractor Job Costing & Estimate Spreadsheet
B3: Estimate → schedule → track hours and costs → change orders → invoice → collect → see real profit. Works in Microsoft Excel (2016+, 365, Mac) and Google Sheets. Version 1.0 (2026-09).
B5: HOW IT FLOWS
B6: 1 Settings | C6: 2 Clients, Vendors & Crew | D6: 3 Jobs | E6: 4 Estimate → Proposal | F6: 5 Schedule | G6: 6 Timesheet, Costs, Mileage, Log | H6: 7 Change Orders | I6: 8 Invoices → Payments
B7: Dashboard, Job Profit Report, Reports, Tax Summary and Health Check update themselves from these inputs.
B9: SETUP
B10: Settings | C10: Company details, markups, tax, deposit and progress %, mileage rate, labor burden, cost codes, document text. Start here.
B11: Clients | C11: Client directory with lifetime value and balance due.
B12: Vendors & Crew | C12: Crew rates for the Timesheet; vendor and sub directory with insurance alerts and 1099 flags.
B13: Cost Library | C13: Your price book: items with unit and unit cost that fill into estimates.
B15: INPUTS
B16: Jobs | C16: One row per job. Everything rolls up here.
B17: Estimate | C17: Line-by-line quote with automatic category markup and library lookups.
B18: Schedule | C18: Tasks with workday end dates and a 12-week Gantt chart.
B19: Timesheet | C19: Crew hours by day and job with a weekly payroll summary.
B20: Job Costs | C20: Materials, subs, equipment, permits and other actual costs.
B21: Mileage | C21: Job-related driving at your mileage rate.
B22: Daily Log | C22: Weather, crew, work performed, issues, inspections — your dispute record.
B23: Change Orders | C23: Added work; approved COs raise the contract and the budget.
B24: Invoices | C24: Invoices with balances, status, days overdue and aging bucket.
B25: Payments | C25: Money received, linked to invoices and jobs.
B27: DOCUMENTS & REPORTS
B28: Proposal | C28: Client-ready proposal: scope, payment schedule, detailed lines, terms, signatures.
B29: CO Form | C29: Signature-ready change order document.
B30: Invoice Print | C30: Printable invoice with contract summary.
B31: Client Statement | C31: All of a client's invoices, balances and aging on one page.
B32: Job Profit Report | C32: Budget vs actual by category and cost code for one job.
B33: Reports | C33: Receivables aging, cash forecast, pipeline, win rate, cost-code performance.
B34: Tax Summary | C34: Year-end totals by category, mileage, 1099 review list.
B35: Dashboard | C35: 16 KPIs, alerts, charts, per-job table, monthly P&L.
B36: Health Check | C36: Counts data problems and formula errors. Keep it at ALL CLEAR.
B38: TEN-MINUTE SETUP
B39: 1. Settings: company details, markups, contingency, tax, deposit %, mileage rate, labor burden. Rename cost codes to match your trade.
B40: 2. Vendors & Crew: add your workers with cost and bill rates, and your subs and suppliers.
B41: 3. Clients and Jobs: add a client, then a job row with a Job ID such as J-1001 (the sheet suggests the next one).
B42: 4. Estimate the job, open Proposal, pick the Job ID, print. Enter the signed Contract Value on Jobs.
B43: 5. As work happens: Timesheet for crew hours, Job Costs for everything else, Mileage, Daily Log, Change Orders.
B44: 6. Invoice from the Invoices sheet and print with Invoice Print; record Payments; send Client Statements. Watch the Dashboard.
B46: COLOR KEY
B47: Light-blue cells are inputs. Every other cell is a formula: do not type over them (Undo with Ctrl+Z / Cmd+Z if you do).
B48: Red = over budget, overdue, late, expired, or a data problem. Yellow = watch. Green = on track / paid / done.
B50: PROTECT AGAINST ACCIDENTS (optional)
B51: Input cells are already unlocked. On any sheet, Review → Protect Sheet (leave the password blank) and only the light-blue cells stay editable. Unprotect before inserting rows.
... B63: Licensed for use in your own business on any number of your devices. Resale or redistribution of the template is not permitted.

Sheet Dashboard
A1: Dashboard
A2: Company-wide view. Everything here is calculated. Change the reporting year in Settings to move the monthly P&L. | K2: As of | L2: =TODAY()
B4: Revised contract value (all jobs) | E4: Estimated cost | H4: Actual cost to date | K4: Projected gross profit
B5: =Jobs!K45 | E5: =Jobs!L45 | H5: =Jobs!M45 | K5: =Jobs!T45
B7: Projected gross margin | E7: Margin after overhead (Settings %) | H7: Invoiced | K7: Collected
B8: =Jobs!U45 | E8: =IF(Jobs!K45=0,0,(Jobs!T45-Jobs!K45*Settings!$B$17)/Jobs!K45) | H8: =Jobs!Q45 | K8: =Jobs!R45
B10: Outstanding balance | E10: Overdue balance | H10: Backlog (active jobs not yet invoiced) | K10: Unpaid bills logged (Paid? = No)
B11: =Jobs!S45 | E11: =SUMIFS(Invoices!$H$5:$H$204,Invoices!$I$5:$I$204,"Overdue") | H11: =SUMIFS(Jobs!$K$5:$K$44,Jobs!$D$5:$D$44,"Approved")+SUMIFS(Jobs!$K$5:$K$44,Jobs!$D$5:$D$44,"In Progress")-(SUMIFS(Jobs!$Q$5:$Q$44,Jobs!$D$5:$D$44,"Approved")+SUMIFS(Jobs!$Q$5:$Q$44,Jobs!$D$5:$D$44,"In Progress")) | K11: =SUMIFS('Job Costs'!$I$5:$I$1004,'Job Costs'!$J$5:$J$1004,"No")
B13: Active jobs (Approved / In Progress) | E13: Jobs over budget | H13: Labor hours this month | K13: Win rate (won ÷ won + lost)
B14: =COUNTIF(Jobs!$D$5:$D$44,"Approved")+COUNTIF(Jobs!$D$5:$D$44,"In Progress") | E14: =COUNTIF(Jobs!$O$5:$O$44,">1") | H14: =SUMIFS(Timesheet!$E$5:$E$1004,Timesheet!$A$5:$A$1004,">="&DATE(YEAR(TODAY()),MONTH(TODAY()),1),Timesheet!$A$5:$A$1004,"<="&EOMONTH(TODAY(),0)) | K14: =IF(COUNTIF(Jobs!$D$5:$D$44,"Approved")+COUNTIF(Jobs!$D$5:$D$44,"In Progress")+COUNTIF(Jobs!$D$5:$D$44,"Complete")+COUNTIF(Jobs!$D$5:$D$44,"Closed")+COUNTIF(Jobs!$D$5:$D$44,"Lost")=0,0,(COUNTIF(Jobs!$D$5:$D$44,"Approved")+COUNTIF(Jobs!$D$5:$D$44,"In Progress")+COUNTIF(Jobs!$D$5:$D$44,"Complete")+COUNTIF(Jobs!$D$5:$D$44,"Closed"))/(COUNTIF(Jobs!$D$5:$D$44,"Approved")+COUNTIF(Jobs!$D$5:$D$44,"In Progress")+COUNTIF(Jobs!$D$5:$D$44,"Complete")+COUNTIF(Jobs!$D$5:$D$44,"Closed")+COUNTIF(Jobs!$D$5:$D$44,"Lost")))
B16: ALERTS
B17: Overdue invoices | E17: Late schedule tasks | H17: Vendor insurance expired / expiring | K17: Data issues (Health Check)
B18: =COUNTIF(Invoices!$I$5:$I$204,"Overdue") | E18: =COUNTIF(Schedule!$H$5:$H$204,"Late") | H18: =COUNTIF('Vendors & Crew'!$H$41:$H$140,"EXPIRED")+COUNTIF('Vendors & Crew'!$H$41:$H$140,"Expiring soon") | K18: ='Health Check'!C19
B20: THIS MONTH
B21: Invoiced this month | E21: Collected this month | H21: Costs this month (all sources) | K21: Cash profit this month
B22: =SUMIFS(Invoices!$E$5:$E$204,Invoices!$C$5:$C$204,">="&DATE(YEAR(TODAY()),MONTH(TODAY()),1),Invoices!$C$5:$C$204,"<="&EOMONTH(TODAY(),0)) | E22: =SUMIFS(Payments!$D$5:$D$304,Payments!$A$5:$A$304,">="&DATE(YEAR(TODAY()),MONTH(TODAY()),1),Payments!$A$5:$A$304,"<="&EOMONTH(TODAY(),0)) | H22: =SUMIFS('Job Costs'!$I$5:$I$1004,'Job Costs'!$A$5:$A$1004,">="&DATE(YEAR(TODAY()),MONTH(TODAY()),1),'Job Costs'!$A$5:$A$1004,"<="&EOMONTH(TODAY(),0))+SUMIFS(Timesheet!$H$5:$H$1004,Timesheet!$A$5:$A$1004,">="&DATE(YEAR(TODAY()),MONTH(TODAY()),1),Timesheet!$A$5:$A$1004,"<="&EOMONTH(TODAY(),0))+SUMIFS(Mileage!$I$5:$I$304,Mileage!$A$5:$A$304,">="&DATE(YEAR(TODAY()),MONTH(TODAY()),1),Mileage!$A$5:$A$304,"<="&EOMONTH(TODAY(),0)) | K22: =E22-H22
B24: Charts
B39: Jobs
B40: Job ID | C40: Client | D40: Status | E40: Revised Contract | F40: Actual Cost | G40: Projected Profit | H40: Margin % | I40: % Budget Used | J40: Balance Due | K40: Days to Target | L40: Hours
B41: =IF(Jobs!$A5="","",Jobs!A5) | C41: =IF(Jobs!$A5="","",Jobs!B5) | D41: =IF(Jobs!$A5="","",Jobs!D5) | E41: =IF(Jobs!$A5="","",Jobs!K5) | F41: =IF(Jobs!$A5="","",Jobs!M5) | G41: =IF(Jobs!$A5="","",Jobs!T5) | H41: =IF(Jobs!$A5="","",Jobs!U5) | I41: =IF(Jobs!$A5="","",Jobs!O5) | J41: =IF(Jobs!$A5="","",Jobs!S5) | K41: =IF(Jobs!$A5="","",Jobs!W5) | L41: =IF(Jobs!$A5="","",Jobs!P5)
B42: =IF(Jobs!$A6="","",Jobs!A6) | C42: =IF(Jobs!$A6="","",Jobs!B6) | D42: =IF(Jobs!$A6="","",Jobs!D6) | E42: =IF(Jobs!$A6="","",Jobs!K6) | F42: =IF(Jobs!$A6="","",Jobs!M6) | G42: =IF(Jobs!$A6="","",Jobs!T6) | H42: =IF(Jobs!$A6="","",Jobs!U6) | I42: =IF(Jobs!$A6="","",Jobs!O6) | J42: =IF(Jobs!$A6="","",Jobs!S6) | K42: =IF(Jobs!$A6="","",Jobs!W6) | L42: =IF(Jobs!$A6="","",Jobs!P6)
B43: =IF(Jobs!$A7="","",Jobs!A7) | C43: =IF(Jobs!$A7="","",Jobs!B7) | D43: =IF(Jobs!$A7="","",Jobs!D7) | E43: =IF(Jobs!$A7="","",Jobs!K7) | F43: =IF(Jobs!$A7="","",Jobs!M7) | G43: =IF(Jobs!$A7="","",Jobs!T7) | H43: =IF(Jobs!$A7="","",Jobs!U7) | I43: =IF(Jobs!$A7="","",Jobs!O7) | J43: =IF(Jobs!$A7="","",Jobs!S7) | K43: =IF(Jobs!$A7="","",Jobs!W7) | L43: =IF(Jobs!$A7="","",Jobs!P7)
B44: =IF(Jobs!$A8="","",Jobs!A8) | C44: =IF(Jobs!$A8="","",Jobs!B8) | D44: =IF(Jobs!$A8="","",Jobs!D8) | E44: =IF(Jobs!$A8="","",Jobs!K8) | F44: =IF(Jobs!$A8="","",Jobs!M8) | G44: =IF(Jobs!$A8="","",Jobs!T8) | H44: =IF(Jobs!$A8="","",Jobs!U8) | I44: =IF(Jobs!$A8="","",Jobs!O8) | J44: =IF(Jobs!$A8="","",Jobs!S8) | K44: =IF(Jobs!$A8="","",Jobs!W8) | L44: =IF(Jobs!$A8="","",Jobs!P8)
B45: =IF(Jobs!$A9="","",Jobs!A9) | C45: =IF(Jobs!$A9="","",Jobs!B9) | D45: =IF(Jobs!$A9="","",Jobs!D9) | E45: =IF(Jobs!$A9="","",Jobs!K9) | F45: =IF(Jobs!$A9="","",Jobs!M9) | G45: =IF(Jobs!$A9="","",Jobs!T9) | H45: =IF(Jobs!$A9="","",Jobs!U9) | I45: =IF(Jobs!$A9="","",Jobs!O9) | J45: =IF(Jobs!$A9="","",Jobs!S9) | K45: =IF(Jobs!$A9="","",Jobs!W9) | L45: =IF(Jobs!$A9="","",Jobs!P9)
B46: =IF(Jobs!$A10="","",Jobs!A10) | C46: =IF(Jobs!$A10="","",Jobs!B10) | D46: =IF(Jobs!$A10="","",Jobs!D10) | E46: =IF(Jobs!$A10="","",Jobs!K10) | F46: =IF(Jobs!$A10="","",Jobs!M10) | G46: =IF(Jobs!$A10="","",Jobs!T10) | H46: =IF(Jobs!$A10="","",Jobs!U10) | I46: =IF(Jobs!$A10="","",Jobs!O10) | J46: =IF(Jobs!$A10="","",Jobs!S10) | K46: =IF(Jobs!$A10="","",Jobs!W10) | L46: =IF(Jobs!$A10="","",Jobs!P10)
B47: =IF(Jobs!$A11="","",Jobs!A11) | C47: =IF(Jobs!$A11="","",Jobs!B11) | D47: =IF(Jobs!$A11="","",Jobs!D11) | E47: =IF(Jobs!$A11="","",Jobs!K11) | F47: =IF(Jobs!$A11="","",Jobs!M11) | G47: =IF(Jobs!$A11="","",Jobs!T11) | H47: =IF(Jobs!$A11="","",Jobs!U11) | I47: =IF(Jobs!$A11="","",Jobs!O11) | J47: =IF(Jobs!$A11="","",Jobs!S11) | K47: =IF(Jobs!$A11="","",Jobs!W11) | L47: =IF(Jobs!$A11="","",Jobs!P11)
B48: =IF(Jobs!$A12="","",Jobs!A12) | C48: =IF(Jobs!$A12="","",Jobs!B12) | D48: =IF(Jobs!$A12="","",Jobs!D12) | E48: =IF(Jobs!$A12="","",Jobs!K12) | F48: =IF(Jobs!$A12="","",Jobs!M12) | G48: =IF(Jobs!$A12="","",Jobs!T12) | H48: =IF(Jobs!$A12="","",Jobs!U12) | I48: =IF(Jobs!$A12="","",Jobs!O12) | J48: =IF(Jobs!$A12="","",Jobs!S12) | K48: =IF(Jobs!$A12="","",Jobs!W12) | L48: =IF(Jobs!$A12="","",Jobs!P12)
B49: =IF(Jobs!$A13="","",Jobs!A13) | C49: =IF(Jobs!$A13="","",Jobs!B13) | D49: =IF(Jobs!$A13="","",Jobs!D13) | E49: =IF(Jobs!$A13="","",Jobs!K13) | F49: =IF(Jobs!$A13="","",Jobs!M13) | G49: =IF(Jobs!$A13="","",Jobs!T13) | H49: =IF(Jobs!$A13="","",Jobs!U13) | I49: =IF(Jobs!$A13="","",Jobs!O13) | J49: =IF(Jobs!$A13="","",Jobs!S13) | K49: =IF(Jobs!$A13="","",Jobs!W13) | L49: =IF(Jobs!$A13="","",Jobs!P13)
B50: =IF(Jobs!$A14="","",Jobs!A14) | C50: =IF(Jobs!$A14="","",Jobs!B14) | D50: =IF(Jobs!$A14="","",Jobs!D14) | E50: =IF(Jobs!$A14="","",Jobs!K14) | F50: =IF(Jobs!$A14="","",Jobs!M14) | G50: =IF(Jobs!$A14="","",Jobs!T14) | H50: =IF(Jobs!$A14="","",Jobs!U14) | I50: =IF(Jobs!$A14="","",Jobs!O14) | J50: =IF(Jobs!$A14="","",Jobs!S14) | K50: =IF(Jobs!$A14="","",Jobs!W14) | L50: =IF(Jobs!$A14="","",Jobs!P14)
B51: =IF(Jobs!$A15="","",Jobs!A15) | C51: =IF(Jobs!$A15="","",Jobs!B15) | D51: =IF(Jobs!$A15="","",Jobs!D15) | E51: =IF(Jobs!$A15="","",Jobs!K15) | F51: =IF(Jobs!$A15="","",Jobs!M15) | G51: =IF(Jobs!$A15="","",Jobs!T15) | H51: =IF(Jobs!$A15="","",Jobs!U15) | I51: =IF(Jobs!$A15="","",Jobs!O15) | J51: =IF(Jobs!$A15="","",Jobs!S15) | K51: =IF(Jobs!$A15="","",Jobs!W15) | L51: =IF(Jobs!$A15="","",Jobs!P15)
B52: =IF(Jobs!$A16="","",Jobs!A16) | C52: =IF(Jobs!$A16="","",Jobs!B16) | D52: =IF(Jobs!$A16="","",Jobs!D16) | E52: =IF(Jobs!$A16="","",Jobs!K16) | F52: =IF(Jobs!$A16="","",Jobs!M16) | G52: =IF(Jobs!$A16="","",Jobs!T16) | H52: =IF(Jobs!$A16="","",Jobs!U16) | I52: =IF(Jobs!$A16="","",Jobs!O16) | J52: =IF(Jobs!$A16="","",Jobs!S16) | K52: =IF(Jobs!$A16="","",Jobs!W16) | L52: =IF(Jobs!$A16="","",Jobs!P16)
... B80: =IF(Jobs!$A44="","",Jobs!A44) | C80: =IF(Jobs!$A44="","",Jobs!B44) | D80: =IF(Jobs!$A44="","",Jobs!D44) | E80: =IF(Jobs!$A44="","",Jobs!K44) | F80: =IF(Jobs!$A44="","",Jobs!M44) | G80: =IF(Jobs!$A44="","",Jobs!T44) | H80: =IF(Jobs!$A44="","",Jobs!U44) | I80: =IF(Jobs!$A44="","",Jobs!O44) | J80: =IF(Jobs!$A44="","",Jobs!S44) | K80: =IF(Jobs!$A44="","",Jobs!W44) | L80: =IF(Jobs!$A44="","",Jobs!P44)
B82: Monthly P&L | D82: Year: | E82: =Settings!$B$14
B83: Month | C83: Invoiced | D83: Payments Received | E83: Costs (all sources) | F83: Cash Profit | G83: Cumulative | H83: Labor Hours
B84: =DATE($E$82,1,1) | C84: =SUMIFS(Invoices!$E$5:$E$204,Invoices!$C$5:$C$204,">="&B84,Invoices!$C$5:$C$204,"<="&EOMONTH(B84,0)) | D84: =SUMIFS(Payments!$D$5:$D$304,Payments!$A$5:$A$304,">="&B84,Payments!$A$5:$A$304,"<="&EOMONTH(B84,0)) | E84: =SUMIFS('Job Costs'!$I$5:$I$1004,'Job Costs'!$A$5:$A$1004,">="&B84,'Job Costs'!$A$5:$A$1004,"<="&EOMONTH(B84,0))+SUMIFS(Timesheet!$H$5:$H$1004,Timesheet!$A$5:$A$1004,">="&B84,Timesheet!$A$5:$A$1004,"<="&EOMONTH(B84,0))+SUMIFS(Mileage!$I$5:$I$304,Mileage!$A$5:$A$304,">="&B84,Mileage!$A$5:$A$304,"<="&EOMONTH(B84,0)) | F84: =D84-E84 | G84: =SUM($F$84:F84) | H84: =SUMIFS(Timesheet!$E$5:$E$1004,Timesheet!$A$5:$A$1004,">="&B84,Timesheet!$A$5:$A$1004,"<="&EOMONTH(B84,0))
B85: =DATE($E$82,2,1) | C85: =SUMIFS(Invoices!$E$5:$E$204,Invoices!$C$5:$C$204,">="&B85,Invoices!$C$5:$C$204,"<="&EOMONTH(B85,0)) | D85: =SUMIFS(Payments!$D$5:$D$304,Payments!$A$5:$A$304,">="&B85,Payments!$A$5:$A$304,"<="&EOMONTH(B85,0)) | E85: =SUMIFS('Job Costs'!$I$5:$I$1004,'Job Costs'!$A$5:$A$1004,">="&B85,'Job Costs'!$A$5:$A$1004,"<="&EOMONTH(B85,0))+SUMIFS(Timesheet!$H$5:$H$1004,Timesheet!$A$5:$A$1004,">="&B85,Timesheet!$A$5:$A$1004,"<="&EOMONTH(B85,0))+SUMIFS(Mileage!$I$5:$I$304,Mileage!$A$5:$A$304,">="&B85,Mileage!$A$5:$A$304,"<="&EOMONTH(B85,0)) | F85: =D85-E85 | G85: =SUM($F$84:F85) | H85: =SUMIFS(Timesheet!$E$5:$E$1004,Timesheet!$A$5:$A$1004,">="&B85,Timesheet!$A$5:$A$1004,"<="&EOMONTH(B85,0))
B86: =DATE($E$82,3,1) | C86: =SUMIFS(Invoices!$E$5:$E$204,Invoices!$C$5:$C$204,">="&B86,Invoices!$C$5:$C$204,"<="&EOMONTH(B86,0)) | D86: =SUMIFS(Payments!$D$5:$D$304,Payments!$A$5:$A$304,">="&B86,Payments!$A$5:$A$304,"<="&EOMONTH(B86,0)) | E86: =SUMIFS('Job Costs'!$I$5:$I$1004,'Job Costs'!$A$5:$A$1004,">="&B86,'Job Costs'!$A$5:$A$1004,"<="&EOMONTH(B86,0))+SUMIFS(Timesheet!$H$5:$H$1004,Timesheet!$A$5:$A$1004,">="&B86,Timesheet!$A$5:$A$1004,"<="&EOMONTH(B86,0))+SUMIFS(Mileage!$I$5:$I$304,Mileage!$A$5:$A$304,">="&B86,Mileage!$A$5:$A$304,"<="&EOMONTH(B86,0)) | F86: =D86-E86 | G86: =SUM($F$84:F86) | H86: =SUMIFS(Timesheet!$E$5:$E$1004,Timesheet!$A$5:$A$1004,">="&B86,Timesheet!$A$5:$A$1004,"<="&EOMONTH(B86,0))
B87: =DATE($E$82,4,1) | C87: =SUMIFS(Invoices!$E$5:$E$204,Invoices!$C$5:$C$204,">="&B87,Invoices!$C$5:$C$204,"<="&EOMONTH(B87,0)) | D87: =SUMIFS(Payments!$D$5:$D$304,Payments!$A$5:$A$304,">="&B87,Payments!$A$5:$A$304,"<="&EOMONTH(B87,0)) | E87: =SUMIFS('Job Costs'!$I$5:$I$1004,'Job Costs'!$A$5:$A$1004,">="&B87,'Job Costs'!$A$5:$A$1004,"<="&EOMONTH(B87,0))+SUMIFS(Timesheet!$H$5:$H$1004,Timesheet!$A$5:$A$1004,">="&B87,Timesheet!$A$5:$A$1004,"<="&EOMONTH(B87,0))+SUMIFS(Mileage!$I$5:$I$304,Mileage!$A$5:$A$304,">="&B87,Mileage!$A$5:$A$304,"<="&EOMONTH(B87,0)) | F87: =D87-E87 | G87: =SUM($F$84:F87) | H87: =SUMIFS(Timesheet!$E$5:$E$1004,Timesheet!$A$5:$A$1004,">="&B87,Timesheet!$A$5:$A$1004,"<="&EOMONTH(B87,0))
B88: =DATE($E$82,5,1) | C88: =SUMIFS(Invoices!$E$5:$E$204,Invoices!$C$5:$C$204,">="&B88,Invoices!$C$5:$C$204,"<="&EOMONTH(B88,0)) | D88: =SUMIFS(Payments!$D$5:$D$304,Payments!$A$5:$A$304,">="&B88,Payments!$A$5:$A$304,"<="&EOMONTH(B88,0)) | E88: =SUMIFS('Job Costs'!$I$5:$I$1004,'Job Costs'!$A$5:$A$1004,">="&B88,'Job Costs'!$A$5:$A$1004,"<="&EOMONTH(B88,0))+SUMIFS(Timesheet!$H$5:$H$1004,Timesheet!$A$5:$A$1004,">="&B88,Timesheet!$A$5:$A$1004,"<="&EOMONTH(B88,0))+SUMIFS(Mileage!$I$5:$I$304,Mileage!$A$5:$A$304,">="&B88,Mileage!$A$5:$A$304,"<="&EOMONTH(B88,0)) | F88: =D88-E88 | G88: =SUM($F$84:F88) | H88: =SUMIFS(Timesheet!$E$5:$E$1004,Timesheet!$A$5:$A$1004,">="&B88,Timesheet!$A$5:$A$1004,"<="&EOMONTH(B88,0))
B89: =DATE($E$82,6,1) | C89: =SUMIFS(Invoices!$E$5:$E$204,Invoices!$C$5:$C$204,">="&B89,Invoices!$C$5:$C$204,"<="&EOMONTH(B89,0)) | D89: =SUMIFS(Payments!$D$5:$D$304,Payments!$A$5:$A$304,">="&B89,Payments!$A$5:$A$304,"<="&EOMONTH(B89,0)) | E89: =SUMIFS('Job Costs'!$I$5:$I$1004,'Job Costs'!$A$5:$A$1004,">="&B89,'Job Costs'!$A$5:$A$1004,"<="&EOMONTH(B89,0))+SUMIFS(Timesheet!$H$5:$H$1004,Timesheet!$A$5:$A$1004,">="&B89,Timesheet!$A$5:$A$1004,"<="&EOMONTH(B89,0))+SUMIFS(Mileage!$I$5:$I$304,Mileage!$A$5:$A$304,">="&B89,Mileage!$A$5:$A$304,"<="&EOMONTH(B89,0)) | F89: =D89-E89 | G89: =SUM($F$84:F89) | H89: =SUMIFS(Timesheet!$E$5:$E$1004,Timesheet!$A$5:$A$1004,">="&B89,Timesheet!$A$5:$A$1004,"<="&EOMONTH(B89,0))
B90: =DATE($E$82,7,1) | C90: =SUMIFS(Invoices!$E$5:$E$204,Invoices!$C$5:$C$204,">="&B90,Invoices!$C$5:$C$204,"<="&EOMONTH(B90,0)) | D90: =SUMIFS(Payments!$D$5:$D$304,Payments!$A$5:$A$304,">="&B90,Payments!$A$5:$A$304,"<="&EOMONTH(B90,0)) | E90: =SUMIFS('Job Costs'!$I$5:$I$1004,'Job Costs'!$A$5:$A$1004,">="&B90,'Job Costs'!$A$5:$A$1004,"<="&EOMONTH(B90,0))+SUMIFS(Timesheet!$H$5:$H$1004,Timesheet!$A$5:$A$1004,">="&B90,Timesheet!$A$5:$A$1004,"<="&EOMONTH(B90,0))+SUMIFS(Mileage!$I$5:$I$304,Mileage!$A$5:$A$304,">="&B90,Mileage!$A$5:$A$304,"<="&EOMONTH(B90,0)) | F90: =D90-E90 | G90: =SUM($F$84:F90) | H90: =SUMIFS(Timesheet!$E$5:$E$1004,Timesheet!$A$5:$A$1004,">="&B90,Timesheet!$A$5:$A$1004,"<="&EOMONTH(B90,0))
B91: =DATE($E$82,8,1) | C91: =SUMIFS(Invoices!$E$5:$E$204,Invoices!$C$5:$C$204,">="&B91,Invoices!$C$5:$C$204,"<="&EOMONTH(B91,0)) | D91: =SUMIFS(Payments!$D$5:$D$304,Payments!$A$5:$A$304,">="&B91,Payments!$A$5:$A$304,"<="&EOMONTH(B91,0)) | E91: =SUMIFS('Job Costs'!$I$5:$I$1004,'Job Costs'!$A$5:$A$1004,">="&B91,'Job Costs'!$A$5:$A$1004,"<="&EOMONTH(B91,0))+SUMIFS(Timesheet!$H$5:$H$1004,Timesheet!$A$5:$A$1004,">="&B91,Timesheet!$A$5:$A$1004,"<="&EOMONTH(B91,0))+SUMIFS(Mileage!$I$5:$I$304,Mileage!$A$5:$A$304,">="&B91,Mileage!$A$5:$A$304,"<="&EOMONTH(B91,0)) | F91: =D91-E91 | G91: =SUM($F$84:F91) | H91: =SUMIFS(Timesheet!$E$5:$E$1004,Timesheet!$A$5:$A$1004,">="&B91,Timesheet!$A$5:$A$1004,"<="&EOMONTH(B91,0))
B92: =DATE($E$82,9,1) | C92: =SUMIFS(Invoices!$E$5:$E$204,Invoices!$C$5:$C$204,">="&B92,Invoices!$C$5:$C$204,"<="&EOMONTH(B92,0)) | D92: =SUMIFS(Payments!$D$5:$D$304,Payments!$A$5:$A$304,">="&B92,Payments!$A$5:$A$304,"<="&EOMONTH(B92,0)) | E92: =SUMIFS('Job Costs'!$I$5:$I$1004,'Job Costs'!$A$5:$A$1004,">="&B92,'Job Costs'!$A$5:$A$1004,"<="&EOMONTH(B92,0))+SUMIFS(Timesheet!$H$5:$H$1004,Timesheet!$A$5:$A$1004,">="&B92,Timesheet!$A$5:$A$1004,"<="&EOMONTH(B92,0))+SUMIFS(Mileage!$I$5:$I$304,Mileage!$A$5:$A$304,">="&B92,Mileage!$A$5:$A$304,"<="&EOMONTH(B92,0)) | F92: =D92-E92 | G92: =SUM($F$84:F92) | H92: =SUMIFS(Timesheet!$E$5:$E$1004,Timesheet!$A$5:$A$1004,">="&B92,Timesheet!$A$5:$A$1004,"<="&EOMONTH(B92,0))
B93: =DATE($E$82,10,1) | C93: =SUMIFS(Invoices!$E$5:$E$204,Invoices!$C$5:$C$204,">="&B93,Invoices!$C$5:$C$204,"<="&EOMONTH(B93,0)) | D93: =SUMIFS(Payments!$D$5:$D$304,Payments!$A$5:$A$304,">="&B93,Payments!$A$5:$A$304,"<="&EOMONTH(B93,0)) | E93: =SUMIFS('Job Costs'!$I$5:$I$1004,'Job Costs'!$A$5:$A$1004,">="&B93,'Job Costs'!$A$5:$A$1004,"<="&EOMONTH(B93,0))+SUMIFS(Timesheet!$H$5:$H$1004,Timesheet!$A$5:$A$1004,">="&B93,Timesheet!$A$5:$A$1004,"<="&EOMONTH(B93,0))+SUMIFS(Mileage!$I$5:$I$304,Mileage!$A$5:$A$304,">="&B93,Mileage!$A$5:$A$304,"<="&EOMONTH(B93,0)) | F93: =D93-E93 | G93: =SUM($F$84:F93) | H93: =SUMIFS(Timesheet!$E$5:$E$1004,Timesheet!$A$5:$A$1004,">="&B93,Timesheet!$A$5:$A$1004,"<="&EOMONTH(B93,0))
B94: =DATE($E$82,11,1) | C94: =SUMIFS(Invoices!$E$5:$E$204,Invoices!$C$5:$C$204,">="&B94,Invoices!$C$5:$C$204,"<="&EOMONTH(B94,0)) | D94: =SUMIFS(Payments!$D$5:$D$304,Payments!$A$5:$A$304,">="&B94,Payments!$A$5:$A$304,"<="&EOMONTH(B94,0)) | E94: =SUMIFS('Job Costs'!$I$5:$I$1004,'Job Costs'!$A$5:$A$1004,">="&B94,'Job Costs'!$A$5:$A$1004,"<="&EOMONTH(B94,0))+SUMIFS(Timesheet!$H$5:$H$1004,Timesheet!$A$5:$A$1004,">="&B94,Timesheet!$A$5:$A$1004,"<="&EOMONTH(B94,0))+SUMIFS(Mileage!$I$5:$I$304,Mileage!$A$5:$A$304,">="&B94,Mileage!$A$5:$A$304,"<="&EOMONTH(B94,0)) | F94: =D94-E94 | G94: =SUM($F$84:F94) | H94: =SUMIFS(Timesheet!$E$5:$E$1004,Timesheet!$A$5:$A$1004,">="&B94,Timesheet!$A$5:$A$1004,"<="&EOMONTH(B94,0))
B95: =DATE($E$82,12,1) | C95: =SUMIFS(Invoices!$E$5:$E$204,Invoices!$C$5:$C$204,">="&B95,Invoices!$C$5:$C$204,"<="&EOMONTH(B95,0)) | D95: =SUMIFS(Payments!$D$5:$D$304,Payments!$A$5:$A$304,">="&B95,Payments!$A$5:$A$304,"<="&EOMONTH(B95,0)) | E95: =SUMIFS('Job Costs'!$I$5:$I$1004,'Job Costs'!$A$5:$A$1004,">="&B95,'Job Costs'!$A$5:$A$1004,"<="&EOMONTH(B95,0))+SUMIFS(Timesheet!$H$5:$H$1004,Timesheet!$A$5:$A$1004,">="&B95,Timesheet!$A$5:$A$1004,"<="&EOMONTH(B95,0))+SUMIFS(Mileage!$I$5:$I$304,Mileage!$A$5:$A$304,">="&B95,Mileage!$A$5:$A$304,"<="&EOMONTH(B95,0)) | F95: =D95-E95 | G95: =SUM($F$84:F95) | H95: =SUMIFS(Timesheet!$E$5:$E$1004,Timesheet!$A$5:$A$1004,">="&B95,Timesheet!$A$5:$A$1004,"<="&EOMONTH(B95,0))
B96: TOTAL | C96: =SUM(C84:C95) | D96: =SUM(D84:D95) | E96: =SUM(E84:E95) | F96: =SUM(F84:F95) | H96: =SUM(H84:H95)

Sheet Settings
A1: Settings
A2: Light-blue cells are inputs. Everything here feeds dropdowns, markups, documents and reports on the other sheets.
A4: Company & defaults | B4: Value | E4: Code | F4: Cost code name | G4: Category | I4: Job status | J4: Units | K4: Payment methods | L4: Vendor types
A5: Company name | B5: Your Company LLC | E5: 01 | F5: General conditions / supervision | G5: Labor | I5: Lead | J5: ea | K5: Check | L5: Subcontractor
A6: Address | E6: 02 | F6: Demolition & disposal | G6: Labor | I6: Quoted | J6: hr | K6: ACH / Bank | L6: Supplier
A7: Phone / email | E7: 03 | F7: Site work & excavation | G7: Subcontractor | I7: Approved | J7: day | K7: Card | L7: Equipment rental
A8: License # | E8: 04 | F8: Concrete & foundation | G8: Subcontractor | I8: In Progress | J8: sq ft | K8: Cash | L8: Other
A9: Default contingency % | B9: 0.05 | E9: 05 | F9: Framing labor | G9: Labor | I9: Complete | J9: lin ft | K9: Zelle
A10: Sales tax % | B10: 0 | E10: 06 | F10: Lumber & framing materials | G10: Material | I10: Closed | J10: sq yd | K10: Other
A11: Deposit % of proposal total | B11: 0.3 | E11: 07 | F11: Roofing | G11: Subcontractor | I11: Lost | J11: cu yd
A12: Progress payment % (mid-job) | B12: 0.4 | E12: 08 | F12: Windows & doors | G12: Material | J12: gal
A13: Overdue grace (days past due) | B13: 0 | E13: 09 | F13: Exterior finishes / siding | G13: Subcontractor | J13: box
A14: Reporting / tax year | B14: 2026 | E14: 10 | F14: Plumbing | G14: Subcontractor | J14: lot
A15: Mileage rate ($ per mile) | B15: 0.7 | C15: Check the current IRS standard mileage rate each January. | E15: 11 | F15: Electrical | G15: Subcontractor
A16: Proposal valid for (days) | B16: 30 | E16: 12 | F16: HVAC | G16: Subcontractor
A17: Overhead % of revenue (for net margin) | B17: 0.1 | C17: Used for 'margin after overhead' on the Dashboard and Job Profit Report. | E17: 13 | F17: Insulation & drywall | G17: Subcontractor
A18: Labor burden % (payroll taxes, insurance, added to crew cost) | B18: 0 | C18: Applied on the Timesheet: Labor cost = hours × rate × (1 + burden). | E18: 14 | F18: Interior finish labor | G18: Labor
A19: Sales tax applies to | B19: Material only | C19: Material only = tax on Material lines. All lines = tax on the whole subtotal. | E19: 15 | F19: Paint & wall finishes | G19: Material
E20: 16 | F20: Flooring & tile | G20: Material
A21: Cost category | B21: Default markup % | E21: 17 | F21: Cabinets & countertops | G21: Material
A22: Labor | B22: 0.35 | E22: 18 | F22: Fixtures & appliances | G22: Material
A23: Material | B23: 0.2 | E23: 19 | F23: Equipment rental | G23: Equipment
A24: Subcontractor | B24: 0.15 | E24: 20 | F24: Permits & inspections | G24: Permit/Fee
A25: Equipment | B25: 0.15 | E25: 21 | F25: Dumpster & cleanup | G25: Other
A26: Permit/Fee | B26: 0 | E26: 22 | F26: Fuel & mileage | G26: Other
A27: Other | B27: 0.1 | E27: 23 | F27: Warranty / callbacks | G27: Labor
A28: Markup is applied to cost: Price = Cost × (1 + markup). Override per line on the Estimate. | E28: 24 | F28: Miscellaneous | G28: Other
A29: Document text | B29: Value
A30: Proposal terms | B30: This proposal is valid until the date shown. Work begins on receipt of the deposit. Changes to scope are priced as written change orders before work proceeds. Balance is due on completion.
A31: Invoice payment instructions | B31: Pay by check to the company name above, or by bank transfer. Please reference the invoice number.
A32: Invoice / statement footer | B32: Thank you for your business.
A33: Change order terms | B33: The client authorizes the added work and price above. The revised contract total and any schedule change apply from the date signed.
A34: Proposal exclusions & assumptions | B34: Excludes permits not listed, hazardous-material remediation, structural repairs discovered after demolition, and work outside the described scope. Pricing assumes access to water and power on site.
A35: Logo: on Proposal, Invoice Print, CO Form or Client Statement use Insert → Pictures and place it top-right.

Sheet Clients
A1: Clients
A2: One row per client. Jobs, contract value, collected and balance due are calculated from the Jobs sheet. Print a statement from the Client Statement sheet.
A4: Client | B4: Contact person | C4: Phone | D4: Email | E4: Billing address | F4: Notes | G4: Jobs | H4: Contract value (all jobs) | I4: Collected | J4: Balance due | K4: Check
G5: =IF(A5="","",COUNTIF(Jobs!$B$5:$B$44,A5)) | H5: =IF(A5="","",SUMIFS(Jobs!$K$5:$K$44,Jobs!$B$5:$B$44,A5)) | I5: =IF(A5="","",SUMIFS(Jobs!$R$5:$R$44,Jobs!$B$5:$B$44,A5)) | J5: =IF(A5="","",SUMIFS(Jobs!$S$5:$S$44,Jobs!$B$5:$B$44,A5)) | K5: =IF(A5="","",IF(COUNTIF(Clients!$A$5:$A$104,A5)>1,"Duplicate client",""))
G6: =IF(A6="","",COUNTIF(Jobs!$B$5:$B$44,A6)) | H6: =IF(A6="","",SUMIFS(Jobs!$K$5:$K$44,Jobs!$B$5:$B$44,A6)) | I6: =IF(A6="","",SUMIFS(Jobs!$R$5:$R$44,Jobs!$B$5:$B$44,A6)) | J6: =IF(A6="","",SUMIFS(Jobs!$S$5:$S$44,Jobs!$B$5:$B$44,A6)) | K6: =IF(A6="","",IF(COUNTIF(Clients!$A$5:$A$104,A6)>1,"Duplicate client",""))
G7: =IF(A7="","",COUNTIF(Jobs!$B$5:$B$44,A7)) | H7: =IF(A7="","",SUMIFS(Jobs!$K$5:$K$44,Jobs!$B$5:$B$44,A7)) | I7: =IF(A7="","",SUMIFS(Jobs!$R$5:$R$44,Jobs!$B$5:$B$44,A7)) | J7: =IF(A7="","",SUMIFS(Jobs!$S$5:$S$44,Jobs!$B$5:$B$44,A7)) | K7: =IF(A7="","",IF(COUNTIF(Clients!$A$5:$A$104,A7)>1,"Duplicate client",""))
G8: =IF(A8="","",COUNTIF(Jobs!$B$5:$B$44,A8)) | H8: =IF(A8="","",SUMIFS(Jobs!$K$5:$K$44,Jobs!$B$5:$B$44,A8)) | I8: =IF(A8="","",SUMIFS(Jobs!$R$5:$R$44,Jobs!$B$5:$B$44,A8)) | J8: =IF(A8="","",SUMIFS(Jobs!$S$5:$S$44,Jobs!$B$5:$B$44,A8)) | K8: =IF(A8="","",IF(COUNTIF(Clients!$A$5:$A$104,A8)>1,"Duplicate client",""))
G9: =IF(A9="","",COUNTIF(Jobs!$B$5:$B$44,A9)) | H9: =IF(A9="","",SUMIFS(Jobs!$K$5:$K$44,Jobs!$B$5:$B$44,A9)) | I9: =IF(A9="","",SUMIFS(Jobs!$R$5:$R$44,Jobs!$B$5:$B$44,A9)) | J9: =IF(A9="","",SUMIFS(Jobs!$S$5:$S$44,Jobs!$B$5:$B$44,A9)) | K9: =IF(A9="","",IF(COUNTIF(Clients!$A$5:$A$104,A9)>1,"Duplicate client",""))
G10: =IF(A10="","",COUNTIF(Jobs!$B$5:$B$44,A10)) | H10: =IF(A10="","",SUMIFS(Jobs!$K$5:$K$44,Jobs!$B$5:$B$44,A10)) | I10: =IF(A10="","",SUMIFS(Jobs!$R$5:$R$44,Jobs!$B$5:$B$44,A10)) | J10: =IF(A10="","",SUMIFS(Jobs!$S$5:$S$44,Jobs!$B$5:$B$44,A10)) | K10: =IF(A10="","",IF(COUNTIF(Clients!$A$5:$A$104,A10)>1,"Duplicate client",""))
G11: =IF(A11="","",COUNTIF(Jobs!$B$5:$B$44,A11)) | H11: =IF(A11="","",SUMIFS(Jobs!$K$5:$K$44,Jobs!$B$5:$B$44,A11)) | I11: =IF(A11="","",SUMIFS(Jobs!$R$5:$R$44,Jobs!$B$5:$B$44,A11)) | J11: =IF(A11="","",SUMIFS(Jobs!$S$5:$S$44,Jobs!$B$5:$B$44,A11)) | K11: =IF(A11="","",IF(COUNTIF(Clients!$A$5:$A$104,A11)>1,"Duplicate client",""))
G12: =IF(A12="","",COUNTIF(Jobs!$B$5:$B$44,A12)) | H12: =IF(A12="","",SUMIFS(Jobs!$K$5:$K$44,Jobs!$B$5:$B$44,A12)) | I12: =IF(A12="","",SUMIFS(Jobs!$R$5:$R$44,Jobs!$B$5:$B$44,A12)) | J12: =IF(A12="","",SUMIFS(Jobs!$S$5:$S$44,Jobs!$B$5:$B$44,A12)) | K12: =IF(A12="","",IF(COUNTIF(Clients!$A$5:$A$104,A12)>1,"Duplicate client",""))
G13: =IF(A13="","",COUNTIF(Jobs!$B$5:$B$44,A13)) | H13: =IF(A13="","",SUMIFS(Jobs!$K$5:$K$44,Jobs!$B$5:$B$44,A13)) | I13: =IF(A13="","",SUMIFS(Jobs!$R$5:$R$44,Jobs!$B$5:$B$44,A13)) | J13: =IF(A13="","",SUMIFS(Jobs!$S$5:$S$44,Jobs!$B$5:$B$44,A13)) | K13: =IF(A13="","",IF(COUNTIF(Clients!$A$5:$A$104,A13)>1,"Duplicate client",""))
G14: =IF(A14="","",COUNTIF(Jobs!$B$5:$B$44,A14)) | H14: =IF(A14="","",SUMIFS(Jobs!$K$5:$K$44,Jobs!$B$5:$B$44,A14)) | I14: =IF(A14="","",SUMIFS(Jobs!$R$5:$R$44,Jobs!$B$5:$B$44,A14)) | J14: =IF(A14="","",SUMIFS(Jobs!$S$5:$S$44,Jobs!$B$5:$B$44,A14)) | K14: =IF(A14="","",IF(COUNTIF(Clients!$A$5:$A$104,A14)>1,"Duplicate client",""))
G15: =IF(A15="","",COUNTIF(Jobs!$B$5:$B$44,A15)) | H15: =IF(A15="","",SUMIFS(Jobs!$K$5:$K$44,Jobs!$B$5:$B$44,A15)) | I15: =IF(A15="","",SUMIFS(Jobs!$R$5:$R$44,Jobs!$B$5:$B$44,A15)) | J15: =IF(A15="","",SUMIFS(Jobs!$S$5:$S$44,Jobs!$B$5:$B$44,A15)) | K15: =IF(A15="","",IF(COUNTIF(Clients!$A$5:$A$104,A15)>1,"Duplicate client",""))
G16: =IF(A16="","",COUNTIF(Jobs!$B$5:$B$44,A16)) | H16: =IF(A16="","",SUMIFS(Jobs!$K$5:$K$44,Jobs!$B$5:$B$44,A16)) | I16: =IF(A16="","",SUMIFS(Jobs!$R$5:$R$44,Jobs!$B$5:$B$44,A16)) | J16: =IF(A16="","",SUMIFS(Jobs!$S$5:$S$44,Jobs!$B$5:$B$44,A16)) | K16: =IF(A16="","",IF(COUNTIF(Clients!$A$5:$A$104,A16)>1,"Duplicate client",""))
... G104: =IF(A104="","",COUNTIF(Jobs!$B$5:$B$44,A104)) | H104: =IF(A104="","",SUMIFS(Jobs!$K$5:$K$44,Jobs!$B$5:$B$44,A104)) | I104: =IF(A104="","",SUMIFS(Jobs!$R$5:$R$44,Jobs!$B$5:$B$44,A104)) | J104: =IF(A104="","",SUMIFS(Jobs!$S$5:$S$44,Jobs!$B$5:$B$44,A104)) | K104: =IF(A104="","",IF(COUNTIF(Clients!$A$5:$A$104,A104)>1,"Duplicate client",""))

Sheet Vendors & Crew
A1: Vendors & Crew
A2: Crew (your workers, with cost and bill rates) feeds the Timesheet. Vendors & subs feed Job Costs, insurance alerts and the 1099 review.
A3: CREW
A4: Worker | B4: Role | C4: Cost Rate ($/hr) | D4: Bill Rate ($/hr) | E4: Phone | F4: Hours YTD | G4: Labor Cost YTD | H4: Check | I4: Notes
F5: =IF(A5="","",SUMIFS(Timesheet!$E$5:$E$1004,Timesheet!$B$5:$B$1004,A5,Timesheet!$A$5:$A$1004,">="&DATE(Settings!$B$14,1,1),Timesheet!$A$5:$A$1004,"<="&DATE(Settings!$B$14,12,31))) | G5: =IF(A5="","",SUMIFS(Timesheet!$H$5:$H$1004,Timesheet!$B$5:$B$1004,A5,Timesheet!$A$5:$A$1004,">="&DATE(Settings!$B$14,1,1),Timesheet!$A$5:$A$1004,"<="&DATE(Settings!$B$14,12,31))) | H5: =IF(A5="","",IF(COUNTIF('Vendors & Crew'!$A$5:$A$34,A5)>1,"Duplicate worker",IF(C5="","Missing cost rate","")))
F6: =IF(A6="","",SUMIFS(Timesheet!$E$5:$E$1004,Timesheet!$B$5:$B$1004,A6,Timesheet!$A$5:$A$1004,">="&DATE(Settings!$B$14,1,1),Timesheet!$A$5:$A$1004,"<="&DATE(Settings!$B$14,12,31))) | G6: =IF(A6="","",SUMIFS(Timesheet!$H$5:$H$1004,Timesheet!$B$5:$B$1004,A6,Timesheet!$A$5:$A$1004,">="&DATE(Settings!$B$14,1,1),Timesheet!$A$5:$A$1004,"<="&DATE(Settings!$B$14,12,31))) | H6: =IF(A6="","",IF(COUNTIF('Vendors & Crew'!$A$5:$A$34,A6)>1,"Duplicate worker",IF(C6="","Missing cost rate","")))
F7: =IF(A7="","",SUMIFS(Timesheet!$E$5:$E$1004,Timesheet!$B$5:$B$1004,A7,Timesheet!$A$5:$A$1004,">="&DATE(Settings!$B$14,1,1),Timesheet!$A$5:$A$1004,"<="&DATE(Settings!$B$14,12,31))) | G7: =IF(A7="","",SUMIFS(Timesheet!$H$5:$H$1004,Timesheet!$B$5:$B$1004,A7,Timesheet!$A$5:$A$1004,">="&DATE(Settings!$B$14,1,1),Timesheet!$A$5:$A$1004,"<="&DATE(Settings!$B$14,12,31))) | H7: =IF(A7="","",IF(COUNTIF('Vendors & Crew'!$A$5:$A$34,A7)>1,"Duplicate worker",IF(C7="","Missing cost rate","")))
F8: =IF(A8="","",SUMIFS(Timesheet!$E$5:$E$1004,Timesheet!$B$5:$B$1004,A8,Timesheet!$A$5:$A$1004,">="&DATE(Settings!$B$14,1,1),Timesheet!$A$5:$A$1004,"<="&DATE(Settings!$B$14,12,31))) | G8: =IF(A8="","",SUMIFS(Timesheet!$H$5:$H$1004,Timesheet!$B$5:$B$1004,A8,Timesheet!$A$5:$A$1004,">="&DATE(Settings!$B$14,1,1),Timesheet!$A$5:$A$1004,"<="&DATE(Settings!$B$14,12,31))) | H8: =IF(A8="","",IF(COUNTIF('Vendors & Crew'!$A$5:$A$34,A8)>1,"Duplicate worker",IF(C8="","Missing cost rate","")))
F9: =IF(A9="","",SUMIFS(Timesheet!$E$5:$E$1004,Timesheet!$B$5:$B$1004,A9,Timesheet!$A$5:$A$1004,">="&DATE(Settings!$B$14,1,1),Timesheet!$A$5:$A$1004,"<="&DATE(Settings!$B$14,12,31))) | G9: =IF(A9="","",SUMIFS(Timesheet!$H$5:$H$1004,Timesheet!$B$5:$B$1004,A9,Timesheet!$A$5:$A$1004,">="&DATE(Settings!$B$14,1,1),Timesheet!$A$5:$A$1004,"<="&DATE(Settings!$B$14,12,31))) | H9: =IF(A9="","",IF(COUNTIF('Vendors & Crew'!$A$5:$A$34,A9)>1,"Duplicate worker",IF(C9="","Missing cost rate","")))
F10: =IF(A10="","",SUMIFS(Timesheet!$E$5:$E$1004,Timesheet!$B$5:$B$1004,A10,Timesheet!$A$5:$A$1004,">="&DATE(Settings!$B$14,1,1),Timesheet!$A$5:$A$1004,"<="&DATE(Settings!$B$14,12,31))) | G10: =IF(A10="","",SUMIFS(Timesheet!$H$5:$H$1004,Timesheet!$B$5:$B$1004,A10,Timesheet!$A$5:$A$1004,">="&DATE(Settings!$B$14,1,1),Timesheet!$A$5:$A$1004,"<="&DATE(Settings!$B$14,12,31))) | H10: =IF(A10="","",IF(COUNTIF('Vendors & Crew'!$A$5:$A$34,A10)>1,"Duplicate worker",IF(C10="","Missing cost rate","")))
F11: =IF(A11="","",SUMIFS(Timesheet!$E$5:$E$1004,Timesheet!$B$5:$B$1004,A11,Timesheet!$A$5:$A$1004,">="&DATE(Settings!$B$14,1,1),Timesheet!$A$5:$A$1004,"<="&DATE(Settings!$B$14,12,31))) | G11: =IF(A11="","",SUMIFS(Timesheet!$H$5:$H$1004,Timesheet!$B$5:$B$1004,A11,Timesheet!$A$5:$A$1004,">="&DATE(Settings!$B$14,1,1),Timesheet!$A$5:$A$1004,"<="&DATE(Settings!$B$14,12,31))) | H11: =IF(A11="","",IF(COUNTIF('Vendors & Crew'!$A$5:$A$34,A11)>1,"Duplicate worker",IF(C11="","Missing cost rate","")))
F12: =IF(A12="","",SUMIFS(Timesheet!$E$5:$E$1004,Timesheet!$B$5:$B$1004,A12,Timesheet!$A$5:$A$1004,">="&DATE(Settings!$B$14,1,1),Timesheet!$A$5:$A$1004,"<="&DATE(Settings!$B$14,12,31))) | G12: =IF(A12="","",SUMIFS(Timesheet!$H$5:$H$1004,Timesheet!$B$5:$B$1004,A12,Timesheet!$A$5:$A$1004,">="&DATE(Settings!$B$14,1,1),Timesheet!$A$5:$A$1004,"<="&DATE(Settings!$B$14,12,31))) | H12: =IF(A12="","",IF(COUNTIF('Vendors & Crew'!$A$5:$A$34,A12)>1,"Duplicate worker",IF(C12="","Missing cost rate","")))
F13: =IF(A13="","",SUMIFS(Timesheet!$E$5:$E$1004,Timesheet!$B$5:$B$1004,A13,Timesheet!$A$5:$A$1004,">="&DATE(Settings!$B$14,1,1),Timesheet!$A$5:$A$1004,"<="&DATE(Settings!$B$14,12,31))) | G13: =IF(A13="","",SUMIFS(Timesheet!$H$5:$H$1004,Timesheet!$B$5:$B$1004,A13,Timesheet!$A$5:$A$1004,">="&DATE(Settings!$B$14,1,1),Timesheet!$A$5:$A$1004,"<="&DATE(Settings!$B$14,12,31))) | H13: =IF(A13="","",IF(COUNTIF('Vendors & Crew'!$A$5:$A$34,A13)>1,"Duplicate worker",IF(C13="","Missing cost rate","")))
F14: =IF(A14="","",SUMIFS(Timesheet!$E$5:$E$1004,Timesheet!$B$5:$B$1004,A14,Timesheet!$A$5:$A$1004,">="&DATE(Settings!$B$14,1,1),Timesheet!$A$5:$A$1004,"<="&DATE(Settings!$B$14,12,31))) | G14: =IF(A14="","",SUMIFS(Timesheet!$H$5:$H$1004,Timesheet!$B$5:$B$1004,A14,Timesheet!$A$5:$A$1004,">="&DATE(Settings!$B$14,1,1),Timesheet!$A$5:$A$1004,"<="&DATE(Settings!$B$14,12,31))) | H14: =IF(A14="","",IF(COUNTIF('Vendors & Crew'!$A$5:$A$34,A14)>1,"Duplicate worker",IF(C14="","Missing cost rate","")))
F15: =IF(A15="","",SUMIFS(Timesheet!$E$5:$E$1004,Timesheet!$B$5:$B$1004,A15,Timesheet!$A$5:$A$1004,">="&DATE(Settings!$B$14,1,1),Timesheet!$A$5:$A$1004,"<="&DATE(Settings!$B$14,12,31))) | G15: =IF(A15="","",SUMIFS(Timesheet!$H$5:$H$1004,Timesheet!$B$5:$B$1004,A15,Timesheet!$A$5:$A$1004,">="&DATE(Settings!$B$14,1,1),Timesheet!$A$5:$A$1004,"<="&DATE(Settings!$B$14,12,31))) | H15: =IF(A15="","",IF(COUNTIF('Vendors & Crew'!$A$5:$A$34,A15)>1,"Duplicate worker",IF(C15="","Missing cost rate","")))
F16: =IF(A16="","",SUMIFS(Timesheet!$E$5:$E$1004,Timesheet!$B$5:$B$1004,A16,Timesheet!$A$5:$A$1004,">="&DATE(Settings!$B$14,1,1),Timesheet!$A$5:$A$1004,"<="&DATE(Settings!$B$14,12,31))) | G16: =IF(A16="","",SUMIFS(Timesheet!$H$5:$H$1004,Timesheet!$B$5:$B$1004,A16,Timesheet!$A$5:$A$1004,">="&DATE(Settings!$B$14,1,1),Timesheet!$A$5:$A$1004,"<="&DATE(Settings!$B$14,12,31))) | H16: =IF(A16="","",IF(COUNTIF('Vendors & Crew'!$A$5:$A$34,A16)>1,"Duplicate worker",IF(C16="","Missing cost rate","")))
... F34: =IF(A34="","",SUMIFS(Timesheet!$E$5:$E$1004,Timesheet!$B$5:$B$1004,A34,Timesheet!$A$5:$A$1004,">="&DATE(Settings!$B$14,1,1),Timesheet!$A$5:$A$1004,"<="&DATE(Settings!$B$14,12,31))) | G34: =IF(A34="","",SUMIFS(Timesheet!$H$5:$H$1004,Timesheet!$B$5:$B$1004,A34,Timesheet!$A$5:$A$1004,">="&DATE(Settings!$B$14,1,1),Timesheet!$A$5:$A$1004,"<="&DATE(Settings!$B$14,12,31))) | H34: =IF(A34="","",IF(COUNTIF('Vendors & Crew'!$A$5:$A$34,A34)>1,"Duplicate worker",IF(C34="","Missing cost rate","")))
A39: VENDORS & SUBCONTRACTORS
A40: Vendor / Sub | B40: Type | C40: Trade | D40: Phone | E40: Email | F40: License # | G40: Insurance Expiry | H40: Insurance Status | I40: W-9 on file | J40: 1099-eligible | K40: Paid YTD | L40: Unpaid Balance | M40: 1099 Flag | N40: Check | O40: Notes
H41: =IF(A41="","",IF(G41="","No expiry on file",IF(G41<TODAY(),"EXPIRED",IF(G41-TODAY()<=30,"Expiring soon","OK")))) | K41: =IF(A41="","",SUMIFS('Job Costs'!$I$5:$I$1004,'Job Costs'!$E$5:$E$1004,A41,'Job Costs'!$A$5:$A$1004,">="&DATE(Settings!$B$14,1,1),'Job Costs'!$A$5:$A$1004,"<="&DATE(Settings!$B$14,12,31))) | L41: =IF(A41="","",SUMIFS('Job Costs'!$I$5:$I$1004,'Job Costs'!$E$5:$E$1004,A41,'Job Costs'!$J$5:$J$1004,"No")) | M41: =IF(A41="","",IF(AND(J41="Yes",K41>=600),"Review for 1099","")) | N41: =IF(A41="","",IF(COUNTIF('Vendors & Crew'!$A$41:$A$140,A41)>1,"Duplicate vendor",""))
H42: =IF(A42="","",IF(G42="","No expiry on file",IF(G42<TODAY(),"EXPIRED",IF(G42-TODAY()<=30,"Expiring soon","OK")))) | K42: =IF(A42="","",SUMIFS('Job Costs'!$I$5:$I$1004,'Job Costs'!$E$5:$E$1004,A42,'Job Costs'!$A$5:$A$1004,">="&DATE(Settings!$B$14,1,1),'Job Costs'!$A$5:$A$1004,"<="&DATE(Settings!$B$14,12,31))) | L42: =IF(A42="","",SUMIFS('Job Costs'!$I$5:$I$1004,'Job Costs'!$E$5:$E$1004,A42,'Job Costs'!$J$5:$J$1004,"No")) | M42: =IF(A42="","",IF(AND(J42="Yes",K42>=600),"Review for 1099","")) | N42: =IF(A42="","",IF(COUNTIF('Vendors & Crew'!$A$41:$A$140,A42)>1,"Duplicate vendor",""))
H43: =IF(A43="","",IF(G43="","No expiry on file",IF(G43<TODAY(),"EXPIRED",IF(G43-TODAY()<=30,"Expiring soon","OK")))) | K43: =IF(A43="","",SUMIFS('Job Costs'!$I$5:$I$1004,'Job Costs'!$E$5:$E$1004,A43,'Job Costs'!$A$5:$A$1004,">="&DATE(Settings!$B$14,1,1),'Job Costs'!$A$5:$A$1004,"<="&DATE(Settings!$B$14,12,31))) | L43: =IF(A43="","",SUMIFS('Job Costs'!$I$5:$I$1004,'Job Costs'!$E$5:$E$1004,A43,'Job Costs'!$J$5:$J$1004,"No")) | M43: =IF(A43="","",IF(AND(J43="Yes",K43>=600),"Review for 1099","")) | N43: =IF(A43="","",IF(COUNTIF('Vendors & Crew'!$A$41:$A$140,A43)>1,"Duplicate vendor",""))
H44: =IF(A44="","",IF(G44="","No expiry on file",IF(G44<TODAY(),"EXPIRED",IF(G44-TODAY()<=30,"Expiring soon","OK")))) | K44: =IF(A44="","",SUMIFS('Job Costs'!$I$5:$I$1004,'Job Costs'!$E$5:$E$1004,A44,'Job Costs'!$A$5:$A$1004,">="&DATE(Settings!$B$14,1,1),'Job Costs'!$A$5:$A$1004,"<="&DATE(Settings!$B$14,12,31))) | L44: =IF(A44="","",SUMIFS('Job Costs'!$I$5:$I$1004,'Job Costs'!$E$5:$E$1004,A44,'Job Costs'!$J$5:$J$1004,"No")) | M44: =IF(A44="","",IF(AND(J44="Yes",K44>=600),"Review for 1099","")) | N44: =IF(A44="","",IF(COUNTIF('Vendors & Crew'!$A$41:$A$140,A44)>1,"Duplicate vendor",""))
H45: =IF(A45="","",IF(G45="","No expiry on file",IF(G45<TODAY(),"EXPIRED",IF(G45-TODAY()<=30,"Expiring soon","OK")))) | K45: =IF(A45="","",SUMIFS('Job Costs'!$I$5:$I$1004,'Job Costs'!$E$5:$E$1004,A45,'Job Costs'!$A$5:$A$1004,">="&DATE(Settings!$B$14,1,1),'Job Costs'!$A$5:$A$1004,"<="&DATE(Settings!$B$14,12,31))) | L45: =IF(A45="","",SUMIFS('Job Costs'!$I$5:$I$1004,'Job Costs'!$E$5:$E$1004,A45,'Job Costs'!$J$5:$J$1004,"No")) | M45: =IF(A45="","",IF(AND(J45="Yes",K45>=600),"Review for 1099","")) | N45: =IF(A45="","",IF(COUNTIF('Vendors & Crew'!$A$41:$A$140,A45)>1,"Duplicate vendor",""))
H46: =IF(A46="","",IF(G46="","No expiry on file",IF(G46<TODAY(),"EXPIRED",IF(G46-TODAY()<=30,"Expiring soon","OK")))) | K46: =IF(A46="","",SUMIFS('Job Costs'!$I$5:$I$1004,'Job Costs'!$E$5:$E$1004,A46,'Job Costs'!$A$5:$A$1004,">="&DATE(Settings!$B$14,1,1),'Job Costs'!$A$5:$A$1004,"<="&DATE(Settings!$B$14,12,31))) | L46: =IF(A46="","",SUMIFS('Job Costs'!$I$5:$I$1004,'Job Costs'!$E$5:$E$1004,A46,'Job Costs'!$J$5:$J$1004,"No")) | M46: =IF(A46="","",IF(AND(J46="Yes",K46>=600),"Review for 1099","")) | N46: =IF(A46="","",IF(COUNTIF('Vendors & Crew'!$A$41:$A$140,A46)>1,"Duplicate vendor",""))
H47: =IF(A47="","",IF(G47="","No expiry on file",IF(G47<TODAY(),"EXPIRED",IF(G47-TODAY()<=30,"Expiring soon","OK")))) | K47: =IF(A47="","",SUMIFS('Job Costs'!$I$5:$I$1004,'Job Costs'!$E$5:$E$1004,A47,'Job Costs'!$A$5:$A$1004,">="&DATE(Settings!$B$14,1,1),'Job Costs'!$A$5:$A$1004,"<="&DATE(Settings!$B$14,12,31))) | L47: =IF(A47="","",SUMIFS('Job Costs'!$I$5:$I$1004,'Job Costs'!$E$5:$E$1004,A47,'Job Costs'!$J$5:$J$1004,"No")) | M47: =IF(A47="","",IF(AND(J47="Yes",K47>=600),"Review for 1099","")) | N47: =IF(A47="","",IF(COUNTIF('Vendors & Crew'!$A$41:$A$140,A47)>1,"Duplicate vendor",""))
H48: =IF(A48="","",IF(G48="","No expiry on file",IF(G48<TODAY(),"EXPIRED",IF(G48-TODAY()<=30,"Expiring soon","OK")))) | K48: =IF(A48="","",SUMIFS('Job Costs'!$I$5:$I$1004,'Job Costs'!$E$5:$E$1004,A48,'Job Costs'!$A$5:$A$1004,">="&DATE(Settings!$B$14,1,1),'Job Costs'!$A$5:$A$1004,"<="&DATE(Settings!$B$14,12,31))) | L48: =IF(A48="","",SUMIFS('Job Costs'!$I$5:$I$1004,'Job Costs'!$E$5:$E$1004,A48,'Job Costs'!$J$5:$J$1004,"No")) | M48: =IF(A48="","",IF(AND(J48="Yes",K48>=600),"Review for 1099","")) | N48: =IF(A48="","",IF(COUNTIF('Vendors & Crew'!$A$41:$A$140,A48)>1,"Duplicate vendor",""))
H49: =IF(A49="","",IF(G49="","No expiry on file",IF(G49<TODAY(),"EXPIRED",IF(G49-TODAY()<=30,"Expiring soon","OK")))) | K49: =IF(A49="","",SUMIFS('Job Costs'!$I$5:$I$1004,'Job Costs'!$E$5:$E$1004,A49,'Job Costs'!$A$5:$A$1004,">="&DATE(Settings!$B$14,1,1),'Job Costs'!$A$5:$A$1004,"<="&DATE(Settings!$B$14,12,31))) | L49: =IF(A49="","",SUMIFS('Job Costs'!$I$5:$I$1004,'Job Costs'!$E$5:$E$1004,A49,'Job Costs'!$J$5:$J$1004,"No")) | M49: =IF(A49="","",IF(AND(J49="Yes",K49>=600),"Review for 1099","")) | N49: =IF(A49="","",IF(COUNTIF('Vendors & Crew'!$A$41:$A$140,A49)>1,"Duplicate vendor",""))
H50: =IF(A50="","",IF(G50="","No expiry on file",IF(G50<TODAY(),"EXPIRED",IF(G50-TODAY()<=30,"Expiring soon","OK")))) | K50: =IF(A50="","",SUMIFS('Job Costs'!$I$5:$I$1004,'Job Costs'!$E$5:$E$1004,A50,'Job Costs'!$A$5:$A$1004,">="&DATE(Settings!$B$14,1,1),'Job Costs'!$A$5:$A$1004,"<="&DATE(Settings!$B$14,12,31))) | L50: =IF(A50="","",SUMIFS('Job Costs'!$I$5:$I$1004,'Job Costs'!$E$5:$E$1004,A50,'Job Costs'!$J$5:$J$1004,"No")) | M50: =IF(A50="","",IF(AND(J50="Yes",K50>=600),"Review for 1099","")) | N50: =IF(A50="","",IF(COUNTIF('Vendors & Crew'!$A$41:$A$140,A50)>1,"Duplicate vendor",""))
H51: =IF(A51="","",IF(G51="","No expiry on file",IF(G51<TODAY(),"EXPIRED",IF(G51-TODAY()<=30,"Expiring soon","OK")))) | K51: =IF(A51="","",SUMIFS('Job Costs'!$I$5:$I$1004,'Job Costs'!$E$5:$E$1004,A51,'Job Costs'!$A$5:$A$1004,">="&DATE(Settings!$B$14,1,1),'Job Costs'!$A$5:$A$1004,"<="&DATE(Settings!$B$14,12,31))) | L51: =IF(A51="","",SUMIFS('Job Costs'!$I$5:$I$1004,'Job Costs'!$E$5:$E$1004,A51,'Job Costs'!$J$5:$J$1004,"No")) | M51: =IF(A51="","",IF(AND(J51="Yes",K51>=600),"Review for 1099","")) | N51: =IF(A51="","",IF(COUNTIF('Vendors & Crew'!$A$41:$A$140,A51)>1,"Duplicate vendor",""))
H52: =IF(A52="","",IF(G52="","No expiry on file",IF(G52<TODAY(),"EXPIRED",IF(G52-TODAY()<=30,"Expiring soon","OK")))) | K52: =IF(A52="","",SUMIFS('Job Costs'!$I$5:$I$1004,'Job Costs'!$E$5:$E$1004,A52,'Job Costs'!$A$5:$A$1004,">="&DATE(Settings!$B$14,1,1),'Job Costs'!$A$5:$A$1004,"<="&DATE(Settings!$B$14,12,31))) | L52: =IF(A52="","",SUMIFS('Job Costs'!$I$5:$I$1004,'Job Costs'!$E$5:$E$1004,A52,'Job Costs'!$J$5:$J$1004,"No")) | M52: =IF(A52="","",IF(AND(J52="Yes",K52>=600),"Review for 1099","")) | N52: =IF(A52="","",IF(COUNTIF('Vendors & Crew'!$A$41:$A$140,A52)>1,"Duplicate vendor",""))
... H140: =IF(A140="","",IF(G140="","No expiry on file",IF(G140<TODAY(),"EXPIRED",IF(G140-TODAY()<=30,"Expiring soon","OK")))) | K140: =IF(A140="","",SUMIFS('Job Costs'!$I$5:$I$1004,'Job Costs'!$E$5:$E$1004,A140,'Job Costs'!$A$5:$A$1004,">="&DATE(Settings!$B$14,1,1),'Job Costs'!$A$5:$A$1004,"<="&DATE(Settings!$B$14,12,31))) | L140: =IF(A140="","",SUMIFS('Job Costs'!$I$5:$I$1004,'Job Costs'!$E$5:$E$1004,A140,'Job Costs'!$J$5:$J$1004,"No")) | M140: =IF(A140="","",IF(AND(J140="Yes",K140>=600),"Review for 1099","")) | N140: =IF(A140="","",IF(COUNTIF('Vendors & Crew'!$A$41:$A$140,A140)>1,"Duplicate vendor",""))
A142: 1099 flag is informational only (US vendors paid $600+ in the year and marked eligible). Confirm requirements with your tax professional.

Sheet Cost Library
A1: Cost Library (price book)
A2: Save the items you estimate repeatedly. On the Estimate sheet, pick a Library Item and the unit and unit cost fill in unless you type your own.
A4: Item | B4: Cost Code | C4: Unit | D4: Unit Cost | E4: Category | F4: Used in estimates | G4: Notes
E5: =IF(B5="","",IFERROR(VLOOKUP(B5,Settings!$E$5:$G$28,3,FALSE),"Other")) | F5: =IF(A5="","",COUNTIF(Estimate!$C$5:$C$404,A5))
E6: =IF(B6="","",IFERROR(VLOOKUP(B6,Settings!$E$5:$G$28,3,FALSE),"Other")) | F6: =IF(A6="","",COUNTIF(Estimate!$C$5:$C$404,A6))
E7: =IF(B7="","",IFERROR(VLOOKUP(B7,Settings!$E$5:$G$28,3,FALSE),"Other")) | F7: =IF(A7="","",COUNTIF(Estimate!$C$5:$C$404,A7))
E8: =IF(B8="","",IFERROR(VLOOKUP(B8,Settings!$E$5:$G$28,3,FALSE),"Other")) | F8: =IF(A8="","",COUNTIF(Estimate!$C$5:$C$404,A8))
E9: =IF(B9="","",IFERROR(VLOOKUP(B9,Settings!$E$5:$G$28,3,FALSE),"Other")) | F9: =IF(A9="","",COUNTIF(Estimate!$C$5:$C$404,A9))
E10: =IF(B10="","",IFERROR(VLOOKUP(B10,Settings!$E$5:$G$28,3,FALSE),"Other")) | F10: =IF(A10="","",COUNTIF(Estimate!$C$5:$C$404,A10))
E11: =IF(B11="","",IFERROR(VLOOKUP(B11,Settings!$E$5:$G$28,3,FALSE),"Other")) | F11: =IF(A11="","",COUNTIF(Estimate!$C$5:$C$404,A11))
E12: =IF(B12="","",IFERROR(VLOOKUP(B12,Settings!$E$5:$G$28,3,FALSE),"Other")) | F12: =IF(A12="","",COUNTIF(Estimate!$C$5:$C$404,A12))
E13: =IF(B13="","",IFERROR(VLOOKUP(B13,Settings!$E$5:$G$28,3,FALSE),"Other")) | F13: =IF(A13="","",COUNTIF(Estimate!$C$5:$C$404,A13))
E14: =IF(B14="","",IFERROR(VLOOKUP(B14,Settings!$E$5:$G$28,3,FALSE),"Other")) | F14: =IF(A14="","",COUNTIF(Estimate!$C$5:$C$404,A14))
E15: =IF(B15="","",IFERROR(VLOOKUP(B15,Settings!$E$5:$G$28,3,FALSE),"Other")) | F15: =IF(A15="","",COUNTIF(Estimate!$C$5:$C$404,A15))
E16: =IF(B16="","",IFERROR(VLOOKUP(B16,Settings!$E$5:$G$28,3,FALSE),"Other")) | F16: =IF(A16="","",COUNTIF(Estimate!$C$5:$C$404,A16))
... E204: =IF(B204="","",IFERROR(VLOOKUP(B204,Settings!$E$5:$G$28,3,FALSE),"Other")) | F204: =IF(A204="","",COUNTIF(Estimate!$C$5:$C$404,A204))

Sheet Jobs
A1: Jobs
A2: One row per job. Costs, hours, invoices and payments flow in from the other sheets. Contract Value is optional: leave blank to use the Estimate Price.
A3: ="Suggested next Job ID: J-"&(1000+COUNTA(A5:A44)+1)
A4: Job ID | B4: Client | C4: Job address / description | D4: Status | E4: Start date | F4: Target end | G4: % Complete (manual) | H4: Estimate Price | I4: Contract Value (signed) | J4: Approved Change Orders | K4: Revised Contract | L4: Estimated Cost | M4: Actual Cost to Date | N4: Cost Variance | O4: % of Budget Used | P4: Labor Hours | Q4: Invoiced | R4: Collected | S4: Balance Due | T4: Projected Gross Profit | U4: Projected Margin % | V4: Estimated Margin % | W4: Days to Target | X4: Check | Y4: Notes
H5: =IF($A5="","",SUMIFS(Estimate!$M$5:$M$404,Estimate!$A$5:$A$404,$A5)) | J5: =IF($A5="","",SUMIFS('Change Orders'!$H$5:$H$104,'Change Orders'!$B$5:$B$104,$A5,'Change Orders'!$E$5:$E$104,"Approved")) | K5: =IF($A5="","",IF(I5="",H5,I5)+J5) | L5: =IF($A5="","",SUMIFS(Estimate!$K$5:$K$404,Estimate!$A$5:$A$404,$A5)+SUMIFS('Change Orders'!$G$5:$G$104,'Change Orders'!$B$5:$B$104,$A5,'Change Orders'!$E$5:$E$104,"Approved")) | M5: =IF($A5="","",SUMIFS('Job Costs'!$I$5:$I$1004,'Job Costs'!$B$5:$B$1004,$A5)+SUMIFS(Timesheet!$H$5:$H$1004,Timesheet!$C$5:$C$1004,$A5)+SUMIFS(Mileage!$I$5:$I$304,Mileage!$B$5:$B$304,$A5)) | N5: =IF($A5="","",L5-M5) | O5: =IF($A5="","",IF(L5=0,0,M5/L5)) | P5: =IF($A5="","",SUMIFS(Timesheet!$E$5:$E$1004,Timesheet!$C$5:$C$1004,$A5)+SUMIFS('Job Costs'!$G$5:$G$1004,'Job Costs'!$B$5:$B$1004,$A5,'Job Costs'!$D$5:$D$1004,"Labor")) | Q5: =IF($A5="","",SUMIFS(Invoices!$E$5:$E$204,Invoices!$B$5:$B$204,$A5)) | R5: =IF($A5="","",SUMIFS(Payments!$D$5:$D$304,Payments!$B$5:$B$304,$A5)) | S5: =IF($A5="","",Q5-R5) | T5: =IF($A5="","",K5-MAX(L5,M5)) | U5: =IF($A5="","",IF(K5=0,0,T5/K5)) | V5: =IF($A5="","",IF(K5=0,0,(K5-L5)/K5)) | W5: =IF(OR($A5="",F5="",D5="Complete",D5="Closed",D5="Lost"),"",F5-TODAY()) | X5: =IF($A5="","",IF(COUNTIF(Jobs!$A$5:$A$44,$A5)>1,"Duplicate Job ID",IF(AND(B5<>"",COUNTIF(Clients!$A$5:$A$104,B5)=0),"Client not in Clients sheet",IF(D5="","Missing status",IF(AND(OR(D5="Approved",D5="In Progress"),H5=0,I5=""),"Active job with no estimate or contract value","")))))
H6: =IF($A6="","",SUMIFS(Estimate!$M$5:$M$404,Estimate!$A$5:$A$404,$A6)) | J6: =IF($A6="","",SUMIFS('Change Orders'!$H$5:$H$104,'Change Orders'!$B$5:$B$104,$A6,'Change Orders'!$E$5:$E$104,"Approved")) | K6: =IF($A6="","",IF(I6="",H6,I6)+J6) | L6: =IF($A6="","",SUMIFS(Estimate!$K$5:$K$404,Estimate!$A$5:$A$404,$A6)+SUMIFS('Change Orders'!$G$5:$G$104,'Change Orders'!$B$5:$B$104,$A6,'Change Orders'!$E$5:$E$104,"Approved")) | M6: =IF($A6="","",SUMIFS('Job Costs'!$I$5:$I$1004,'Job Costs'!$B$5:$B$1004,$A6)+SUMIFS(Timesheet!$H$5:$H$1004,Timesheet!$C$5:$C$1004,$A6)+SUMIFS(Mileage!$I$5:$I$304,Mileage!$B$5:$B$304,$A6)) | N6: =IF($A6="","",L6-M6) | O6: =IF($A6="","",IF(L6=0,0,M6/L6)) | P6: =IF($A6="","",SUMIFS(Timesheet!$E$5:$E$1004,Timesheet!$C$5:$C$1004,$A6)+SUMIFS('Job Costs'!$G$5:$G$1004,'Job Costs'!$B$5:$B$1004,$A6,'Job Costs'!$D$5:$D$1004,"Labor")) | Q6: =IF($A6="","",SUMIFS(Invoices!$E$5:$E$204,Invoices!$B$5:$B$204,$A6)) | R6: =IF($A6="","",SUMIFS(Payments!$D$5:$D$304,Payments!$B$5:$B$304,$A6)) | S6: =IF($A6="","",Q6-R6) | T6: =IF($A6="","",K6-MAX(L6,M6)) | U6: =IF($A6="","",IF(K6=0,0,T6/K6)) | V6: =IF($A6="","",IF(K6=0,0,(K6-L6)/K6)) | W6: =IF(OR($A6="",F6="",D6="Complete",D6="Closed",D6="Lost"),"",F6-TODAY()) | X6: =IF($A6="","",IF(COUNTIF(Jobs!$A$5:$A$44,$A6)>1,"Duplicate Job ID",IF(AND(B6<>"",COUNTIF(Clients!$A$5:$A$104,B6)=0),"Client not in Clients sheet",IF(D6="","Missing status",IF(AND(OR(D6="Approved",D6="In Progress"),H6=0,I6=""),"Active job with no estimate or contract value","")))))
H7: =IF($A7="","",SUMIFS(Estimate!$M$5:$M$404,Estimate!$A$5:$A$404,$A7)) | J7: =IF($A7="","",SUMIFS('Change Orders'!$H$5:$H$104,'Change Orders'!$B$5:$B$104,$A7,'Change Orders'!$E$5:$E$104,"Approved")) | K7: =IF($A7="","",IF(I7="",H7,I7)+J7) | L7: =IF($A7="","",SUMIFS(Estimate!$K$5:$K$404,Estimate!$A$5:$A$404,$A7)+SUMIFS('Change Orders'!$G$5:$G$104,'Change Orders'!$B$5:$B$104,$A7,'Change Orders'!$E$5:$E$104,"Approved")) | M7: =IF($A7="","",SUMIFS('Job Costs'!$I$5:$I$1004,'Job Costs'!$B$5:$B$1004,$A7)+SUMIFS(Timesheet!$H$5:$H$1004,Timesheet!$C$5:$C$1004,$A7)+SUMIFS(Mileage!$I$5:$I$304,Mileage!$B$5:$B$304,$A7)) | N7: =IF($A7="","",L7-M7) | O7: =IF($A7="","",IF(L7=0,0,M7/L7)) | P7: =IF($A7="","",SUMIFS(Timesheet!$E$5:$E$1004,Timesheet!$C$5:$C$1004,$A7)+SUMIFS('Job Costs'!$G$5:$G$1004,'Job Costs'!$B$5:$B$1004,$A7,'Job Costs'!$D$5:$D$1004,"Labor")) | Q7: =IF($A7="","",SUMIFS(Invoices!$E$5:$E$204,Invoices!$B$5:$B$204,$A7)) | R7: =IF($A7="","",SUMIFS(Payments!$D$5:$D$304,Payments!$B$5:$B$304,$A7)) | S7: =IF($A7="","",Q7-R7) | T7: =IF($A7="","",K7-MAX(L7,M7)) | U7: =IF($A7="","",IF(K7=0,0,T7/K7)) | V7: =IF($A7="","",IF(K7=0,0,(K7-L7)/K7)) | W7: =IF(OR($A7="",F7="",D7="Complete",D7="Closed",D7="Lost"),"",F7-TODAY()) | X7: =IF($A7="","",IF(COUNTIF(Jobs!$A$5:$A$44,$A7)>1,"Duplicate Job ID",IF(AND(B7<>"",COUNTIF(Clients!$A$5:$A$104,B7)=0),"Client not in Clients sheet",IF(D7="","Missing status",IF(AND(OR(D7="Approved",D7="In Progress"),H7=0,I7=""),"Active job with no estimate or contract value","")))))
H8: =IF($A8="","",SUMIFS(Estimate!$M$5:$M$404,Estimate!$A$5:$A$404,$A8)) | J8: =IF($A8="","",SUMIFS('Change Orders'!$H$5:$H$104,'Change Orders'!$B$5:$B$104,$A8,'Change Orders'!$E$5:$E$104,"Approved")) | K8: =IF($A8="","",IF(I8="",H8,I8)+J8) | L8: =IF($A8="","",SUMIFS(Estimate!$K$5:$K$404,Estimate!$A$5:$A$404,$A8)+SUMIFS('Change Orders'!$G$5:$G$104,'Change Orders'!$B$5:$B$104,$A8,'Change Orders'!$E$5:$E$104,"Approved")) | M8: =IF($A8="","",SUMIFS('Job Costs'!$I$5:$I$1004,'Job Costs'!$B$5:$B$1004,$A8)+SUMIFS(Timesheet!$H$5:$H$1004,Timesheet!$C$5:$C$1004,$A8)+SUMIFS(Mileage!$I$5:$I$304,Mileage!$B$5:$B$304,$A8)) | N8: =IF($A8="","",L8-M8) | O8: =IF($A8="","",IF(L8=0,0,M8/L8)) | P8: =IF($A8="","",SUMIFS(Timesheet!$E$5:$E$1004,Timesheet!$C$5:$C$1004,$A8)+SUMIFS('Job Costs'!$G$5:$G$1004,'Job Costs'!$B$5:$B$1004,$A8,'Job Costs'!$D$5:$D$1004,"Labor")) | Q8: =IF($A8="","",SUMIFS(Invoices!$E$5:$E$204,Invoices!$B$5:$B$204,$A8)) | R8: =IF($A8="","",SUMIFS(Payments!$D$5:$D$304,Payments!$B$5:$B$304,$A8)) | S8: =IF($A8="","",Q8-R8) | T8: =IF($A8="","",K8-MAX(L8,M8)) | U8: =IF($A8="","",IF(K8=0,0,T8/K8)) | V8: =IF($A8="","",IF(K8=0,0,(K8-L8)/K8)) | W8: =IF(OR($A8="",F8="",D8="Complete",D8="Closed",D8="Lost"),"",F8-TODAY()) | X8: =IF($A8="","",IF(COUNTIF(Jobs!$A$5:$A$44,$A8)>1,"Duplicate Job ID",IF(AND(B8<>"",COUNTIF(Clients!$A$5:$A$104,B8)=0),"Client not in Clients sheet",IF(D8="","Missing status",IF(AND(OR(D8="Approved",D8="In Progress"),H8=0,I8=""),"Active job with no estimate or contract value","")))))
H9: =IF($A9="","",SUMIFS(Estimate!$M$5:$M$404,Estimate!$A$5:$A$404,$A9)) | J9: =IF($A9="","",SUMIFS('Change Orders'!$H$5:$H$104,'Change Orders'!$B$5:$B$104,$A9,'Change Orders'!$E$5:$E$104,"Approved")) | K9: =IF($A9="","",IF(I9="",H9,I9)+J9) | L9: =IF($A9="","",SUMIFS(Estimate!$K$5:$K$404,Estimate!$A$5:$A$404,$A9)+SUMIFS('Change Orders'!$G$5:$G$104,'Change Orders'!$B$5:$B$104,$A9,'Change Orders'!$E$5:$E$104,"Approved")) | M9: =IF($A9="","",SUMIFS('Job Costs'!$I$5:$I$1004,'Job Costs'!$B$5:$B$1004,$A9)+SUMIFS(Timesheet!$H$5:$H$1004,Timesheet!$C$5:$C$1004,$A9)+SUMIFS(Mileage!$I$5:$I$304,Mileage!$B$5:$B$304,$A9)) | N9: =IF($A9="","",L9-M9) | O9: =IF($A9="","",IF(L9=0,0,M9/L9)) | P9: =IF($A9="","",SUMIFS(Timesheet!$E$5:$E$1004,Timesheet!$C$5:$C$1004,$A9)+SUMIFS('Job Costs'!$G$5:$G$1004,'Job Costs'!$B$5:$B$1004,$A9,'Job Costs'!$D$5:$D$1004,"Labor")) | Q9: =IF($A9="","",SUMIFS(Invoices!$E$5:$E$204,Invoices!$B$5:$B$204,$A9)) | R9: =IF($A9="","",SUMIFS(Payments!$D$5:$D$304,Payments!$B$5:$B$304,$A9)) | S9: =IF($A9="","",Q9-R9) | T9: =IF($A9="","",K9-MAX(L9,M9)) | U9: =IF($A9="","",IF(K9=0,0,T9/K9)) | V9: =IF($A9="","",IF(K9=0,0,(K9-L9)/K9)) | W9: =IF(OR($A9="",F9="",D9="Complete",D9="Closed",D9="Lost"),"",F9-TODAY()) | X9: =IF($A9="","",IF(COUNTIF(Jobs!$A$5:$A$44,$A9)>1,"Duplicate Job ID",IF(AND(B9<>"",COUNTIF(Clients!$A$5:$A$104,B9)=0),"Client not in Clients sheet",IF(D9="","Missing status",IF(AND(OR(D9="Approved",D9="In Progress"),H9=0,I9=""),"Active job with no estimate or contract value","")))))
H10: =IF($A10="","",SUMIFS(Estimate!$M$5:$M$404,Estimate!$A$5:$A$404,$A10)) | J10: =IF($A10="","",SUMIFS('Change Orders'!$H$5:$H$104,'Change Orders'!$B$5:$B$104,$A10,'Change Orders'!$E$5:$E$104,"Approved")) | K10: =IF($A10="","",IF(I10="",H10,I10)+J10) | L10: =IF($A10="","",SUMIFS(Estimate!$K$5:$K$404,Estimate!$A$5:$A$404,$A10)+SUMIFS('Change Orders'!$G$5:$G$104,'Change Orders'!$B$5:$B$104,$A10,'Change Orders'!$E$5:$E$104,"Approved")) | M10: =IF($A10="","",SUMIFS('Job Costs'!$I$5:$I$1004,'Job Costs'!$B$5:$B$1004,$A10)+SUMIFS(Timesheet!$H$5:$H$1004,Timesheet!$C$5:$C$1004,$A10)+SUMIFS(Mileage!$I$5:$I$304,Mileage!$B$5:$B$304,$A10)) | N10: =IF($A10="","",L10-M10) | O10: =IF($A10="","",IF(L10=0,0,M10/L10)) | P10: =IF($A10="","",SUMIFS(Timesheet!$E$5:$E$1004,Timesheet!$C$5:$C$1004,$A10)+SUMIFS('Job Costs'!$G$5:$G$1004,'Job Costs'!$B$5:$B$1004,$A10,'Job Costs'!$D$5:$D$1004,"Labor")) | Q10: =IF($A10="","",SUMIFS(Invoices!$E$5:$E$204,Invoices!$B$5:$B$204,$A10)) | R10: =IF($A10="","",SUMIFS(Payments!$D$5:$D$304,Payments!$B$5:$B$304,$A10)) | S10: =IF($A10="","",Q10-R10) | T10: =IF($A10="","",K10-MAX(L10,M10)) | U10: =IF($A10="","",IF(K10=0,0,T10/K10)) | V10: =IF($A10="","",IF(K10=0,0,(K10-L10)/K10)) | W10: =IF(OR($A10="",F10="",D10="Complete",D10="Closed",D10="Lost"),"",F10-TODAY()) | X10: =IF($A10="","",IF(COUNTIF(Jobs!$A$5:$A$44,$A10)>1,"Duplicate Job ID",IF(AND(B10<>"",COUNTIF(Clients!$A$5:$A$104,B10)=0),"Client not in Clients sheet",IF(D10="","Missing status",IF(AND(OR(D10="Approved",D10="In Progress"),H10=0,I10=""),"Active job with no estimate or contract value","")))))
H11: =IF($A11="","",SUMIFS(Estimate!$M$5:$M$404,Estimate!$A$5:$A$404,$A11)) | J11: =IF($A11="","",SUMIFS('Change Orders'!$H$5:$H$104,'Change Orders'!$B$5:$B$104,$A11,'Change Orders'!$E$5:$E$104,"Approved")) | K11: =IF($A11="","",IF(I11="",H11,I11)+J11) | L11: =IF($A11="","",SUMIFS(Estimate!$K$5:$K$404,Estimate!$A$5:$A$404,$A11)+SUMIFS('Change Orders'!$G$5:$G$104,'Change Orders'!$B$5:$B$104,$A11,'Change Orders'!$E$5:$E$104,"Approved")) | M11: =IF($A11="","",SUMIFS('Job Costs'!$I$5:$I$1004,'Job Costs'!$B$5:$B$1004,$A11)+SUMIFS(Timesheet!$H$5:$H$1004,Timesheet!$C$5:$C$1004,$A11)+SUMIFS(Mileage!$I$5:$I$304,Mileage!$B$5:$B$304,$A11)) | N11: =IF($A11="","",L11-M11) | O11: =IF($A11="","",IF(L11=0,0,M11/L11)) | P11: =IF($A11="","",SUMIFS(Timesheet!$E$5:$E$1004,Timesheet!$C$5:$C$1004,$A11)+SUMIFS('Job Costs'!$G$5:$G$1004,'Job Costs'!$B$5:$B$1004,$A11,'Job Costs'!$D$5:$D$1004,"Labor")) | Q11: =IF($A11="","",SUMIFS(Invoices!$E$5:$E$204,Invoices!$B$5:$B$204,$A11)) | R11: =IF($A11="","",SUMIFS(Payments!$D$5:$D$304,Payments!$B$5:$B$304,$A11)) | S11: =IF($A11="","",Q11-R11) | T11: =IF($A11="","",K11-MAX(L11,M11)) | U11: =IF($A11="","",IF(K11=0,0,T11/K11)) | V11: =IF($A11="","",IF(K11=0,0,(K11-L11)/K11)) | W11: =IF(OR($A11="",F11="",D11="Complete",D11="Closed",D11="Lost"),"",F11-TODAY()) | X11: =IF($A11="","",IF(COUNTIF(Jobs!$A$5:$A$44,$A11)>1,"Duplicate Job ID",IF(AND(B11<>"",COUNTIF(Clients!$A$5:$A$104,B11)=0),"Client not in Clients sheet",IF(D11="","Missing status",IF(AND(OR(D11="Approved",D11="In Progress"),H11=0,I11=""),"Active job with no estimate or contract value","")))))
H12: =IF($A12="","",SUMIFS(Estimate!$M$5:$M$404,Estimate!$A$5:$A$404,$A12)) | J12: =IF($A12="","",SUMIFS('Change Orders'!$H$5:$H$104,'Change Orders'!$B$5:$B$104,$A12,'Change Orders'!$E$5:$E$104,"Approved")) | K12: =IF($A12="","",IF(I12="",H12,I12)+J12) | L12: =IF($A12="","",SUMIFS(Estimate!$K$5:$K$404,Estimate!$A$5:$A$404,$A12)+SUMIFS('Change Orders'!$G$5:$G$104,'Change Orders'!$B$5:$B$104,$A12,'Change Orders'!$E$5:$E$104,"Approved")) | M12: =IF($A12="","",SUMIFS('Job Costs'!$I$5:$I$1004,'Job Costs'!$B$5:$B$1004,$A12)+SUMIFS(Timesheet!$H$5:$H$1004,Timesheet!$C$5:$C$1004,$A12)+SUMIFS(Mileage!$I$5:$I$304,Mileage!$B$5:$B$304,$A12)) | N12: =IF($A12="","",L12-M12) | O12: =IF($A12="","",IF(L12=0,0,M12/L12)) | P12: =IF($A12="","",SUMIFS(Timesheet!$E$5:$E$1004,Timesheet!$C$5:$C$1004,$A12)+SUMIFS('Job Costs'!$G$5:$G$1004,'Job Costs'!$B$5:$B$1004,$A12,'Job Costs'!$D$5:$D$1004,"Labor")) | Q12: =IF($A12="","",SUMIFS(Invoices!$E$5:$E$204,Invoices!$B$5:$B$204,$A12)) | R12: =IF($A12="","",SUMIFS(Payments!$D$5:$D$304,Payments!$B$5:$B$304,$A12)) | S12: =IF($A12="","",Q12-R12) | T12: =IF($A12="","",K12-MAX(L12,M12)) | U12: =IF($A12="","",IF(K12=0,0,T12/K12)) | V12: =IF($A12="","",IF(K12=0,0,(K12-L12)/K12)) | W12: =IF(OR($A12="",F12="",D12="Complete",D12="Closed",D12="Lost"),"",F12-TODAY()) | X12: =IF($A12="","",IF(COUNTIF(Jobs!$A$5:$A$44,$A12)>1,"Duplicate Job ID",IF(AND(B12<>"",COUNTIF(Clients!$A$5:$A$104,B12)=0),"Client not in Clients sheet",IF(D12="","Missing status",IF(AND(OR(D12="Approved",D12="In Progress"),H12=0,I12=""),"Active job with no estimate or contract value","")))))
H13: =IF($A13="","",SUMIFS(Estimate!$M$5:$M$404,Estimate!$A$5:$A$404,$A13)) | J13: =IF($A13="","",SUMIFS('Change Orders'!$H$5:$H$104,'Change Orders'!$B$5:$B$104,$A13,'Change Orders'!$E$5:$E$104,"Approved")) | K13: =IF($A13="","",IF(I13="",H13,I13)+J13) | L13: =IF($A13="","",SUMIFS(Estimate!$K$5:$K$404,Estimate!$A$5:$A$404,$A13)+SUMIFS('Change Orders'!$G$5:$G$104,'Change Orders'!$B$5:$B$104,$A13,'Change Orders'!$E$5:$E$104,"Approved")) | M13: =IF($A13="","",SUMIFS('Job Costs'!$I$5:$I$1004,'Job Costs'!$B$5:$B$1004,$A13)+SUMIFS(Timesheet!$H$5:$H$1004,Timesheet!$C$5:$C$1004,$A13)+SUMIFS(Mileage!$I$5:$I$304,Mileage!$B$5:$B$304,$A13)) | N13: =IF($A13="","",L13-M13) | O13: =IF($A13="","",IF(L13=0,0,M13/L13)) | P13: =IF($A13="","",SUMIFS(Timesheet!$E$5:$E$1004,Timesheet!$C$5:$C$1004,$A13)+SUMIFS('Job Costs'!$G$5:$G$1004,'Job Costs'!$B$5:$B$1004,$A13,'Job Costs'!$D$5:$D$1004,"Labor")) | Q13: =IF($A13="","",SUMIFS(Invoices!$E$5:$E$204,Invoices!$B$5:$B$204,$A13)) | R13: =IF($A13="","",SUMIFS(Payments!$D$5:$D$304,Payments!$B$5:$B$304,$A13)) | S13: =IF($A13="","",Q13-R13) | T13: =IF($A13="","",K13-MAX(L13,M13)) | U13: =IF($A13="","",IF(K13=0,0,T13/K13)) | V13: =IF($A13="","",IF(K13=0,0,(K13-L13)/K13)) | W13: =IF(OR($A13="",F13="",D13="Complete",D13="Closed",D13="Lost"),"",F13-TODAY()) | X13: =IF($A13="","",IF(COUNTIF(Jobs!$A$5:$A$44,$A13)>1,"Duplicate Job ID",IF(AND(B13<>"",COUNTIF(Clients!$A$5:$A$104,B13)=0),"Client not in Clients sheet",IF(D13="","Missing status",IF(AND(OR(D13="Approved",D13="In Progress"),H13=0,I13=""),"Active job with no estimate or contract value","")))))
H14: =IF($A14="","",SUMIFS(Estimate!$M$5:$M$404,Estimate!$A$5:$A$404,$A14)) | J14: =IF($A14="","",SUMIFS('Change Orders'!$H$5:$H$104,'Change Orders'!$B$5:$B$104,$A14,'Change Orders'!$E$5:$E$104,"Approved")) | K14: =IF($A14="","",IF(I14="",H14,I14)+J14) | L14: =IF($A14="","",SUMIFS(Estimate!$K$5:$K$404,Estimate!$A$5:$A$404,$A14)+SUMIFS('Change Orders'!$G$5:$G$104,'Change Orders'!$B$5:$B$104,$A14,'Change Orders'!$E$5:$E$104,"Approved")) | M14: =IF($A14="","",SUMIFS('Job Costs'!$I$5:$I$1004,'Job Costs'!$B$5:$B$1004,$A14)+SUMIFS(Timesheet!$H$5:$H$1004,Timesheet!$C$5:$C$1004,$A14)+SUMIFS(Mileage!$I$5:$I$304,Mileage!$B$5:$B$304,$A14)) | N14: =IF($A14="","",L14-M14) | O14: =IF($A14="","",IF(L14=0,0,M14/L14)) | P14: =IF($A14="","",SUMIFS(Timesheet!$E$5:$E$1004,Timesheet!$C$5:$C$1004,$A14)+SUMIFS('Job Costs'!$G$5:$G$1004,'Job Costs'!$B$5:$B$1004,$A14,'Job Costs'!$D$5:$D$1004,"Labor")) | Q14: =IF($A14="","",SUMIFS(Invoices!$E$5:$E$204,Invoices!$B$5:$B$204,$A14)) | R14: =IF($A14="","",SUMIFS(Payments!$D$5:$D$304,Payments!$B$5:$B$304,$A14)) | S14: =IF($A14="","",Q14-R14) | T14: =IF($A14="","",K14-MAX(L14,M14)) | U14: =IF($A14="","",IF(K14=0,0,T14/K14)) | V14: =IF($A14="","",IF(K14=0,0,(K14-L14)/K14)) | W14: =IF(OR($A14="",F14="",D14="Complete",D14="Closed",D14="Lost"),"",F14-TODAY()) | X14: =IF($A14="","",IF(COUNTIF(Jobs!$A$5:$A$44,$A14)>1,"Duplicate Job ID",IF(AND(B14<>"",COUNTIF(Clients!$A$5:$A$104,B14)=0),"Client not in Clients sheet",IF(D14="","Missing status",IF(AND(OR(D14="Approved",D14="In Progress"),H14=0,I14=""),"Active job with no estimate or contract value","")))))
H15: =IF($A15="","",SUMIFS(Estimate!$M$5:$M$404,Estimate!$A$5:$A$404,$A15)) | J15: =IF($A15="","",SUMIFS('Change Orders'!$H$5:$H$104,'Change Orders'!$B$5:$B$104,$A15,'Change Orders'!$E$5:$E$104,"Approved")) | K15: =IF($A15="","",IF(I15="",H15,I15)+J15) | L15: =IF($A15="","",SUMIFS(Estimate!$K$5:$K$404,Estimate!$A$5:$A$404,$A15)+SUMIFS('Change Orders'!$G$5:$G$104,'Change Orders'!$B$5:$B$104,$A15,'Change Orders'!$E$5:$E$104,"Approved")) | M15: =IF($A15="","",SUMIFS('Job Costs'!$I$5:$I$1004,'Job Costs'!$B$5:$B$1004,$A15)+SUMIFS(Timesheet!$H$5:$H$1004,Timesheet!$C$5:$C$1004,$A15)+SUMIFS(Mileage!$I$5:$I$304,Mileage!$B$5:$B$304,$A15)) | N15: =IF($A15="","",L15-M15) | O15: =IF($A15="","",IF(L15=0,0,M15/L15)) | P15: =IF($A15="","",SUMIFS(Timesheet!$E$5:$E$1004,Timesheet!$C$5:$C$1004,$A15)+SUMIFS('Job Costs'!$G$5:$G$1004,'Job Costs'!$B$5:$B$1004,$A15,'Job Costs'!$D$5:$D$1004,"Labor")) | Q15: =IF($A15="","",SUMIFS(Invoices!$E$5:$E$204,Invoices!$B$5:$B$204,$A15)) | R15: =IF($A15="","",SUMIFS(Payments!$D$5:$D$304,Payments!$B$5:$B$304,$A15)) | S15: =IF($A15="","",Q15-R15) | T15: =IF($A15="","",K15-MAX(L15,M15)) | U15: =IF($A15="","",IF(K15=0,0,T15/K15)) | V15: =IF($A15="","",IF(K15=0,0,(K15-L15)/K15)) | W15: =IF(OR($A15="",F15="",D15="Complete",D15="Closed",D15="Lost"),"",F15-TODAY()) | X15: =IF($A15="","",IF(COUNTIF(Jobs!$A$5:$A$44,$A15)>1,"Duplicate Job ID",IF(AND(B15<>"",COUNTIF(Clients!$A$5:$A$104,B15)=0),"Client not in Clients sheet",IF(D15="","Missing status",IF(AND(OR(D15="Approved",D15="In Progress"),H15=0,I15=""),"Active job with no estimate or contract value","")))))
H16: =IF($A16="","",SUMIFS(Estimate!$M$5:$M$404,Estimate!$A$5:$A$404,$A16)) | J16: =IF($A16="","",SUMIFS('Change Orders'!$H$5:$H$104,'Change Orders'!$B$5:$B$104,$A16,'Change Orders'!$E$5:$E$104,"Approved")) | K16: =IF($A16="","",IF(I16="",H16,I16)+J16) | L16: =IF($A16="","",SUMIFS(Estimate!$K$5:$K$404,Estimate!$A$5:$A$404,$A16)+SUMIFS('Change Orders'!$G$5:$G$104,'Change Orders'!$B$5:$B$104,$A16,'Change Orders'!$E$5:$E$104,"Approved")) | M16: =IF($A16="","",SUMIFS('Job Costs'!$I$5:$I$1004,'Job Costs'!$B$5:$B$1004,$A16)+SUMIFS(Timesheet!$H$5:$H$1004,Timesheet!$C$5:$C$1004,$A16)+SUMIFS(Mileage!$I$5:$I$304,Mileage!$B$5:$B$304,$A16)) | N16: =IF($A16="","",L16-M16) | O16: =IF($A16="","",IF(L16=0,0,M16/L16)) | P16: =IF($A16="","",SUMIFS(Timesheet!$E$5:$E$1004,Timesheet!$C$5:$C$1004,$A16)+SUMIFS('Job Costs'!$G$5:$G$1004,'Job Costs'!$B$5:$B$1004,$A16,'Job Costs'!$D$5:$D$1004,"Labor")) | Q16: =IF($A16="","",SUMIFS(Invoices!$E$5:$E$204,Invoices!$B$5:$B$204,$A16)) | R16: =IF($A16="","",SUMIFS(Payments!$D$5:$D$304,Payments!$B$5:$B$304,$A16)) | S16: =IF($A16="","",Q16-R16) | T16: =IF($A16="","",K16-MAX(L16,M16)) | U16: =IF($A16="","",IF(K16=0,0,T16/K16)) | V16: =IF($A16="","",IF(K16=0,0,(K16-L16)/K16)) | W16: =IF(OR($A16="",F16="",D16="Complete",D16="Closed",D16="Lost"),"",F16-TODAY()) | X16: =IF($A16="","",IF(COUNTIF(Jobs!$A$5:$A$44,$A16)>1,"Duplicate Job ID",IF(AND(B16<>"",COUNTIF(Clients!$A$5:$A$104,B16)=0),"Client not in Clients sheet",IF(D16="","Missing status",IF(AND(OR(D16="Approved",D16="In Progress"),H16=0,I16=""),"Active job with no estimate or contract value","")))))
... H44: =IF($A44="","",SUMIFS(Estimate!$M$5:$M$404,Estimate!$A$5:$A$404,$A44)) | J44: =IF($A44="","",SUMIFS('Change Orders'!$H$5:$H$104,'Change Orders'!$B$5:$B$104,$A44,'Change Orders'!$E$5:$E$104,"Approved")) | K44: =IF($A44="","",IF(I44="",H44,I44)+J44) | L44: =IF($A44="","",SUMIFS(Estimate!$K$5:$K$404,Estimate!$A$5:$A$404,$A44)+SUMIFS('Change Orders'!$G$5:$G$104,'Change Orders'!$B$5:$B$104,$A44,'Change Orders'!$E$5:$E$104,"Approved")) | M44: =IF($A44="","",SUMIFS('Job Costs'!$I$5:$I$1004,'Job Costs'!$B$5:$B$1004,$A44)+SUMIFS(Timesheet!$H$5:$H$1004,Timesheet!$C$5:$C$1004,$A44)+SUMIFS(Mileage!$I$5:$I$304,Mileage!$B$5:$B$304,$A44)) | N44: =IF($A44="","",L44-M44) | O44: =IF($A44="","",IF(L44=0,0,M44/L44)) | P44: =IF($A44="","",SUMIFS(Timesheet!$E$5:$E$1004,Timesheet!$C$5:$C$1004,$A44)+SUMIFS('Job Costs'!$G$5:$G$1004,'Job Costs'!$B$5:$B$1004,$A44,'Job Costs'!$D$5:$D$1004,"Labor")) | Q44: =IF($A44="","",SUMIFS(Invoices!$E$5:$E$204,Invoices!$B$5:$B$204,$A44)) | R44: =IF($A44="","",SUMIFS(Payments!$D$5:$D$304,Payments!$B$5:$B$304,$A44)) | S44: =IF($A44="","",Q44-R44) | T44: =IF($A44="","",K44-MAX(L44,M44)) | U44: =IF($A44="","",IF(K44=0,0,T44/K44)) | V44: =IF($A44="","",IF(K44=0,0,(K44-L44)/K44)) | W44: =IF(OR($A44="",F44="",D44="Complete",D44="Closed",D44="Lost"),"",F44-TODAY()) | X44: =IF($A44="","",IF(COUNTIF(Jobs!$A$5:$A$44,$A44)>1,"Duplicate Job ID",IF(AND(B44<>"",COUNTIF(Clients!$A$5:$A$104,B44)=0),"Client not in Clients sheet",IF(D44="","Missing status",IF(AND(OR(D44="Approved",D44="In Progress"),H44=0,I44=""),"Active job with no estimate or contract value","")))))
A45: TOTAL | H45: =SUM(H5:H44) | I45: =SUM(I5:I44) | J45: =SUM(J5:J44) | K45: =SUM(K5:K44) | L45: =SUM(L5:L44) | M45: =SUM(M5:M44) | N45: =SUM(N5:N44) | O45: =IF(L45=0,0,M45/L45) | P45: =SUM(P5:P44) | Q45: =SUM(Q5:Q44) | R45: =SUM(R5:R44) | S45: =SUM(S5:S44) | T45: =SUM(T5:T44) | U45: =IF(K45=0,0,T45/K45) | V45: =IF(K45=0,0,(K45-L45)/K45)

Sheet Estimate
A1: Estimate
A2: One line per item. Pick a Cost Code (drives category and markup) and optionally a Library Item (fills unit and unit cost unless you type your own).
A4: Job ID | B4: Cost Code | C4: Library Item | D4: Description | E4: Qty | F4: Unit | G4: Unit Cost | H4: Category | I4: Unit Cost Used | J4: Unit Used | K4: Est. Cost | L4: Markup Override | M4: Price to Client | N4: Markup Used | O4: Proposal Line # | P4: Check | Q4: Notes
H5: =IF(B5="","",IFERROR(VLOOKUP(B5,Settings!$E$5:$G$28,3,FALSE),"Other")) | I5: =IF($A5="","",IF(G5<>"",G5,IFERROR(VLOOKUP(C5,'Cost Library'!$A$5:$D$204,4,FALSE),0))) | J5: =IF($A5="","",IF(F5<>"",F5,IFERROR(VLOOKUP(C5,'Cost Library'!$A$5:$D$204,3,FALSE),""))) | K5: =IF($A5="","",E5*I5) | M5: =IF($A5="","",K5*(1+N5)) | N5: =IF($A5="","",IF(L5="",IFERROR(VLOOKUP(H5,Settings!$A$22:$B$27,2,FALSE),0),L5)) | O5: =IF(AND($A5<>"",$A5=Proposal!$I$2),COUNTIF($A$5:$A5,Proposal!$I$2),"") | P5: =IF($A5="","",IF(COUNTIF(Jobs!$A$5:$A$44,$A5)=0,"Unknown Job ID",IF(B5="","Missing cost code",IF(COUNTIF(Settings!$E$5:$E$28,B5)=0,"Unknown cost code",IF(AND(G5="",C5=""),"No unit cost",IF(E5="","Missing qty",""))))))
H6: =IF(B6="","",IFERROR(VLOOKUP(B6,Settings!$E$5:$G$28,3,FALSE),"Other")) | I6: =IF($A6="","",IF(G6<>"",G6,IFERROR(VLOOKUP(C6,'Cost Library'!$A$5:$D$204,4,FALSE),0))) | J6: =IF($A6="","",IF(F6<>"",F6,IFERROR(VLOOKUP(C6,'Cost Library'!$A$5:$D$204,3,FALSE),""))) | K6: =IF($A6="","",E6*I6) | M6: =IF($A6="","",K6*(1+N6)) | N6: =IF($A6="","",IF(L6="",IFERROR(VLOOKUP(H6,Settings!$A$22:$B$27,2,FALSE),0),L6)) | O6: =IF(AND($A6<>"",$A6=Proposal!$I$2),COUNTIF($A$5:$A6,Proposal!$I$2),"") | P6: =IF($A6="","",IF(COUNTIF(Jobs!$A$5:$A$44,$A6)=0,"Unknown Job ID",IF(B6="","Missing cost code",IF(COUNTIF(Settings!$E$5:$E$28,B6)=0,"Unknown cost code",IF(AND(G6="",C6=""),"No unit cost",IF(E6="","Missing qty",""))))))
H7: =IF(B7="","",IFERROR(VLOOKUP(B7,Settings!$E$5:$G$28,3,FALSE),"Other")) | I7: =IF($A7="","",IF(G7<>"",G7,IFERROR(VLOOKUP(C7,'Cost Library'!$A$5:$D$204,4,FALSE),0))) | J7: =IF($A7="","",IF(F7<>"",F7,IFERROR(VLOOKUP(C7,'Cost Library'!$A$5:$D$204,3,FALSE),""))) | K7: =IF($A7="","",E7*I7) | M7: =IF($A7="","",K7*(1+N7)) | N7: =IF($A7="","",IF(L7="",IFERROR(VLOOKUP(H7,Settings!$A$22:$B$27,2,FALSE),0),L7)) | O7: =IF(AND($A7<>"",$A7=Proposal!$I$2),COUNTIF($A$5:$A7,Proposal!$I$2),"") | P7: =IF($A7="","",IF(COUNTIF(Jobs!$A$5:$A$44,$A7)=0,"Unknown Job ID",IF(B7="","Missing cost code",IF(COUNTIF(Settings!$E$5:$E$28,B7)=0,"Unknown cost code",IF(AND(G7="",C7=""),"No unit cost",IF(E7="","Missing qty",""))))))
H8: =IF(B8="","",IFERROR(VLOOKUP(B8,Settings!$E$5:$G$28,3,FALSE),"Other")) | I8: =IF($A8="","",IF(G8<>"",G8,IFERROR(VLOOKUP(C8,'Cost Library'!$A$5:$D$204,4,FALSE),0))) | J8: =IF($A8="","",IF(F8<>"",F8,IFERROR(VLOOKUP(C8,'Cost Library'!$A$5:$D$204,3,FALSE),""))) | K8: =IF($A8="","",E8*I8) | M8: =IF($A8="","",K8*(1+N8)) | N8: =IF($A8="","",IF(L8="",IFERROR(VLOOKUP(H8,Settings!$A$22:$B$27,2,FALSE),0),L8)) | O8: =IF(AND($A8<>"",$A8=Proposal!$I$2),COUNTIF($A$5:$A8,Proposal!$I$2),"") | P8: =IF($A8="","",IF(COUNTIF(Jobs!$A$5:$A$44,$A8)=0,"Unknown Job ID",IF(B8="","Missing cost code",IF(COUNTIF(Settings!$E$5:$E$28,B8)=0,"Unknown cost code",IF(AND(G8="",C8=""),"No unit cost",IF(E8="","Missing qty",""))))))
H9: =IF(B9="","",IFERROR(VLOOKUP(B9,Settings!$E$5:$G$28,3,FALSE),"Other")) | I9: =IF($A9="","",IF(G9<>"",G9,IFERROR(VLOOKUP(C9,'Cost Library'!$A$5:$D$204,4,FALSE),0))) | J9: =IF($A9="","",IF(F9<>"",F9,IFERROR(VLOOKUP(C9,'Cost Library'!$A$5:$D$204,3,FALSE),""))) | K9: =IF($A9="","",E9*I9) | M9: =IF($A9="","",K9*(1+N9)) | N9: =IF($A9="","",IF(L9="",IFERROR(VLOOKUP(H9,Settings!$A$22:$B$27,2,FALSE),0),L9)) | O9: =IF(AND($A9<>"",$A9=Proposal!$I$2),COUNTIF($A$5:$A9,Proposal!$I$2),"") | P9: =IF($A9="","",IF(COUNTIF(Jobs!$A$5:$A$44,$A9)=0,"Unknown Job ID",IF(B9="","Missing cost code",IF(COUNTIF(Settings!$E$5:$E$28,B9)=0,"Unknown cost code",IF(AND(G9="",C9=""),"No unit cost",IF(E9="","Missing qty",""))))))
H10: =IF(B10="","",IFERROR(VLOOKUP(B10,Settings!$E$5:$G$28,3,FALSE),"Other")) | I10: =IF($A10="","",IF(G10<>"",G10,IFERROR(VLOOKUP(C10,'Cost Library'!$A$5:$D$204,4,FALSE),0))) | J10: =IF($A10="","",IF(F10<>"",F10,IFERROR(VLOOKUP(C10,'Cost Library'!$A$5:$D$204,3,FALSE),""))) | K10: =IF($A10="","",E10*I10) | M10: =IF($A10="","",K10*(1+N10)) | N10: =IF($A10="","",IF(L10="",IFERROR(VLOOKUP(H10,Settings!$A$22:$B$27,2,FALSE),0),L10)) | O10: =IF(AND($A10<>"",$A10=Proposal!$I$2),COUNTIF($A$5:$A10,Proposal!$I$2),"") | P10: =IF($A10="","",IF(COUNTIF(Jobs!$A$5:$A$44,$A10)=0,"Unknown Job ID",IF(B10="","Missing cost code",IF(COUNTIF(Settings!$E$5:$E$28,B10)=0,"Unknown cost code",IF(AND(G10="",C10=""),"No unit cost",IF(E10="","Missing qty",""))))))
H11: =IF(B11="","",IFERROR(VLOOKUP(B11,Settings!$E$5:$G$28,3,FALSE),"Other")) | I11: =IF($A11="","",IF(G11<>"",G11,IFERROR(VLOOKUP(C11,'Cost Library'!$A$5:$D$204,4,FALSE),0))) | J11: =IF($A11="","",IF(F11<>"",F11,IFERROR(VLOOKUP(C11,'Cost Library'!$A$5:$D$204,3,FALSE),""))) | K11: =IF($A11="","",E11*I11) | M11: =IF($A11="","",K11*(1+N11)) | N11: =IF($A11="","",IF(L11="",IFERROR(VLOOKUP(H11,Settings!$A$22:$B$27,2,FALSE),0),L11)) | O11: =IF(AND($A11<>"",$A11=Proposal!$I$2),COUNTIF($A$5:$A11,Proposal!$I$2),"") | P11: =IF($A11="","",IF(COUNTIF(Jobs!$A$5:$A$44,$A11)=0,"Unknown Job ID",IF(B11="","Missing cost code",IF(COUNTIF(Settings!$E$5:$E$28,B11)=0,"Unknown cost code",IF(AND(G11="",C11=""),"No unit cost",IF(E11="","Missing qty",""))))))
H12: =IF(B12="","",IFERROR(VLOOKUP(B12,Settings!$E$5:$G$28,3,FALSE),"Other")) | I12: =IF($A12="","",IF(G12<>"",G12,IFERROR(VLOOKUP(C12,'Cost Library'!$A$5:$D$204,4,FALSE),0))) | J12: =IF($A12="","",IF(F12<>"",F12,IFERROR(VLOOKUP(C12,'Cost Library'!$A$5:$D$204,3,FALSE),""))) | K12: =IF($A12="","",E12*I12) | M12: =IF($A12="","",K12*(1+N12)) | N12: =IF($A12="","",IF(L12="",IFERROR(VLOOKUP(H12,Settings!$A$22:$B$27,2,FALSE),0),L12)) | O12: =IF(AND($A12<>"",$A12=Proposal!$I$2),COUNTIF($A$5:$A12,Proposal!$I$2),"") | P12: =IF($A12="","",IF(COUNTIF(Jobs!$A$5:$A$44,$A12)=0,"Unknown Job ID",IF(B12="","Missing cost code",IF(COUNTIF(Settings!$E$5:$E$28,B12)=0,"Unknown cost code",IF(AND(G12="",C12=""),"No unit cost",IF(E12="","Missing qty",""))))))
H13: =IF(B13="","",IFERROR(VLOOKUP(B13,Settings!$E$5:$G$28,3,FALSE),"Other")) | I13: =IF($A13="","",IF(G13<>"",G13,IFERROR(VLOOKUP(C13,'Cost Library'!$A$5:$D$204,4,FALSE),0))) | J13: =IF($A13="","",IF(F13<>"",F13,IFERROR(VLOOKUP(C13,'Cost Library'!$A$5:$D$204,3,FALSE),""))) | K13: =IF($A13="","",E13*I13) | M13: =IF($A13="","",K13*(1+N13)) | N13: =IF($A13="","",IF(L13="",IFERROR(VLOOKUP(H13,Settings!$A$22:$B$27,2,FALSE),0),L13)) | O13: =IF(AND($A13<>"",$A13=Proposal!$I$2),COUNTIF($A$5:$A13,Proposal!$I$2),"") | P13: =IF($A13="","",IF(COUNTIF(Jobs!$A$5:$A$44,$A13)=0,"Unknown Job ID",IF(B13="","Missing cost code",IF(COUNTIF(Settings!$E$5:$E$28,B13)=0,"Unknown cost code",IF(AND(G13="",C13=""),"No unit cost",IF(E13="","Missing qty",""))))))
H14: =IF(B14="","",IFERROR(VLOOKUP(B14,Settings!$E$5:$G$28,3,FALSE),"Other")) | I14: =IF($A14="","",IF(G14<>"",G14,IFERROR(VLOOKUP(C14,'Cost Library'!$A$5:$D$204,4,FALSE),0))) | J14: =IF($A14="","",IF(F14<>"",F14,IFERROR(VLOOKUP(C14,'Cost Library'!$A$5:$D$204,3,FALSE),""))) | K14: =IF($A14="","",E14*I14) | M14: =IF($A14="","",K14*(1+N14)) | N14: =IF($A14="","",IF(L14="",IFERROR(VLOOKUP(H14,Settings!$A$22:$B$27,2,FALSE),0),L14)) | O14: =IF(AND($A14<>"",$A14=Proposal!$I$2),COUNTIF($A$5:$A14,Proposal!$I$2),"") | P14: =IF($A14="","",IF(COUNTIF(Jobs!$A$5:$A$44,$A14)=0,"Unknown Job ID",IF(B14="","Missing cost code",IF(COUNTIF(Settings!$E$5:$E$28,B14)=0,"Unknown cost code",IF(AND(G14="",C14=""),"No unit cost",IF(E14="","Missing qty",""))))))
H15: =IF(B15="","",IFERROR(VLOOKUP(B15,Settings!$E$5:$G$28,3,FALSE),"Other")) | I15: =IF($A15="","",IF(G15<>"",G15,IFERROR(VLOOKUP(C15,'Cost Library'!$A$5:$D$204,4,FALSE),0))) | J15: =IF($A15="","",IF(F15<>"",F15,IFERROR(VLOOKUP(C15,'Cost Library'!$A$5:$D$204,3,FALSE),""))) | K15: =IF($A15="","",E15*I15) | M15: =IF($A15="","",K15*(1+N15)) | N15: =IF($A15="","",IF(L15="",IFERROR(VLOOKUP(H15,Settings!$A$22:$B$27,2,FALSE),0),L15)) | O15: =IF(AND($A15<>"",$A15=Proposal!$I$2),COUNTIF($A$5:$A15,Proposal!$I$2),"") | P15: =IF($A15="","",IF(COUNTIF(Jobs!$A$5:$A$44,$A15)=0,"Unknown Job ID",IF(B15="","Missing cost code",IF(COUNTIF(Settings!$E$5:$E$28,B15)=0,"Unknown cost code",IF(AND(G15="",C15=""),"No unit cost",IF(E15="","Missing qty",""))))))
H16: =IF(B16="","",IFERROR(VLOOKUP(B16,Settings!$E$5:$G$28,3,FALSE),"Other")) | I16: =IF($A16="","",IF(G16<>"",G16,IFERROR(VLOOKUP(C16,'Cost Library'!$A$5:$D$204,4,FALSE),0))) | J16: =IF($A16="","",IF(F16<>"",F16,IFERROR(VLOOKUP(C16,'Cost Library'!$A$5:$D$204,3,FALSE),""))) | K16: =IF($A16="","",E16*I16) | M16: =IF($A16="","",K16*(1+N16)) | N16: =IF($A16="","",IF(L16="",IFERROR(VLOOKUP(H16,Settings!$A$22:$B$27,2,FALSE),0),L16)) | O16: =IF(AND($A16<>"",$A16=Proposal!$I$2),COUNTIF($A$5:$A16,Proposal!$I$2),"") | P16: =IF($A16="","",IF(COUNTIF(Jobs!$A$5:$A$44,$A16)=0,"Unknown Job ID",IF(B16="","Missing cost code",IF(COUNTIF(Settings!$E$5:$E$28,B16)=0,"Unknown cost code",IF(AND(G16="",C16=""),"No unit cost",IF(E16="","Missing qty",""))))))
... H404: =IF(B404="","",IFERROR(VLOOKUP(B404,Settings!$E$5:$G$28,3,FALSE),"Other")) | I404: =IF($A404="","",IF(G404<>"",G404,IFERROR(VLOOKUP(C404,'Cost Library'!$A$5:$D$204,4,FALSE),0))) | J404: =IF($A404="","",IF(F404<>"",F404,IFERROR(VLOOKUP(C404,'Cost Library'!$A$5:$D$204,3,FALSE),""))) | K404: =IF($A404="","",E404*I404) | M404: =IF($A404="","",K404*(1+N404)) | N404: =IF($A404="","",IF(L404="",IFERROR(VLOOKUP(H404,Settings!$A$22:$B$27,2,FALSE),0),L404)) | O404: =IF(AND($A404<>"",$A404=Proposal!$I$2),COUNTIF($A$5:$A404,Proposal!$I$2),"") | P404: =IF($A404="","",IF(COUNTIF(Jobs!$A$5:$A$44,$A404)=0,"Unknown Job ID",IF(B404="","Missing cost code",IF(COUNTIF(Settings!$E$5:$E$28,B404)=0,"Unknown cost code",IF(AND(G404="",C404=""),"No unit cost",IF(E404="","Missing qty",""))))))
D405: TOTAL (all jobs) | K405: =SUM(K5:K404) | M405: =SUM(M5:M404)

Sheet Proposal
A1: PROPOSAL
H2: Job ID
H3: ← pick a job; the proposal at left fills in. Columns H–J never print.
B4: FROM | E4: PREPARED FOR | H4: INTERNAL — not printed
B5: =Settings!$B$5&"" | E5: =IFERROR(INDEX(Jobs!$B$5:$B$44,MATCH($I$2,Jobs!$A$5:$A$44,0)),"")
B6: =Settings!$B$6&"" | E6: =IFERROR(INDEX(Clients!$B$5:$B$104,MATCH(IFERROR(INDEX(Jobs!$B$5:$B$44,MATCH($I$2,Jobs!$A$5:$A$44,0)),""),Clients!$A$5:$A$104,0)),"")&IF(IFERROR(INDEX(Clients!$C$5:$C$104,MATCH(IFERROR(INDEX(Jobs!$B$5:$B$44,MATCH($I$2,Jobs!$A$5:$A$44,0)),""),Clients!$A$5:$A$104,0)),"")="",""," · "&IFERROR(INDEX(Clients!$C$5:$C$104,MATCH(IFERROR(INDEX(Jobs!$B$5:$B$44,MATCH($I$2,Jobs!$A$5:$A$44,0)),""),Clients!$A$5:$A$104,0)),""))
B7: =Settings!$B$7&"" | E7: =IFERROR(INDEX(Clients!$E$5:$E$104,MATCH(IFERROR(INDEX(Jobs!$B$5:$B$44,MATCH($I$2,Jobs!$A$5:$A$44,0)),""),Clients!$A$5:$A$104,0)),"")
B8: =IF(Settings!$B$8="","","License # "&Settings!$B$8) | E8: =IFERROR(INDEX(Clients!$D$5:$D$104,MATCH(IFERROR(INDEX(Jobs!$B$5:$B$44,MATCH($I$2,Jobs!$A$5:$A$44,0)),""),Clients!$A$5:$A$104,0)),"")
E9: Proposal # | F9: =IF($I$2="","","P-"&$I$2)
B10: Project | E10: Proposal date | F10: =TODAY()
B11: =IFERROR(INDEX(Jobs!$C$5:$C$44,MATCH($I$2,Jobs!$A$5:$A$44,0)),"") | E11: Valid until | F11: =TODAY()+Settings!$B$16
B13: Scope summary | E13: Price | F13: % of total | H13: Category | I13: Est. Cost | J13: Markup $
B14: Labor | E14: =SUMIFS(Estimate!$M$5:$M$404,Estimate!$A$5:$A$404,$I$2,Estimate!$H$5:$H$404,B14) | F14: =IF($E$20=0,0,E14/$E$20) | H14: Labor | I14: =SUMIFS(Estimate!$K$5:$K$404,Estimate!$A$5:$A$404,$I$2,Estimate!$H$5:$H$404,B14) | J14: =E14-I14
B15: Material | E15: =SUMIFS(Estimate!$M$5:$M$404,Estimate!$A$5:$A$404,$I$2,Estimate!$H$5:$H$404,B15) | F15: =IF($E$20=0,0,E15/$E$20) | H15: Material | I15: =SUMIFS(Estimate!$K$5:$K$404,Estimate!$A$5:$A$404,$I$2,Estimate!$H$5:$H$404,B15) | J15: =E15-I15
B16: Subcontractor | E16: =SUMIFS(Estimate!$M$5:$M$404,Estimate!$A$5:$A$404,$I$2,Estimate!$H$5:$H$404,B16) | F16: =IF($E$20=0,0,E16/$E$20) | H16: Subcontractor | I16: =SUMIFS(Estimate!$K$5:$K$404,Estimate!$A$5:$A$404,$I$2,Estimate!$H$5:$H$404,B16) | J16: =E16-I16
B17: Equipment | E17: =SUMIFS(Estimate!$M$5:$M$404,Estimate!$A$5:$A$404,$I$2,Estimate!$H$5:$H$404,B17) | F17: =IF($E$20=0,0,E17/$E$20) | H17: Equipment | I17: =SUMIFS(Estimate!$K$5:$K$404,Estimate!$A$5:$A$404,$I$2,Estimate!$H$5:$H$404,B17) | J17: =E17-I17
B18: Permit/Fee | E18: =SUMIFS(Estimate!$M$5:$M$404,Estimate!$A$5:$A$404,$I$2,Estimate!$H$5:$H$404,B18) | F18: =IF($E$20=0,0,E18/$E$20) | H18: Permit/Fee | I18: =SUMIFS(Estimate!$K$5:$K$404,Estimate!$A$5:$A$404,$I$2,Estimate!$H$5:$H$404,B18) | J18: =E18-I18
B19: Other | E19: =SUMIFS(Estimate!$M$5:$M$404,Estimate!$A$5:$A$404,$I$2,Estimate!$H$5:$H$404,B19) | F19: =IF($E$20=0,0,E19/$E$20) | H19: Other | I19: =SUMIFS(Estimate!$K$5:$K$404,Estimate!$A$5:$A$404,$I$2,Estimate!$H$5:$H$404,B19) | J19: =E19-I19
B20: Subtotal | E20: =SUM(E14:E19) | H20: Total cost | I20: =SUM(I14:I19)
B21: Contingency | E21: =E20*F21 | F21: =Settings!$B$9 | H21: Gross margin on subtotal | I21: =IF(E20=0,0,(E20-I20)/E20)
B22: =IF(Settings!$B$19="All lines","Sales tax","Sales tax on materials") | E22: =IF(Settings!$B$19="All lines",E20*F22,E15*F22) | F22: =Settings!$B$10 | H22: Gross margin on total | I22: =IF(E23=0,0,(E23-I20)/E23)
B23: PROPOSAL TOTAL | E23: =E20+E21+E22 | H23: Estimate lines for this job | I23: =COUNTIF(Estimate!$A$5:$A$404,$I$2)
B25: Payment schedule
B26: Deposit at signing | E26: =E23*F26 | F26: =Settings!$B$11
B27: Progress payment (mid-job) | E27: =E23*F27 | F27: =Settings!$B$12
B28: Final payment on completion | E28: =E23-E26-E27 | F28: =1-F26-F27
A30: # | B30: Detail | D30: Qty | E30: Unit | F30: Line price
A31: =IF(ISNUMBER(MATCH(1,Estimate!$O$5:$O$404,0)),1,"") | B31: =IFERROR(IF(INDEX(Estimate!$D$5:$D$404,MATCH(1,Estimate!$O$5:$O$404,0))="",INDEX(Estimate!$C$5:$C$404,MATCH(1,Estimate!$O$5:$O$404,0)),INDEX(Estimate!$D$5:$D$404,MATCH(1,Estimate!$O$5:$O$404,0))),"") | D31: =IFERROR(INDEX(Estimate!$E$5:$E$404,MATCH(1,Estimate!$O$5:$O$404,0)),"") | E31: =IFERROR(INDEX(Estimate!$J$5:$J$404,MATCH(1,Estimate!$O$5:$O$404,0)),"") | F31: =IFERROR(INDEX(Estimate!$M$5:$M$404,MATCH(1,Estimate!$O$5:$O$404,0)),"")
A32: =IF(ISNUMBER(MATCH(2,Estimate!$O$5:$O$404,0)),2,"") | B32: =IFERROR(IF(INDEX(Estimate!$D$5:$D$404,MATCH(2,Estimate!$O$5:$O$404,0))="",INDEX(Estimate!$C$5:$C$404,MATCH(2,Estimate!$O$5:$O$404,0)),INDEX(Estimate!$D$5:$D$404,MATCH(2,Estimate!$O$5:$O$404,0))),"") | D32: =IFERROR(INDEX(Estimate!$E$5:$E$404,MATCH(2,Estimate!$O$5:$O$404,0)),"") | E32: =IFERROR(INDEX(Estimate!$J$5:$J$404,MATCH(2,Estimate!$O$5:$O$404,0)),"") | F32: =IFERROR(INDEX(Estimate!$M$5:$M$404,MATCH(2,Estimate!$O$5:$O$404,0)),"")
A33: =IF(ISNUMBER(MATCH(3,Estimate!$O$5:$O$404,0)),3,"") | B33: =IFERROR(IF(INDEX(Estimate!$D$5:$D$404,MATCH(3,Estimate!$O$5:$O$404,0))="",INDEX(Estimate!$C$5:$C$404,MATCH(3,Estimate!$O$5:$O$404,0)),INDEX(Estimate!$D$5:$D$404,MATCH(3,Estimate!$O$5:$O$404,0))),"") | D33: =IFERROR(INDEX(Estimate!$E$5:$E$404,MATCH(3,Estimate!$O$5:$O$404,0)),"") | E33: =IFERROR(INDEX(Estimate!$J$5:$J$404,MATCH(3,Estimate!$O$5:$O$404,0)),"") | F33: =IFERROR(INDEX(Estimate!$M$5:$M$404,MATCH(3,Estimate!$O$5:$O$404,0)),"")
A34: =IF(ISNUMBER(MATCH(4,Estimate!$O$5:$O$404,0)),4,"") | B34: =IFERROR(IF(INDEX(Estimate!$D$5:$D$404,MATCH(4,Estimate!$O$5:$O$404,0))="",INDEX(Estimate!$C$5:$C$404,MATCH(4,Estimate!$O$5:$O$404,0)),INDEX(Estimate!$D$5:$D$404,MATCH(4,Estimate!$O$5:$O$404,0))),"") | D34: =IFERROR(INDEX(Estimate!$E$5:$E$404,MATCH(4,Estimate!$O$5:$O$404,0)),"") | E34: =IFERROR(INDEX(Estimate!$J$5:$J$404,MATCH(4,Estimate!$O$5:$O$404,0)),"") | F34: =IFERROR(INDEX(Estimate!$M$5:$M$404,MATCH(4,Estimate!$O$5:$O$404,0)),"")
A35: =IF(ISNUMBER(MATCH(5,Estimate!$O$5:$O$404,0)),5,"") | B35: =IFERROR(IF(INDEX(Estimate!$D$5:$D$404,MATCH(5,Estimate!$O$5:$O$404,0))="",INDEX(Estimate!$C$5:$C$404,MATCH(5,Estimate!$O$5:$O$404,0)),INDEX(Estimate!$D$5:$D$404,MATCH(5,Estimate!$O$5:$O$404,0))),"") | D35: =IFERROR(INDEX(Estimate!$E$5:$E$404,MATCH(5,Estimate!$O$5:$O$404,0)),"") | E35: =IFERROR(INDEX(Estimate!$J$5:$J$404,MATCH(5,Estimate!$O$5:$O$404,0)),"") | F35: =IFERROR(INDEX(Estimate!$M$5:$M$404,MATCH(5,Estimate!$O$5:$O$404,0)),"")
A36: =IF(ISNUMBER(MATCH(6,Estimate!$O$5:$O$404,0)),6,"") | B36: =IFERROR(IF(INDEX(Estimate!$D$5:$D$404,MATCH(6,Estimate!$O$5:$O$404,0))="",INDEX(Estimate!$C$5:$C$404,MATCH(6,Estimate!$O$5:$O$404,0)),INDEX(Estimate!$D$5:$D$404,MATCH(6,Estimate!$O$5:$O$404,0))),"") | D36: =IFERROR(INDEX(Estimate!$E$5:$E$404,MATCH(6,Estimate!$O$5:$O$404,0)),"") | E36: =IFERROR(INDEX(Estimate!$J$5:$J$404,MATCH(6,Estimate!$O$5:$O$404,0)),"") | F36: =IFERROR(INDEX(Estimate!$M$5:$M$404,MATCH(6,Estimate!$O$5:$O$404,0)),"")
A37: =IF(ISNUMBER(MATCH(7,Estimate!$O$5:$O$404,0)),7,"") | B37: =IFERROR(IF(INDEX(Estimate!$D$5:$D$404,MATCH(7,Estimate!$O$5:$O$404,0))="",INDEX(Estimate!$C$5:$C$404,MATCH(7,Estimate!$O$5:$O$404,0)),INDEX(Estimate!$D$5:$D$404,MATCH(7,Estimate!$O$5:$O$404,0))),"") | D37: =IFERROR(INDEX(Estimate!$E$5:$E$404,MATCH(7,Estimate!$O$5:$O$404,0)),"") | E37: =IFERROR(INDEX(Estimate!$J$5:$J$404,MATCH(7,Estimate!$O$5:$O$404,0)),"") | F37: =IFERROR(INDEX(Estimate!$M$5:$M$404,MATCH(7,Estimate!$O$5:$O$404,0)),"")
A38: =IF(ISNUMBER(MATCH(8,Estimate!$O$5:$O$404,0)),8,"") | B38: =IFERROR(IF(INDEX(Estimate!$D$5:$D$404,MATCH(8,Estimate!$O$5:$O$404,0))="",INDEX(Estimate!$C$5:$C$404,MATCH(8,Estimate!$O$5:$O$404,0)),INDEX(Estimate!$D$5:$D$404,MATCH(8,Estimate!$O$5:$O$404,0))),"") | D38: =IFERROR(INDEX(Estimate!$E$5:$E$404,MATCH(8,Estimate!$O$5:$O$404,0)),"") | E38: =IFERROR(INDEX(Estimate!$J$5:$J$404,MATCH(8,Estimate!$O$5:$O$404,0)),"") | F38: =IFERROR(INDEX(Estimate!$M$5:$M$404,MATCH(8,Estimate!$O$5:$O$404,0)),"")
A39: =IF(ISNUMBER(MATCH(9,Estimate!$O$5:$O$404,0)),9,"") | B39: =IFERROR(IF(INDEX(Estimate!$D$5:$D$404,MATCH(9,Estimate!$O$5:$O$404,0))="",INDEX(Estimate!$C$5:$C$404,MATCH(9,Estimate!$O$5:$O$404,0)),INDEX(Estimate!$D$5:$D$404,MATCH(9,Estimate!$O$5:$O$404,0))),"") | D39: =IFERROR(INDEX(Estimate!$E$5:$E$404,MATCH(9,Estimate!$O$5:$O$404,0)),"") | E39: =IFERROR(INDEX(Estimate!$J$5:$J$404,MATCH(9,Estimate!$O$5:$O$404,0)),"") | F39: =IFERROR(INDEX(Estimate!$M$5:$M$404,MATCH(9,Estimate!$O$5:$O$404,0)),"")
A40: =IF(ISNUMBER(MATCH(10,Estimate!$O$5:$O$404,0)),10,"") | B40: =IFERROR(IF(INDEX(Estimate!$D$5:$D$404,MATCH(10,Estimate!$O$5:$O$404,0))="",INDEX(Estimate!$C$5:$C$404,MATCH(10,Estimate!$O$5:$O$404,0)),INDEX(Estimate!$D$5:$D$404,MATCH(10,Estimate!$O$5:$O$404,0))),"") | D40: =IFERROR(INDEX(Estimate!$E$5:$E$404,MATCH(10,Estimate!$O$5:$O$404,0)),"") | E40: =IFERROR(INDEX(Estimate!$J$5:$J$404,MATCH(10,Estimate!$O$5:$O$404,0)),"") | F40: =IFERROR(INDEX(Estimate!$M$5:$M$404,MATCH(10,Estimate!$O$5:$O$404,0)),"")
A41: =IF(ISNUMBER(MATCH(11,Estimate!$O$5:$O$404,0)),11,"") | B41: =IFERROR(IF(INDEX(Estimate!$D$5:$D$404,MATCH(11,Estimate!$O$5:$O$404,0))="",INDEX(Estimate!$C$5:$C$404,MATCH(11,Estimate!$O$5:$O$404,0)),INDEX(Estimate!$D$5:$D$404,MATCH(11,Estimate!$O$5:$O$404,0))),"") | D41: =IFERROR(INDEX(Estimate!$E$5:$E$404,MATCH(11,Estimate!$O$5:$O$404,0)),"") | E41: =IFERROR(INDEX(Estimate!$J$5:$J$404,MATCH(11,Estimate!$O$5:$O$404,0)),"") | F41: =IFERROR(INDEX(Estimate!$M$5:$M$404,MATCH(11,Estimate!$O$5:$O$404,0)),"")
A42: =IF(ISNUMBER(MATCH(12,Estimate!$O$5:$O$404,0)),12,"") | B42: =IFERROR(IF(INDEX(Estimate!$D$5:$D$404,MATCH(12,Estimate!$O$5:$O$404,0))="",INDEX(Estimate!$C$5:$C$404,MATCH(12,Estimate!$O$5:$O$404,0)),INDEX(Estimate!$D$5:$D$404,MATCH(12,Estimate!$O$5:$O$404,0))),"") | D42: =IFERROR(INDEX(Estimate!$E$5:$E$404,MATCH(12,Estimate!$O$5:$O$404,0)),"") | E42: =IFERROR(INDEX(Estimate!$J$5:$J$404,MATCH(12,Estimate!$O$5:$O$404,0)),"") | F42: =IFERROR(INDEX(Estimate!$M$5:$M$404,MATCH(12,Estimate!$O$5:$O$404,0)),"")
A43: =IF(ISNUMBER(MATCH(13,Estimate!$O$5:$O$404,0)),13,"") | B43: =IFERROR(IF(INDEX(Estimate!$D$5:$D$404,MATCH(13,Estimate!$O$5:$O$404,0))="",INDEX(Estimate!$C$5:$C$404,MATCH(13,Estimate!$O$5:$O$404,0)),INDEX(Estimate!$D$5:$D$404,MATCH(13,Estimate!$O$5:$O$404,0))),"") | D43: =IFERROR(INDEX(Estimate!$E$5:$E$404,MATCH(13,Estimate!$O$5:$O$404,0)),"") | E43: =IFERROR(INDEX(Estimate!$J$5:$J$404,MATCH(13,Estimate!$O$5:$O$404,0)),"") | F43: =IFERROR(INDEX(Estimate!$M$5:$M$404,MATCH(13,Estimate!$O$5:$O$404,0)),"")
A44: =IF(ISNUMBER(MATCH(14,Estimate!$O$5:$O$404,0)),14,"") | B44: =IFERROR(IF(INDEX(Estimate!$D$5:$D$404,MATCH(14,Estimate!$O$5:$O$404,0))="",INDEX(Estimate!$C$5:$C$404,MATCH(14,Estimate!$O$5:$O$404,0)),INDEX(Estimate!$D$5:$D$404,MATCH(14,Estimate!$O$5:$O$404,0))),"") | D44: =IFERROR(INDEX(Estimate!$E$5:$E$404,MATCH(14,Estimate!$O$5:$O$404,0)),"") | E44: =IFERROR(INDEX(Estimate!$J$5:$J$404,MATCH(14,Estimate!$O$5:$O$404,0)),"") | F44: =IFERROR(INDEX(Estimate!$M$5:$M$404,MATCH(14,Estimate!$O$5:$O$404,0)),"")
A45: =IF(ISNUMBER(MATCH(15,Estimate!$O$5:$O$404,0)),15,"") | B45: =IFERROR(IF(INDEX(Estimate!$D$5:$D$404,MATCH(15,Estimate!$O$5:$O$404,0))="",INDEX(Estimate!$C$5:$C$404,MATCH(15,Estimate!$O$5:$O$404,0)),INDEX(Estimate!$D$5:$D$404,MATCH(15,Estimate!$O$5:$O$404,0))),"") | D45: =IFERROR(INDEX(Estimate!$E$5:$E$404,MATCH(15,Estimate!$O$5:$O$404,0)),"") | E45: =IFERROR(INDEX(Estimate!$J$5:$J$404,MATCH(15,Estimate!$O$5:$O$404,0)),"") | F45: =IFERROR(INDEX(Estimate!$M$5:$M$404,MATCH(15,Estimate!$O$5:$O$404,0)),"")
A46: =IF(ISNUMBER(MATCH(16,Estimate!$O$5:$O$404,0)),16,"") | B46: =IFERROR(IF(INDEX(Estimate!$D$5:$D$404,MATCH(16,Estimate!$O$5:$O$404,0))="",INDEX(Estimate!$C$5:$C$404,MATCH(16,Estimate!$O$5:$O$404,0)),INDEX(Estimate!$D$5:$D$404,MATCH(16,Estimate!$O$5:$O$404,0))),"") | D46: =IFERROR(INDEX(Estimate!$E$5:$E$404,MATCH(16,Estimate!$O$5:$O$404,0)),"") | E46: =IFERROR(INDEX(Estimate!$J$5:$J$404,MATCH(16,Estimate!$O$5:$O$404,0)),"") | F46: =IFERROR(INDEX(Estimate!$M$5:$M$404,MATCH(16,Estimate!$O$5:$O$404,0)),"")
A47: =IF(ISNUMBER(MATCH(17,Estimate!$O$5:$O$404,0)),17,"") | B47: =IFERROR(IF(INDEX(Estimate!$D$5:$D$404,MATCH(17,Estimate!$O$5:$O$404,0))="",INDEX(Estimate!$C$5:$C$404,MATCH(17,Estimate!$O$5:$O$404,0)),INDEX(Estimate!$D$5:$D$404,MATCH(17,Estimate!$O$5:$O$404,0))),"") | D47: =IFERROR(INDEX(Estimate!$E$5:$E$404,MATCH(17,Estimate!$O$5:$O$404,0)),"") | E47: =IFERROR(INDEX(Estimate!$J$5:$J$404,MATCH(17,Estimate!$O$5:$O$404,0)),"") | F47: =IFERROR(INDEX(Estimate!$M$5:$M$404,MATCH(17,Estimate!$O$5:$O$404,0)),"")
A48: =IF(ISNUMBER(MATCH(18,Estimate!$O$5:$O$404,0)),18,"") | B48: =IFERROR(IF(INDEX(Estimate!$D$5:$D$404,MATCH(18,Estimate!$O$5:$O$404,0))="",INDEX(Estimate!$C$5:$C$404,MATCH(18,Estimate!$O$5:$O$404,0)),INDEX(Estimate!$D$5:$D$404,MATCH(18,Estimate!$O$5:$O$404,0))),"") | D48: =IFERROR(INDEX(Estimate!$E$5:$E$404,MATCH(18,Estimate!$O$5:$O$404,0)),"") | E48: =IFERROR(INDEX(Estimate!$J$5:$J$404,MATCH(18,Estimate!$O$5:$O$404,0)),"") | F48: =IFERROR(INDEX(Estimate!$M$5:$M$404,MATCH(18,Estimate!$O$5:$O$404,0)),"")
A49: =IF(ISNUMBER(MATCH(19,Estimate!$O$5:$O$404,0)),19,"") | B49: =IFERROR(IF(INDEX(Estimate!$D$5:$D$404,MATCH(19,Estimate!$O$5:$O$404,0))="",INDEX(Estimate!$C$5:$C$404,MATCH(19,Estimate!$O$5:$O$404,0)),INDEX(Estimate!$D$5:$D$404,MATCH(19,Estimate!$O$5:$O$404,0))),"") | D49: =IFERROR(INDEX(Estimate!$E$5:$E$404,MATCH(19,Estimate!$O$5:$O$404,0)),"") | E49: =IFERROR(INDEX(Estimate!$J$5:$J$404,MATCH(19,Estimate!$O$5:$O$404,0)),"") | F49: =IFERROR(INDEX(Estimate!$M$5:$M$404,MATCH(19,Estimate!$O$5:$O$404,0)),"")
A50: =IF(ISNUMBER(MATCH(20,Estimate!$O$5:$O$404,0)),20,"") | B50: =IFERROR(IF(INDEX(Estimate!$D$5:$D$404,MATCH(20,Estimate!$O$5:$O$404,0))="",INDEX(Estimate!$C$5:$C$404,MATCH(20,Estimate!$O$5:$O$404,0)),INDEX(Estimate!$D$5:$D$404,MATCH(20,Estimate!$O$5:$O$404,0))),"") | D50: =IFERROR(INDEX(Estimate!$E$5:$E$404,MATCH(20,Estimate!$O$5:$O$404,0)),"") | E50: =IFERROR(INDEX(Estimate!$J$5:$J$404,MATCH(20,Estimate!$O$5:$O$404,0)),"") | F50: =IFERROR(INDEX(Estimate!$M$5:$M$404,MATCH(20,Estimate!$O$5:$O$404,0)),"")
A51: =IF(ISNUMBER(MATCH(21,Estimate!$O$5:$O$404,0)),21,"") | B51: =IFERROR(IF(INDEX(Estimate!$D$5:$D$404,MATCH(21,Estimate!$O$5:$O$404,0))="",INDEX(Estimate!$C$5:$C$404,MATCH(21,Estimate!$O$5:$O$404,0)),INDEX(Estimate!$D$5:$D$404,MATCH(21,Estimate!$O$5:$O$404,0))),"") | D51: =IFERROR(INDEX(Estimate!$E$5:$E$404,MATCH(21,Estimate!$O$5:$O$404,0)),"") | E51: =IFERROR(INDEX(Estimate!$J$5:$J$404,MATCH(21,Estimate!$O$5:$O$404,0)),"") | F51: =IFERROR(INDEX(Estimate!$M$5:$M$404,MATCH(21,Estimate!$O$5:$O$404,0)),"")
A52: =IF(ISNUMBER(MATCH(22,Estimate!$O$5:$O$404,0)),22,"") | B52: =IFERROR(IF(INDEX(Estimate!$D$5:$D$404,MATCH(22,Estimate!$O$5:$O$404,0))="",INDEX(Estimate!$C$5:$C$404,MATCH(22,Estimate!$O$5:$O$404,0)),INDEX(Estimate!$D$5:$D$404,MATCH(22,Estimate!$O$5:$O$404,0))),"") | D52: =IFERROR(INDEX(Estimate!$E$5:$E$404,MATCH(22,Estimate!$O$5:$O$404,0)),"") | E52: =IFERROR(INDEX(Estimate!$J$5:$J$404,MATCH(22,Estimate!$O$5:$O$404,0)),"") | F52: =IFERROR(INDEX(Estimate!$M$5:$M$404,MATCH(22,Estimate!$O$5:$O$404,0)),"")
A53: =IF(ISNUMBER(MATCH(23,Estimate!$O$5:$O$404,0)),23,"") | B53: =IFERROR(IF(INDEX(Estimate!$D$5:$D$404,MATCH(23,Estimate!$O$5:$O$404,0))="",INDEX(Estimate!$C$5:$C$404,MATCH(23,Estimate!$O$5:$O$404,0)),INDEX(Estimate!$D$5:$D$404,MATCH(23,Estimate!$O$5:$O$404,0))),"") | D53: =IFERROR(INDEX(Estimate!$E$5:$E$404,MATCH(23,Estimate!$O$5:$O$404,0)),"") | E53: =IFERROR(INDEX(Estimate!$J$5:$J$404,MATCH(23,Estimate!$O$5:$O$404,0)),"") | F53: =IFERROR(INDEX(Estimate!$M$5:$M$404,MATCH(23,Estimate!$O$5:$O$404,0)),"")
A54: =IF(ISNUMBER(MATCH(24,Estimate!$O$5:$O$404,0)),24,"") | B54: =IFERROR(IF(INDEX(Estimate!$D$5:$D$404,MATCH(24,Estimate!$O$5:$O$404,0))="",INDEX(Estimate!$C$5:$C$404,MATCH(24,Estimate!$O$5:$O$404,0)),INDEX(Estimate!$D$5:$D$404,MATCH(24,Estimate!$O$5:$O$404,0))),"") | D54: =IFERROR(INDEX(Estimate!$E$5:$E$404,MATCH(24,Estimate!$O$5:$O$404,0)),"") | E54: =IFERROR(INDEX(Estimate!$J$5:$J$404,MATCH(24,Estimate!$O$5:$O$404,0)),"") | F54: =IFERROR(INDEX(Estimate!$M$5:$M$404,MATCH(24,Estimate!$O$5:$O$404,0)),"")
A55: =IF(ISNUMBER(MATCH(25,Estimate!$O$5:$O$404,0)),25,"") | B55: =IFERROR(IF(INDEX(Estimate!$D$5:$D$404,MATCH(25,Estimate!$O$5:$O$404,0))="",INDEX(Estimate!$C$5:$C$404,MATCH(25,Estimate!$O$5:$O$404,0)),INDEX(Estimate!$D$5:$D$404,MATCH(25,Estimate!$O$5:$O$404,0))),"") | D55: =IFERROR(INDEX(Estimate!$E$5:$E$404,MATCH(25,Estimate!$O$5:$O$404,0)),"") | E55: =IFERROR(INDEX(Estimate!$J$5:$J$404,MATCH(25,Estimate!$O$5:$O$404,0)),"") | F55: =IFERROR(INDEX(Estimate!$M$5:$M$404,MATCH(25,Estimate!$O$5:$O$404,0)),"")
A56: =IF(ISNUMBER(MATCH(26,Estimate!$O$5:$O$404,0)),26,"") | B56: =IFERROR(IF(INDEX(Estimate!$D$5:$D$404,MATCH(26,Estimate!$O$5:$O$404,0))="",INDEX(Estimate!$C$5:$C$404,MATCH(26,Estimate!$O$5:$O$404,0)),INDEX(Estimate!$D$5:$D$404,MATCH(26,Estimate!$O$5:$O$404,0))),"") | D56: =IFERROR(INDEX(Estimate!$E$5:$E$404,MATCH(26,Estimate!$O$5:$O$404,0)),"") | E56: =IFERROR(INDEX(Estimate!$J$5:$J$404,MATCH(26,Estimate!$O$5:$O$404,0)),"") | F56: =IFERROR(INDEX(Estimate!$M$5:$M$404,MATCH(26,Estimate!$O$5:$O$404,0)),"")
A57: =IF(ISNUMBER(MATCH(27,Estimate!$O$5:$O$404,0)),27,"") | B57: =IFERROR(IF(INDEX(Estimate!$D$5:$D$404,MATCH(27,Estimate!$O$5:$O$404,0))="",INDEX(Estimate!$C$5:$C$404,MATCH(27,Estimate!$O$5:$O$404,0)),INDEX(Estimate!$D$5:$D$404,MATCH(27,Estimate!$O$5:$O$404,0))),"") | D57: =IFERROR(INDEX(Estimate!$E$5:$E$404,MATCH(27,Estimate!$O$5:$O$404,0)),"") | E57: =IFERROR(INDEX(Estimate!$J$5:$J$404,MATCH(27,Estimate!$O$5:$O$404,0)),"") | F57: =IFERROR(INDEX(Estimate!$M$5:$M$404,MATCH(27,Estimate!$O$5:$O$404,0)),"")
A58: =IF(ISNUMBER(MATCH(28,Estimate!$O$5:$O$404,0)),28,"") | B58: =IFERROR(IF(INDEX(Estimate!$D$5:$D$404,MATCH(28,Estimate!$O$5:$O$404,0))="",INDEX(Estimate!$C$5:$C$404,MATCH(28,Estimate!$O$5:$O$404,0)),INDEX(Estimate!$D$5:$D$404,MATCH(28,Estimate!$O$5:$O$404,0))),"") | D58: =IFERROR(INDEX(Estimate!$E$5:$E$404,MATCH(28,Estimate!$O$5:$O$404,0)),"") | E58: =IFERROR(INDEX(Estimate!$J$5:$J$404,MATCH(28,Estimate!$O$5:$O$404,0)),"") | F58: =IFERROR(INDEX(Estimate!$M$5:$M$404,MATCH(28,Estimate!$O$5:$O$404,0)),"")
A59: =IF(ISNUMBER(MATCH(29,Estimate!$O$5:$O$404,0)),29,"") | B59: =IFERROR(IF(INDEX(Estimate!$D$5:$D$404,MATCH(29,Estimate!$O$5:$O$404,0))="",INDEX(Estimate!$C$5:$C$404,MATCH(29,Estimate!$O$5:$O$404,0)),INDEX(Estimate!$D$5:$D$404,MATCH(29,Estimate!$O$5:$O$404,0))),"") | D59: =IFERROR(INDEX(Estimate!$E$5:$E$404,MATCH(29,Estimate!$O$5:$O$404,0)),"") | E59: =IFERROR(INDEX(Estimate!$J$5:$J$404,MATCH(29,Estimate!$O$5:$O$404,0)),"") | F59: =IFERROR(INDEX(Estimate!$M$5:$M$404,MATCH(29,Estimate!$O$5:$O$404,0)),"")
A60: =IF(ISNUMBER(MATCH(30,Estimate!$O$5:$O$404,0)),30,"") | B60: =IFERROR(IF(INDEX(Estimate!$D$5:$D$404,MATCH(30,Estimate!$O$5:$O$404,0))="",INDEX(Estimate!$C$5:$C$404,MATCH(30,Estimate!$O$5:$O$404,0)),INDEX(Estimate!$D$5:$D$404,MATCH(30,Estimate!$O$5:$O$404,0))),"") | D60: =IFERROR(INDEX(Estimate!$E$5:$E$404,MATCH(30,Estimate!$O$5:$O$404,0)),"") | E60: =IFERROR(INDEX(Estimate!$J$5:$J$404,MATCH(30,Estimate!$O$5:$O$404,0)),"") | F60: =IFERROR(INDEX(Estimate!$M$5:$M$404,MATCH(30,Estimate!$O$5:$O$404,0)),"")
A61: =IF(ISNUMBER(MATCH(31,Estimate!$O$5:$O$404,0)),31,"") | B61: =IFERROR(IF(INDEX(Estimate!$D$5:$D$404,MATCH(31,Estimate!$O$5:$O$404,0))="",INDEX(Estimate!$C$5:$C$404,MATCH(31,Estimate!$O$5:$O$404,0)),INDEX(Estimate!$D$5:$D$404,MATCH(31,Estimate!$O$5:$O$404,0))),"") | D61: =IFERROR(INDEX(Estimate!$E$5:$E$404,MATCH(31,Estimate!$O$5:$O$404,0)),"") | E61: =IFERROR(INDEX(Estimate!$J$5:$J$404,MATCH(31,Estimate!$O$5:$O$404,0)),"") | F61: =IFERROR(INDEX(Estimate!$M$5:$M$404,MATCH(31,Estimate!$O$5:$O$404,0)),"")
A62: =IF(ISNUMBER(MATCH(32,Estimate!$O$5:$O$404,0)),32,"") | B62: =IFERROR(IF(INDEX(Estimate!$D$5:$D$404,MATCH(32,Estimate!$O$5:$O$404,0))="",INDEX(Estimate!$C$5:$C$404,MATCH(32,Estimate!$O$5:$O$404,0)),INDEX(Estimate!$D$5:$D$404,MATCH(32,Estimate!$O$5:$O$404,0))),"") | D62: =IFERROR(INDEX(Estimate!$E$5:$E$404,MATCH(32,Estimate!$O$5:$O$404,0)),"") | E62: =IFERROR(INDEX(Estimate!$J$5:$J$404,MATCH(32,Estimate!$O$5:$O$404,0)),"") | F62: =IFERROR(INDEX(Estimate!$M$5:$M$404,MATCH(32,Estimate!$O$5:$O$404,0)),"")
A63: =IF(ISNUMBER(MATCH(33,Estimate!$O$5:$O$404,0)),33,"") | B63: =IFERROR(IF(INDEX(Estimate!$D$5:$D$404,MATCH(33,Estimate!$O$5:$O$404,0))="",INDEX(Estimate!$C$5:$C$404,MATCH(33,Estimate!$O$5:$O$404,0)),INDEX(Estimate!$D$5:$D$404,MATCH(33,Estimate!$O$5:$O$404,0))),"") | D63: =IFERROR(INDEX(Estimate!$E$5:$E$404,MATCH(33,Estimate!$O$5:$O$404,0)),"") | E63: =IFERROR(INDEX(Estimate!$J$5:$J$404,MATCH(33,Estimate!$O$5:$O$404,0)),"") | F63: =IFERROR(INDEX(Estimate!$M$5:$M$404,MATCH(33,Estimate!$O$5:$O$404,0)),"")
A64: =IF(ISNUMBER(MATCH(34,Estimate!$O$5:$O$404,0)),34,"") | B64: =IFERROR(IF(INDEX(Estimate!$D$5:$D$404,MATCH(34,Estimate!$O$5:$O$404,0))="",INDEX(Estimate!$C$5:$C$404,MATCH(34,Estimate!$O$5:$O$404,0)),INDEX(Estimate!$D$5:$D$404,MATCH(34,Estimate!$O$5:$O$404,0))),"") | D64: =IFERROR(INDEX(Estimate!$E$5:$E$404,MATCH(34,Estimate!$O$5:$O$404,0)),"") | E64: =IFERROR(INDEX(Estimate!$J$5:$J$404,MATCH(34,Estimate!$O$5:$O$404,0)),"") | F64: =IFERROR(INDEX(Estimate!$M$5:$M$404,MATCH(34,Estimate!$O$5:$O$404,0)),"")
A65: =IF(ISNUMBER(MATCH(35,Estimate!$O$5:$O$404,0)),35,"") | B65: =IFERROR(IF(INDEX(Estimate!$D$5:$D$404,MATCH(35,Estimate!$O$5:$O$404,0))="",INDEX(Estimate!$C$5:$C$404,MATCH(35,Estimate!$O$5:$O$404,0)),INDEX(Estimate!$D$5:$D$404,MATCH(35,Estimate!$O$5:$O$404,0))),"") | D65: =IFERROR(INDEX(Estimate!$E$5:$E$404,MATCH(35,Estimate!$O$5:$O$404,0)),"") | E65: =IFERROR(INDEX(Estimate!$J$5:$J$404,MATCH(35,Estimate!$O$5:$O$404,0)),"") | F65: =IFERROR(INDEX(Estimate!$M$5:$M$404,MATCH(35,Estimate!$O$5:$O$404,0)),"")
A66: =IF(ISNUMBER(MATCH(36,Estimate!$O$5:$O$404,0)),36,"") | B66: =IFERROR(IF(INDEX(Estimate!$D$5:$D$404,MATCH(36,Estimate!$O$5:$O$404,0))="",INDEX(Estimate!$C$5:$C$404,MATCH(36,Estimate!$O$5:$O$404,0)),INDEX(Estimate!$D$5:$D$404,MATCH(36,Estimate!$O$5:$O$404,0))),"") | D66: =IFERROR(INDEX(Estimate!$E$5:$E$404,MATCH(36,Estimate!$O$5:$O$404,0)),"") | E66: =IFERROR(INDEX(Estimate!$J$5:$J$404,MATCH(36,Estimate!$O$5:$O$404,0)),"") | F66: =IFERROR(INDEX(Estimate!$M$5:$M$404,MATCH(36,Estimate!$O$5:$O$404,0)),"")
A67: =IF(ISNUMBER(MATCH(37,Estimate!$O$5:$O$404,0)),37,"") | B67: =IFERROR(IF(INDEX(Estimate!$D$5:$D$404,MATCH(37,Estimate!$O$5:$O$404,0))="",INDEX(Estimate!$C$5:$C$404,MATCH(37,Estimate!$O$5:$O$404,0)),INDEX(Estimate!$D$5:$D$404,MATCH(37,Estimate!$O$5:$O$404,0))),"") | D67: =IFERROR(INDEX(Estimate!$E$5:$E$404,MATCH(37,Estimate!$O$5:$O$404,0)),"") | E67: =IFERROR(INDEX(Estimate!$J$5:$J$404,MATCH(37,Estimate!$O$5:$O$404,0)),"") | F67: =IFERROR(INDEX(Estimate!$M$5:$M$404,MATCH(37,Estimate!$O$5:$O$404,0)),"")
A68: =IF(ISNUMBER(MATCH(38,Estimate!$O$5:$O$404,0)),38,"") | B68: =IFERROR(IF(INDEX(Estimate!$D$5:$D$404,MATCH(38,Estimate!$O$5:$O$404,0))="",INDEX(Estimate!$C$5:$C$404,MATCH(38,Estimate!$O$5:$O$404,0)),INDEX(Estimate!$D$5:$D$404,MATCH(38,Estimate!$O$5:$O$404,0))),"") | D68: =IFERROR(INDEX(Estimate!$E$5:$E$404,MATCH(38,Estimate!$O$5:$O$404,0)),"") | E68: =IFERROR(INDEX(Estimate!$J$5:$J$404,MATCH(38,Estimate!$O$5:$O$404,0)),"") | F68: =IFERROR(INDEX(Estimate!$M$5:$M$404,MATCH(38,Estimate!$O$5:$O$404,0)),"")
A69: =IF(ISNUMBER(MATCH(39,Estimate!$O$5:$O$404,0)),39,"") | B69: =IFERROR(IF(INDEX(Estimate!$D$5:$D$404,MATCH(39,Estimate!$O$5:$O$404,0))="",INDEX(Estimate!$C$5:$C$404,MATCH(39,Estimate!$O$5:$O$404,0)),INDEX(Estimate!$D$5:$D$404,MATCH(39,Estimate!$O$5:$O$404,0))),"") | D69: =IFERROR(INDEX(Estimate!$E$5:$E$404,MATCH(39,Estimate!$O$5:$O$404,0)),"") | E69: =IFERROR(INDEX(Estimate!$J$5:$J$404,MATCH(39,Estimate!$O$5:$O$404,0)),"") | F69: =IFERROR(INDEX(Estimate!$M$5:$M$404,MATCH(39,Estimate!$O$5:$O$404,0)),"")
A70: =IF(ISNUMBER(MATCH(40,Estimate!$O$5:$O$404,0)),40,"") | B70: =IFERROR(IF(INDEX(Estimate!$D$5:$D$404,MATCH(40,Estimate!$O$5:$O$404,0))="",INDEX(Estimate!$C$5:$C$404,MATCH(40,Estimate!$O$5:$O$404,0)),INDEX(Estimate!$D$5:$D$404,MATCH(40,Estimate!$O$5:$O$404,0))),"") | D70: =IFERROR(INDEX(Estimate!$E$5:$E$404,MATCH(40,Estimate!$O$5:$O$404,0)),"") | E70: =IFERROR(INDEX(Estimate!$J$5:$J$404,MATCH(40,Estimate!$O$5:$O$404,0)),"") | F70: =IFERROR(INDEX(Estimate!$M$5:$M$404,MATCH(40,Estimate!$O$5:$O$404,0)),"")
B71: Lines shown | C71: =IF(COUNTIF(Estimate!$O$5:$O$404,">0")>40,"+ more lines not shown","") | D71: =COUNT(A31:A70) | F71: =SUM(F31:F70)
B73: Terms
B74: =Settings!$B$30
B75: Exclusions & assumptions
B76: =Settings!$B$34
B78: Accepted by (client): ______________________________ Date: ____________
B79: For the contractor: _________________________________ Date: ____________

Sheet Schedule
A1: Schedule
A2: Chart start | B2: =TODAY()-WEEKDAY(TODAY(),2)+1 | C2: Legend: | D2: planned | E2: done | F2: today | G2: weekend | K2: =IF(OR(DAY(K3)=1,11=11),TEXT(K3,"mmm"),"") | L2: =IF(OR(DAY(L3)=1,12=11),TEXT(L3,"mmm"),"") | M2: =IF(OR(DAY(M3)=1,13=11),TEXT(M3,"mmm"),"") | N2: =IF(OR(DAY(N3)=1,14=11),TEXT(N3,"mmm"),"") | O2: =IF(OR(DAY(O3)=1,15=11),TEXT(O3,"mmm"),"") | P2: =IF(OR(DAY(P3)=1,16=11),TEXT(P3,"mmm"),"") | Q2: =IF(OR(DAY(Q3)=1,17=11),TEXT(Q3,"mmm"),"") | R2: =IF(OR(DAY(R3)=1,18=11),TEXT(R3,"mmm"),"") | S2: =IF(OR(DAY(S3)=1,19=11),TEXT(S3,"mmm"),"") | T2: =IF(OR(DAY(T3)=1,20=11),TEXT(T3,"mmm"),"") | U2: =IF(OR(DAY(U3)=1,21=11),TEXT(U3,"mmm"),"") | V2: =IF(OR(DAY(V3)=1,22=11),TEXT(V3,"mmm"),"") | W2: =IF(OR(DAY(W3)=1,23=11),TEXT(W3,"mmm"),"") | X2: =IF(OR(DAY(X3)=1,24=11),TEXT(X3,"mmm"),"") | Y2: =IF(OR(DAY(Y3)=1,25=11),TEXT(Y3,"mmm"),"") | Z2: =IF(OR(DAY(Z3)=1,26=11),TEXT(Z3,"mmm"),"") | AA2: =IF(OR(DAY(AA3)=1,27=11),TEXT(AA3,"mmm"),"") | AB2: =IF(OR(DAY(AB3)=1,28=11),TEXT(AB3,"mmm"),"") | AC2: =IF(OR(DAY(AC3)=1,29=11),TEXT(AC3,"mmm"),"") | AD2: =IF(OR(DAY(AD3)=1,30=11),TEXT(AD3,"mmm"),"") | AE2: =IF(OR(DAY(AE3)=1,31=11),TEXT(AE3,"mmm"),"") | AF2: =IF(OR(DAY(AF3)=1,32=11),TEXT(AF3,"mmm"),"") | AG2: =IF(OR(DAY(AG3)=1,33=11),TEXT(AG3,"mmm"),"") | AH2: =IF(OR(DAY(AH3)=1,34=11),TEXT(AH3,"mmm"),"") | AI2: =IF(OR(DAY(AI3)=1,35=11),TEXT(AI3,"mmm"),"") | AJ2: =IF(OR(DAY(AJ3)=1,36=11),TEXT(AJ3,"mmm"),"") | AK2: =IF(OR(DAY(AK3)=1,37=11),TEXT(AK3,"mmm"),"") | AL2: =IF(OR(DAY(AL3)=1,38=11),TEXT(AL3,"mmm"),"") | AM2: =IF(OR(DAY(AM3)=1,39=11),TEXT(AM3,"mmm"),"") | AN2: =IF(OR(DAY(AN3)=1,40=11),TEXT(AN3,"mmm"),"") | AO2: =IF(OR(DAY(AO3)=1,41=11),TEXT(AO3,"mmm"),"") | AP2: =IF(OR(DAY(AP3)=1,42=11),TEXT(AP3,"mmm"),"") | AQ2: =IF(OR(DAY(AQ3)=1,43=11),TEXT(AQ3,"mmm"),"") | AR2: =IF(OR(DAY(AR3)=1,44=11),TEXT(AR3,"mmm"),"") | AS2: =IF(OR(DAY(AS3)=1,45=11),TEXT(AS3,"mmm"),"") | AT2: =IF(OR(DAY(AT3)=1,46=11),TEXT(AT3,"mmm"),"") | AU2: =IF(OR(DAY(AU3)=1,47=11),TEXT(AU3,"mmm"),"") | AV2: =IF(OR(DAY(AV3)=1,48=11),TEXT(AV3,"mmm"),"") | AW2: =IF(OR(DAY(AW3)=1,49=11),TEXT(AW3,"mmm"),"") | AX2: =IF(OR(DAY(AX3)=1,50=11),TEXT(AX3,"mmm"),"") | AY2: =IF(OR(DAY(AY3)=1,51=11),TEXT(AY3,"mmm"),"") | AZ2: =IF(OR(DAY(AZ3)=1,52=11),TEXT(AZ3,"mmm"),"") | BA2: =IF(OR(DAY(BA3)=1,53=11),TEXT(BA3,"mmm"),"") | BB2: =IF(OR(DAY(BB3)=1,54=11),TEXT(BB3,"mmm"),"") | BC2: =IF(OR(DAY(BC3)=1,55=11),TEXT(BC3,"mmm"),"") | BD2: =IF(OR(DAY(BD3)=1,56=11),TEXT(BD3,"mmm"),"") | BE2: =IF(OR(DAY(BE3)=1,57=11),TEXT(BE3,"mmm"),"") | BF2: =IF(OR(DAY(BF3)=1,58=11),TEXT(BF3,"mmm"),"") | BG2: =IF(OR(DAY(BG3)=1,59=11),TEXT(BG3,"mmm"),"") | BH2: =IF(OR(DAY(BH3)=1,60=11),TEXT(BH3,"mmm"),"") | BI2: =IF(OR(DAY(BI3)=1,61=11),TEXT(BI3,"mmm"),"") | BJ2: =IF(OR(DAY(BJ3)=1,62=11),TEXT(BJ3,"mmm"),"") | BK2: =IF(OR(DAY(BK3)=1,63=11),TEXT(BK3,"mmm"),"") | BL2: =IF(OR(DAY(BL3)=1,64=11),TEXT(BL3,"mmm"),"") | BM2: =IF(OR(DAY(BM3)=1,65=11),TEXT(BM3,"mmm"),"") | BN2: =IF(OR(DAY(BN3)=1,66=11),TEXT(BN3,"mmm"),"") | BO2: =IF(OR(DAY(BO3)=1,67=11),TEXT(BO3,"mmm"),"") | BP2: =IF(OR(DAY(BP3)=1,68=11),TEXT(BP3,"mmm"),"") | BQ2: =IF(OR(DAY(BQ3)=1,69=11),TEXT(BQ3,"mmm"),"") | BR2: =IF(OR(DAY(BR3)=1,70=11),TEXT(BR3,"mmm"),"") | BS2: =IF(OR(DAY(BS3)=1,71=11),TEXT(BS3,"mmm"),"") | BT2: =IF(OR(DAY(BT3)=1,72=11),TEXT(BT3,"mmm"),"") | BU2: =IF(OR(DAY(BU3)=1,73=11),TEXT(BU3,"mmm"),"") | BV2: =IF(OR(DAY(BV3)=1,74=11),TEXT(BV3,"mmm"),"") | BW2: =IF(OR(DAY(BW3)=1,75=11),TEXT(BW3,"mmm"),"") | BX2: =IF(OR(DAY(BX3)=1,76=11),TEXT(BX3,"mmm"),"") | BY2: =IF(OR(DAY(BY3)=1,77=11),TEXT(BY3,"mmm"),"") | BZ2: =IF(OR(DAY(BZ3)=1,78=11),TEXT(BZ3,"mmm"),"") | CA2: =IF(OR(DAY(CA3)=1,79=11),TEXT(CA3,"mmm"),"") | CB2: =IF(OR(DAY(CB3)=1,80=11),TEXT(CB3,"mmm"),"") | CC2: =IF(OR(DAY(CC3)=1,81=11),TEXT(CC3,"mmm"),"") | CD2: =IF(OR(DAY(CD3)=1,82=11),TEXT(CD3,"mmm"),"") | CE2: =IF(OR(DAY(CE3)=1,83=11),TEXT(CE3,"mmm"),"") | CF2: =IF(OR(DAY(CF3)=1,84=11),TEXT(CF3,"mmm"),"") | CG2: =IF(OR(DAY(CG3)=1,85=11),TEXT(CG3,"mmm"),"") | CH2: =IF(OR(DAY(CH3)=1,86=11),TEXT(CH3,"mmm"),"") | CI2: =IF(OR(DAY(CI3)=1,87=11),TEXT(CI3,"mmm"),"") | CJ2: =IF(OR(DAY(CJ3)=1,88=11),TEXT(CJ3,"mmm"),"") | CK2: =IF(OR(DAY(CK3)=1,89=11),TEXT(CK3,"mmm"),"") | CL2: =IF(OR(DAY(CL3)=1,90=11),TEXT(CL3,"mmm"),"") | CM2: =IF(OR(DAY(CM3)=1,91=11),TEXT(CM3,"mmm"),"") | CN2: =IF(OR(DAY(CN3)=1,92=11),TEXT(CN3,"mmm"),"") | CO2: =IF(OR(DAY(CO3)=1,93=11),TEXT(CO3,"mmm"),"") | CP2: =IF(OR(DAY(CP3)=1,94=11),TEXT(CP3,"mmm"),"")
K3: =$B$2 | L3: =K3+1 | M3: =L3+1 | N3: =M3+1 | O3: =N3+1 | P3: =O3+1 | Q3: =P3+1 | R3: =Q3+1 | S3: =R3+1 | ... CP3: =CO3+1
A4: Job ID | B4: Task | C4: Assigned to | D4: Start | E4: Duration (workdays) | F4: End | G4: % Complete | H4: Status | I4: Check | J4: Notes | K4: =LEFT(TEXT(K3,"ddd"),1) | L4: =LEFT(TEXT(L3,"ddd"),1) | M4: =LEFT(TEXT(M3,"ddd"),1) | N4: =LEFT(TEXT(N3,"ddd"),1) | O4: =LEFT(TEXT(O3,"ddd"),1) | P4: =LEFT(TEXT(P3,"ddd"),1) | Q4: =LEFT(TEXT(Q3,"ddd"),1) | R4: =LEFT(TEXT(R3,"ddd"),1) | ... CP4: =LEFT(TEXT(CP3,"ddd"),1)
F5: =IF(OR(D5="",E5=""),"",WORKDAY(D5,MAX(E5,1)-1)) | H5: =IF(D5="","",IF(G5>=1,"Done",IF(TODAY()>F5,"Late",IF(TODAY()>=D5,"In progress","Not started")))) | I5: =IF(B5="","",IF(AND(A5<>"",COUNTIF(Jobs!$A$5:$A$44,A5)=0),"Unknown Job ID",IF(D5="","Missing start",IF(E5="","Missing duration",""))))
F6: =IF(OR(D6="",E6=""),"",WORKDAY(D6,MAX(E6,1)-1)) | H6: =IF(D6="","",IF(G6>=1,"Done",IF(TODAY()>F6,"Late",IF(TODAY()>=D6,"In progress","Not started")))) | I6: =IF(B6="","",IF(AND(A6<>"",COUNTIF(Jobs!$A$5:$A$44,A6)=0),"Unknown Job ID",IF(D6="","Missing start",IF(E6="","Missing duration",""))))
F7: =IF(OR(D7="",E7=""),"",WORKDAY(D7,MAX(E7,1)-1)) | H7: =IF(D7="","",IF(G7>=1,"Done",IF(TODAY()>F7,"Late",IF(TODAY()>=D7,"In progress","Not started")))) | I7: =IF(B7="","",IF(AND(A7<>"",COUNTIF(Jobs!$A$5:$A$44,A7)=0),"Unknown Job ID",IF(D7="","Missing start",IF(E7="","Missing duration",""))))
F8: =IF(OR(D8="",E8=""),"",WORKDAY(D8,MAX(E8,1)-1)) | H8: =IF(D8="","",IF(G8>=1,"Done",IF(TODAY()>F8,"Late",IF(TODAY()>=D8,"In progress","Not started")))) | I8: =IF(B8="","",IF(AND(A8<>"",COUNTIF(Jobs!$A$5:$A$44,A8)=0),"Unknown Job ID",IF(D8="","Missing start",IF(E8="","Missing duration",""))))
F9: =IF(OR(D9="",E9=""),"",WORKDAY(D9,MAX(E9,1)-1)) | H9: =IF(D9="","",IF(G9>=1,"Done",IF(TODAY()>F9,"Late",IF(TODAY()>=D9,"In progress","Not started")))) | I9: =IF(B9="","",IF(AND(A9<>"",COUNTIF(Jobs!$A$5:$A$44,A9)=0),"Unknown Job ID",IF(D9="","Missing start",IF(E9="","Missing duration",""))))
F10: =IF(OR(D10="",E10=""),"",WORKDAY(D10,MAX(E10,1)-1)) | H10: =IF(D10="","",IF(G10>=1,"Done",IF(TODAY()>F10,"Late",IF(TODAY()>=D10,"In progress","Not started")))) | I10: =IF(B10="","",IF(AND(A10<>"",COUNTIF(Jobs!$A$5:$A$44,A10)=0),"Unknown Job ID",IF(D10="","Missing start",IF(E10="","Missing duration",""))))
F11: =IF(OR(D11="",E11=""),"",WORKDAY(D11,MAX(E11,1)-1)) | H11: =IF(D11="","",IF(G11>=1,"Done",IF(TODAY()>F11,"Late",IF(TODAY()>=D11,"In progress","Not started")))) | I11: =IF(B11="","",IF(AND(A11<>"",COUNTIF(Jobs!$A$5:$A$44,A11)=0),"Unknown Job ID",IF(D11="","Missing start",IF(E11="","Missing duration",""))))
F12: =IF(OR(D12="",E12=""),"",WORKDAY(D12,MAX(E12,1)-1)) | H12: =IF(D12="","",IF(G12>=1,"Done",IF(TODAY()>F12,"Late",IF(TODAY()>=D12,"In progress","Not started")))) | I12: =IF(B12="","",IF(AND(A12<>"",COUNTIF(Jobs!$A$5:$A$44,A12)=0),"Unknown Job ID",IF(D12="","Missing start",IF(E12="","Missing duration",""))))
F13: =IF(OR(D13="",E13=""),"",WORKDAY(D13,MAX(E13,1)-1)) | H13: =IF(D13="","",IF(G13>=1,"Done",IF(TODAY()>F13,"Late",IF(TODAY()>=D13,"In progress","Not started")))) | I13: =IF(B13="","",IF(AND(A13<>"",COUNTIF(Jobs!$A$5:$A$44,A13)=0),"Unknown Job ID",IF(D13="","Missing start",IF(E13="","Missing duration",""))))
F14: =IF(OR(D14="",E14=""),"",WORKDAY(D14,MAX(E14,1)-1)) | H14: =IF(D14="","",IF(G14>=1,"Done",IF(TODAY()>F14,"Late",IF(TODAY()>=D14,"In progress","Not started")))) | I14: =IF(B14="","",IF(AND(A14<>"",COUNTIF(Jobs!$A$5:$A$44,A14)=0),"Unknown Job ID",IF(D14="","Missing start",IF(E14="","Missing duration",""))))
F15: =IF(OR(D15="",E15=""),"",WORKDAY(D15,MAX(E15,1)-1)) | H15: =IF(D15="","",IF(G15>=1,"Done",IF(TODAY()>F15,"Late",IF(TODAY()>=D15,"In progress","Not started")))) | I15: =IF(B15="","",IF(AND(A15<>"",COUNTIF(Jobs!$A$5:$A$44,A15)=0),"Unknown Job ID",IF(D15="","Missing start",IF(E15="","Missing duration",""))))
F16: =IF(OR(D16="",E16=""),"",WORKDAY(D16,MAX(E16,1)-1)) | H16: =IF(D16="","",IF(G16>=1,"Done",IF(TODAY()>F16,"Late",IF(TODAY()>=D16,"In progress","Not started")))) | I16: =IF(B16="","",IF(AND(A16<>"",COUNTIF(Jobs!$A$5:$A$44,A16)=0),"Unknown Job ID",IF(D16="","Missing start",IF(E16="","Missing duration",""))))
... F204: =IF(OR(D204="",E204=""),"",WORKDAY(D204,MAX(E204,1)-1)) | H204: =IF(D204="","",IF(G204>=1,"Done",IF(TODAY()>F204,"Late",IF(TODAY()>=D204,"In progress","Not started")))) | I204: =IF(B204="","",IF(AND(A204<>"",COUNTIF(Jobs!$A$5:$A$44,A204)=0),"Unknown Job ID",IF(D204="","Missing start",IF(E204="","Missing duration",""))))

Sheet Timesheet
A1: Timesheet
A2: Crew hours by day and job. Rate Used comes from Vendors & Crew unless you type an override. Log crew labor HERE (or in Job Costs), never both. | P2: WEEKLY PAYROLL SUMMARY
P3: Week ending (Sunday) | Q3: =TODAY()-WEEKDAY(TODAY(),2)+7 | R3: ← type any Sunday
A4: Date | B4: Worker | C4: Job ID | D4: Cost Code | E4: Hours | F4: Cost Rate Override | G4: Rate Used | H4: Labor Cost (incl. burden) | I4: Bill Rate | J4: Billable Value | K4: Week Ending | L4: Category | M4: Check | N4: Notes | P4: Worker | Q4: Hours | R4: Labor cost | S4: Billable | T4: OT hours (>40)
G5: =IF(B5="","",IF(F5<>"",F5,IFERROR(VLOOKUP(B5,'Vendors & Crew'!$A$5:$D$34,3,FALSE),0))) | H5: =IF(B5="","",E5*G5*(1+Settings!$B$18)) | I5: =IF(B5="","",IFERROR(VLOOKUP(B5,'Vendors & Crew'!$A$5:$D$34,4,FALSE),0)) | J5: =IF(B5="","",E5*I5) | K5: =IF(A5="","",A5-WEEKDAY(A5,2)+7) | L5: =IF(B5="","",IF(D5="","Labor",IFERROR(VLOOKUP(D5,Settings!$E$5:$G$28,3,FALSE),"Labor"))) | M5: =IF(B5="","",IF(COUNTIF('Vendors & Crew'!$A$5:$A$34,B5)=0,"Worker not in Crew table",IF(C5="","Missing Job ID",IF(COUNTIF(Jobs!$A$5:$A$44,C5)=0,"Unknown Job ID",IF(E5="","Missing hours",IF(A5="","Missing date","")))))) | P5: =IF('Vendors & Crew'!$A$5="","",'Vendors & Crew'!$A$5) | Q5: =IF(P5="","",SUMIFS(Timesheet!$E$5:$E$1004,Timesheet!$B$5:$B$1004,P5,Timesheet!$K$5:$K$1004,$Q$3)) | R5: =IF(P5="","",SUMIFS(Timesheet!$H$5:$H$1004,Timesheet!$B$5:$B$1004,P5,Timesheet!$K$5:$K$1004,$Q$3)) | S5: =IF(P5="","",SUMIFS(Timesheet!$J$5:$J$1004,Timesheet!$B$5:$B$1004,P5,Timesheet!$K$5:$K$1004,$Q$3)) | T5: =IF(P5="","",MAX(0,Q5-40))
G6: =IF(B6="","",IF(F6<>"",F6,IFERROR(VLOOKUP(B6,'Vendors & Crew'!$A$5:$D$34,3,FALSE),0))) | H6: =IF(B6="","",E6*G6*(1+Settings!$B$18)) | I6: =IF(B6="","",IFERROR(VLOOKUP(B6,'Vendors & Crew'!$A$5:$D$34,4,FALSE),0)) | J6: =IF(B6="","",E6*I6) | K6: =IF(A6="","",A6-WEEKDAY(A6,2)+7) | L6: =IF(B6="","",IF(D6="","Labor",IFERROR(VLOOKUP(D6,Settings!$E$5:$G$28,3,FALSE),"Labor"))) | M6: =IF(B6="","",IF(COUNTIF('Vendors & Crew'!$A$5:$A$34,B6)=0,"Worker not in Crew table",IF(C6="","Missing Job ID",IF(COUNTIF(Jobs!$A$5:$A$44,C6)=0,"Unknown Job ID",IF(E6="","Missing hours",IF(A6="","Missing date","")))))) | P6: =IF('Vendors & Crew'!$A$6="","",'Vendors & Crew'!$A$6) | Q6: =IF(P6="","",SUMIFS(Timesheet!$E$5:$E$1004,Timesheet!$B$5:$B$1004,P6,Timesheet!$K$5:$K$1004,$Q$3)) | R6: =IF(P6="","",SUMIFS(Timesheet!$H$5:$H$1004,Timesheet!$B$5:$B$1004,P6,Timesheet!$K$5:$K$1004,$Q$3)) | S6: =IF(P6="","",SUMIFS(Timesheet!$J$5:$J$1004,Timesheet!$B$5:$B$1004,P6,Timesheet!$K$5:$K$1004,$Q$3)) | T6: =IF(P6="","",MAX(0,Q6-40))
G7: =IF(B7="","",IF(F7<>"",F7,IFERROR(VLOOKUP(B7,'Vendors & Crew'!$A$5:$D$34,3,FALSE),0))) | H7: =IF(B7="","",E7*G7*(1+Settings!$B$18)) | I7: =IF(B7="","",IFERROR(VLOOKUP(B7,'Vendors & Crew'!$A$5:$D$34,4,FALSE),0)) | J7: =IF(B7="","",E7*I7) | K7: =IF(A7="","",A7-WEEKDAY(A7,2)+7) | L7: =IF(B7="","",IF(D7="","Labor",IFERROR(VLOOKUP(D7,Settings!$E$5:$G$28,3,FALSE),"Labor"))) | M7: =IF(B7="","",IF(COUNTIF('Vendors & Crew'!$A$5:$A$34,B7)=0,"Worker not in Crew table",IF(C7="","Missing Job ID",IF(COUNTIF(Jobs!$A$5:$A$44,C7)=0,"Unknown Job ID",IF(E7="","Missing hours",IF(A7="","Missing date","")))))) | P7: =IF('Vendors & Crew'!$A$7="","",'Vendors & Crew'!$A$7) | Q7: =IF(P7="","",SUMIFS(Timesheet!$E$5:$E$1004,Timesheet!$B$5:$B$1004,P7,Timesheet!$K$5:$K$1004,$Q$3)) | R7: =IF(P7="","",SUMIFS(Timesheet!$H$5:$H$1004,Timesheet!$B$5:$B$1004,P7,Timesheet!$K$5:$K$1004,$Q$3)) | S7: =IF(P7="","",SUMIFS(Timesheet!$J$5:$J$1004,Timesheet!$B$5:$B$1004,P7,Timesheet!$K$5:$K$1004,$Q$3)) | T7: =IF(P7="","",MAX(0,Q7-40))
G8: =IF(B8="","",IF(F8<>"",F8,IFERROR(VLOOKUP(B8,'Vendors & Crew'!$A$5:$D$34,3,FALSE),0))) | H8: =IF(B8="","",E8*G8*(1+Settings!$B$18)) | I8: =IF(B8="","",IFERROR(VLOOKUP(B8,'Vendors & Crew'!$A$5:$D$34,4,FALSE),0)) | J8: =IF(B8="","",E8*I8) | K8: =IF(A8="","",A8-WEEKDAY(A8,2)+7) | L8: =IF(B8="","",IF(D8="","Labor",IFERROR(VLOOKUP(D8,Settings!$E$5:$G$28,3,FALSE),"Labor"))) | M8: =IF(B8="","",IF(COUNTIF('Vendors & Crew'!$A$5:$A$34,B8)=0,"Worker not in Crew table",IF(C8="","Missing Job ID",IF(COUNTIF(Jobs!$A$5:$A$44,C8)=0,"Unknown Job ID",IF(E8="","Missing hours",IF(A8="","Missing date","")))))) | P8: =IF('Vendors & Crew'!$A$8="","",'Vendors & Crew'!$A$8) | Q8: =IF(P8="","",SUMIFS(Timesheet!$E$5:$E$1004,Timesheet!$B$5:$B$1004,P8,Timesheet!$K$5:$K$1004,$Q$3)) | R8: =IF(P8="","",SUMIFS(Timesheet!$H$5:$H$1004,Timesheet!$B$5:$B$1004,P8,Timesheet!$K$5:$K$1004,$Q$3)) | S8: =IF(P8="","",SUMIFS(Timesheet!$J$5:$J$1004,Timesheet!$B$5:$B$1004,P8,Timesheet!$K$5:$K$1004,$Q$3)) | T8: =IF(P8="","",MAX(0,Q8-40))
G9: =IF(B9="","",IF(F9<>"",F9,IFERROR(VLOOKUP(B9,'Vendors & Crew'!$A$5:$D$34,3,FALSE),0))) | H9: =IF(B9="","",E9*G9*(1+Settings!$B$18)) | I9: =IF(B9="","",IFERROR(VLOOKUP(B9,'Vendors & Crew'!$A$5:$D$34,4,FALSE),0)) | J9: =IF(B9="","",E9*I9) | K9: =IF(A9="","",A9-WEEKDAY(A9,2)+7) | L9: =IF(B9="","",IF(D9="","Labor",IFERROR(VLOOKUP(D9,Settings!$E$5:$G$28,3,FALSE),"Labor"))) | M9: =IF(B9="","",IF(COUNTIF('Vendors & Crew'!$A$5:$A$34,B9)=0,"Worker not in Crew table",IF(C9="","Missing Job ID",IF(COUNTIF(Jobs!$A$5:$A$44,C9)=0,"Unknown Job ID",IF(E9="","Missing hours",IF(A9="","Missing date","")))))) | P9: =IF('Vendors & Crew'!$A$9="","",'Vendors & Crew'!$A$9) | Q9: =IF(P9="","",SUMIFS(Timesheet!$E$5:$E$1004,Timesheet!$B$5:$B$1004,P9,Timesheet!$K$5:$K$1004,$Q$3)) | R9: =IF(P9="","",SUMIFS(Timesheet!$H$5:$H$1004,Timesheet!$B$5:$B$1004,P9,Timesheet!$K$5:$K$1004,$Q$3)) | S9: =IF(P9="","",SUMIFS(Timesheet!$J$5:$J$1004,Timesheet!$B$5:$B$1004,P9,Timesheet!$K$5:$K$1004,$Q$3)) | T9: =IF(P9="","",MAX(0,Q9-40))
G10: =IF(B10="","",IF(F10<>"",F10,IFERROR(VLOOKUP(B10,'Vendors & Crew'!$A$5:$D$34,3,FALSE),0))) | H10: =IF(B10="","",E10*G10*(1+Settings!$B$18)) | I10: =IF(B10="","",IFERROR(VLOOKUP(B10,'Vendors & Crew'!$A$5:$D$34,4,FALSE),0)) | J10: =IF(B10="","",E10*I10) | K10: =IF(A10="","",A10-WEEKDAY(A10,2)+7) | L10: =IF(B10="","",IF(D10="","Labor",IFERROR(VLOOKUP(D10,Settings!$E$5:$G$28,3,FALSE),"Labor"))) | M10: =IF(B10="","",IF(COUNTIF('Vendors & Crew'!$A$5:$A$34,B10)=0,"Worker not in Crew table",IF(C10="","Missing Job ID",IF(COUNTIF(Jobs!$A$5:$A$44,C10)=0,"Unknown Job ID",IF(E10="","Missing hours",IF(A10="","Missing date","")))))) | P10: =IF('Vendors & Crew'!$A$10="","",'Vendors & Crew'!$A$10) | Q10: =IF(P10="","",SUMIFS(Timesheet!$E$5:$E$1004,Timesheet!$B$5:$B$1004,P10,Timesheet!$K$5:$K$1004,$Q$3)) | R10: =IF(P10="","",SUMIFS(Timesheet!$H$5:$H$1004,Timesheet!$B$5:$B$1004,P10,Timesheet!$K$5:$K$1004,$Q$3)) | S10: =IF(P10="","",SUMIFS(Timesheet!$J$5:$J$1004,Timesheet!$B$5:$B$1004,P10,Timesheet!$K$5:$K$1004,$Q$3)) | T10: =IF(P10="","",MAX(0,Q10-40))
G11: =IF(B11="","",IF(F11<>"",F11,IFERROR(VLOOKUP(B11,'Vendors & Crew'!$A$5:$D$34,3,FALSE),0))) | H11: =IF(B11="","",E11*G11*(1+Settings!$B$18)) | I11: =IF(B11="","",IFERROR(VLOOKUP(B11,'Vendors & Crew'!$A$5:$D$34,4,FALSE),0)) | J11: =IF(B11="","",E11*I11) | K11: =IF(A11="","",A11-WEEKDAY(A11,2)+7) | L11: =IF(B11="","",IF(D11="","Labor",IFERROR(VLOOKUP(D11,Settings!$E$5:$G$28,3,FALSE),"Labor"))) | M11: =IF(B11="","",IF(COUNTIF('Vendors & Crew'!$A$5:$A$34,B11)=0,"Worker not in Crew table",IF(C11="","Missing Job ID",IF(COUNTIF(Jobs!$A$5:$A$44,C11)=0,"Unknown Job ID",IF(E11="","Missing hours",IF(A11="","Missing date","")))))) | P11: =IF('Vendors & Crew'!$A$11="","",'Vendors & Crew'!$A$11) | Q11: =IF(P11="","",SUMIFS(Timesheet!$E$5:$E$1004,Timesheet!$B$5:$B$1004,P11,Timesheet!$K$5:$K$1004,$Q$3)) | R11: =IF(P11="","",SUMIFS(Timesheet!$H$5:$H$1004,Timesheet!$B$5:$B$1004,P11,Timesheet!$K$5:$K$1004,$Q$3)) | S11: =IF(P11="","",SUMIFS(Timesheet!$J$5:$J$1004,Timesheet!$B$5:$B$1004,P11,Timesheet!$K$5:$K$1004,$Q$3)) | T11: =IF(P11="","",MAX(0,Q11-40))
G12: =IF(B12="","",IF(F12<>"",F12,IFERROR(VLOOKUP(B12,'Vendors & Crew'!$A$5:$D$34,3,FALSE),0))) | H12: =IF(B12="","",E12*G12*(1+Settings!$B$18)) | I12: =IF(B12="","",IFERROR(VLOOKUP(B12,'Vendors & Crew'!$A$5:$D$34,4,FALSE),0)) | J12: =IF(B12="","",E12*I12) | K12: =IF(A12="","",A12-WEEKDAY(A12,2)+7) | L12: =IF(B12="","",IF(D12="","Labor",IFERROR(VLOOKUP(D12,Settings!$E$5:$G$28,3,FALSE),"Labor"))) | M12: =IF(B12="","",IF(COUNTIF('Vendors & Crew'!$A$5:$A$34,B12)=0,"Worker not in Crew table",IF(C12="","Missing Job ID",IF(COUNTIF(Jobs!$A$5:$A$44,C12)=0,"Unknown Job ID",IF(E12="","Missing hours",IF(A12="","Missing date","")))))) | P12: =IF('Vendors & Crew'!$A$12="","",'Vendors & Crew'!$A$12) | Q12: =IF(P12="","",SUMIFS(Timesheet!$E$5:$E$1004,Timesheet!$B$5:$B$1004,P12,Timesheet!$K$5:$K$1004,$Q$3)) | R12: =IF(P12="","",SUMIFS(Timesheet!$H$5:$H$1004,Timesheet!$B$5:$B$1004,P12,Timesheet!$K$5:$K$1004,$Q$3)) | S12: =IF(P12="","",SUMIFS(Timesheet!$J$5:$J$1004,Timesheet!$B$5:$B$1004,P12,Timesheet!$K$5:$K$1004,$Q$3)) | T12: =IF(P12="","",MAX(0,Q12-40))
G13: =IF(B13="","",IF(F13<>"",F13,IFERROR(VLOOKUP(B13,'Vendors & Crew'!$A$5:$D$34,3,FALSE),0))) | H13: =IF(B13="","",E13*G13*(1+Settings!$B$18)) | I13: =IF(B13="","",IFERROR(VLOOKUP(B13,'Vendors & Crew'!$A$5:$D$34,4,FALSE),0)) | J13: =IF(B13="","",E13*I13) | K13: =IF(A13="","",A13-WEEKDAY(A13,2)+7) | L13: =IF(B13="","",IF(D13="","Labor",IFERROR(VLOOKUP(D13,Settings!$E$5:$G$28,3,FALSE),"Labor"))) | M13: =IF(B13="","",IF(COUNTIF('Vendors & Crew'!$A$5:$A$34,B13)=0,"Worker not in Crew table",IF(C13="","Missing Job ID",IF(COUNTIF(Jobs!$A$5:$A$44,C13)=0,"Unknown Job ID",IF(E13="","Missing hours",IF(A13="","Missing date","")))))) | P13: =IF('Vendors & Crew'!$A$13="","",'Vendors & Crew'!$A$13) | Q13: =IF(P13="","",SUMIFS(Timesheet!$E$5:$E$1004,Timesheet!$B$5:$B$1004,P13,Timesheet!$K$5:$K$1004,$Q$3)) | R13: =IF(P13="","",SUMIFS(Timesheet!$H$5:$H$1004,Timesheet!$B$5:$B$1004,P13,Timesheet!$K$5:$K$1004,$Q$3)) | S13: =IF(P13="","",SUMIFS(Timesheet!$J$5:$J$1004,Timesheet!$B$5:$B$1004,P13,Timesheet!$K$5:$K$1004,$Q$3)) | T13: =IF(P13="","",MAX(0,Q13-40))
G14: =IF(B14="","",IF(F14<>"",F14,IFERROR(VLOOKUP(B14,'Vendors & Crew'!$A$5:$D$34,3,FALSE),0))) | H14: =IF(B14="","",E14*G14*(1+Settings!$B$18)) | I14: =IF(B14="","",IFERROR(VLOOKUP(B14,'Vendors & Crew'!$A$5:$D$34,4,FALSE),0)) | J14: =IF(B14="","",E14*I14) | K14: =IF(A14="","",A14-WEEKDAY(A14,2)+7) | L14: =IF(B14="","",IF(D14="","Labor",IFERROR(VLOOKUP(D14,Settings!$E$5:$G$28,3,FALSE),"Labor"))) | M14: =IF(B14="","",IF(COUNTIF('Vendors & Crew'!$A$5:$A$34,B14)=0,"Worker not in Crew table",IF(C14="","Missing Job ID",IF(COUNTIF(Jobs!$A$5:$A$44,C14)=0,"Unknown Job ID",IF(E14="","Missing hours",IF(A14="","Missing date","")))))) | P14: =IF('Vendors & Crew'!$A$14="","",'Vendors & Crew'!$A$14) | Q14: =IF(P14="","",SUMIFS(Timesheet!$E$5:$E$1004,Timesheet!$B$5:$B$1004,P14,Timesheet!$K$5:$K$1004,$Q$3)) | R14: =IF(P14="","",SUMIFS(Timesheet!$H$5:$H$1004,Timesheet!$B$5:$B$1004,P14,Timesheet!$K$5:$K$1004,$Q$3)) | S14: =IF(P14="","",SUMIFS(Timesheet!$J$5:$J$1004,Timesheet!$B$5:$B$1004,P14,Timesheet!$K$5:$K$1004,$Q$3)) | T14: =IF(P14="","",MAX(0,Q14-40))
G15: =IF(B15="","",IF(F15<>"",F15,IFERROR(VLOOKUP(B15,'Vendors & Crew'!$A$5:$D$34,3,FALSE),0))) | H15: =IF(B15="","",E15*G15*(1+Settings!$B$18)) | I15: =IF(B15="","",IFERROR(VLOOKUP(B15,'Vendors & Crew'!$A$5:$D$34,4,FALSE),0)) | J15: =IF(B15="","",E15*I15) | K15: =IF(A15="","",A15-WEEKDAY(A15,2)+7) | L15: =IF(B15="","",IF(D15="","Labor",IFERROR(VLOOKUP(D15,Settings!$E$5:$G$28,3,FALSE),"Labor"))) | M15: =IF(B15="","",IF(COUNTIF('Vendors & Crew'!$A$5:$A$34,B15)=0,"Worker not in Crew table",IF(C15="","Missing Job ID",IF(COUNTIF(Jobs!$A$5:$A$44,C15)=0,"Unknown Job ID",IF(E15="","Missing hours",IF(A15="","Missing date","")))))) | P15: =IF('Vendors & Crew'!$A$15="","",'Vendors & Crew'!$A$15) | Q15: =IF(P15="","",SUMIFS(Timesheet!$E$5:$E$1004,Timesheet!$B$5:$B$1004,P15,Timesheet!$K$5:$K$1004,$Q$3)) | R15: =IF(P15="","",SUMIFS(Timesheet!$H$5:$H$1004,Timesheet!$B$5:$B$1004,P15,Timesheet!$K$5:$K$1004,$Q$3)) | S15: =IF(P15="","",SUMIFS(Timesheet!$J$5:$J$1004,Timesheet!$B$5:$B$1004,P15,Timesheet!$K$5:$K$1004,$Q$3)) | T15: =IF(P15="","",MAX(0,Q15-40))
G16: =IF(B16="","",IF(F16<>"",F16,IFERROR(VLOOKUP(B16,'Vendors & Crew'!$A$5:$D$34,3,FALSE),0))) | H16: =IF(B16="","",E16*G16*(1+Settings!$B$18)) | I16: =IF(B16="","",IFERROR(VLOOKUP(B16,'Vendors & Crew'!$A$5:$D$34,4,FALSE),0)) | J16: =IF(B16="","",E16*I16) | K16: =IF(A16="","",A16-WEEKDAY(A16,2)+7) | L16: =IF(B16="","",IF(D16="","Labor",IFERROR(VLOOKUP(D16,Settings!$E$5:$G$28,3,FALSE),"Labor"))) | M16: =IF(B16="","",IF(COUNTIF('Vendors & Crew'!$A$5:$A$34,B16)=0,"Worker not in Crew table",IF(C16="","Missing Job ID",IF(COUNTIF(Jobs!$A$5:$A$44,C16)=0,"Unknown Job ID",IF(E16="","Missing hours",IF(A16="","Missing date","")))))) | P16: =IF('Vendors & Crew'!$A$16="","",'Vendors & Crew'!$A$16) | Q16: =IF(P16="","",SUMIFS(Timesheet!$E$5:$E$1004,Timesheet!$B$5:$B$1004,P16,Timesheet!$K$5:$K$1004,$Q$3)) | R16: =IF(P16="","",SUMIFS(Timesheet!$H$5:$H$1004,Timesheet!$B$5:$B$1004,P16,Timesheet!$K$5:$K$1004,$Q$3)) | S16: =IF(P16="","",SUMIFS(Timesheet!$J$5:$J$1004,Timesheet!$B$5:$B$1004,P16,Timesheet!$K$5:$K$1004,$Q$3)) | T16: =IF(P16="","",MAX(0,Q16-40))
G17: =IF(B17="","",IF(F17<>"",F17,IFERROR(VLOOKUP(B17,'Vendors & Crew'!$A$5:$D$34,3,FALSE),0))) | H17: =IF(B17="","",E17*G17*(1+Settings!$B$18)) | I17: =IF(B17="","",IFERROR(VLOOKUP(B17,'Vendors & Crew'!$A$5:$D$34,4,FALSE),0)) | J17: =IF(B17="","",E17*I17) | K17: =IF(A17="","",A17-WEEKDAY(A17,2)+7) | L17: =IF(B17="","",IF(D17="","Labor",IFERROR(VLOOKUP(D17,Settings!$E$5:$G$28,3,FALSE),"Labor"))) | M17: =IF(B17="","",IF(COUNTIF('Vendors & Crew'!$A$5:$A$34,B17)=0,"Worker not in Crew table",IF(C17="","Missing Job ID",IF(COUNTIF(Jobs!$A$5:$A$44,C17)=0,"Unknown Job ID",IF(E17="","Missing hours",IF(A17="","Missing date","")))))) | P17: =IF('Vendors & Crew'!$A$17="","",'Vendors & Crew'!$A$17) | Q17: =IF(P17="","",SUMIFS(Timesheet!$E$5:$E$1004,Timesheet!$B$5:$B$1004,P17,Timesheet!$K$5:$K$1004,$Q$3)) | R17: =IF(P17="","",SUMIFS(Timesheet!$H$5:$H$1004,Timesheet!$B$5:$B$1004,P17,Timesheet!$K$5:$K$1004,$Q$3)) | S17: =IF(P17="","",SUMIFS(Timesheet!$J$5:$J$1004,Timesheet!$B$5:$B$1004,P17,Timesheet!$K$5:$K$1004,$Q$3)) | T17: =IF(P17="","",MAX(0,Q17-40))
G18: =IF(B18="","",IF(F18<>"",F18,IFERROR(VLOOKUP(B18,'Vendors & Crew'!$A$5:$D$34,3,FALSE),0))) | H18: =IF(B18="","",E18*G18*(1+Settings!$B$18)) | I18: =IF(B18="","",IFERROR(VLOOKUP(B18,'Vendors & Crew'!$A$5:$D$34,4,FALSE),0)) | J18: =IF(B18="","",E18*I18) | K18: =IF(A18="","",A18-WEEKDAY(A18,2)+7) | L18: =IF(B18="","",IF(D18="","Labor",IFERROR(VLOOKUP(D18,Settings!$E$5:$G$28,3,FALSE),"Labor"))) | M18: =IF(B18="","",IF(COUNTIF('Vendors & Crew'!$A$5:$A$34,B18)=0,"Worker not in Crew table",IF(C18="","Missing Job ID",IF(COUNTIF(Jobs!$A$5:$A$44,C18)=0,"Unknown Job ID",IF(E18="","Missing hours",IF(A18="","Missing date","")))))) | P18: =IF('Vendors & Crew'!$A$18="","",'Vendors & Crew'!$A$18) | Q18: =IF(P18="","",SUMIFS(Timesheet!$E$5:$E$1004,Timesheet!$B$5:$B$1004,P18,Timesheet!$K$5:$K$1004,$Q$3)) | R18: =IF(P18="","",SUMIFS(Timesheet!$H$5:$H$1004,Timesheet!$B$5:$B$1004,P18,Timesheet!$K$5:$K$1004,$Q$3)) | S18: =IF(P18="","",SUMIFS(Timesheet!$J$5:$J$1004,Timesheet!$B$5:$B$1004,P18,Timesheet!$K$5:$K$1004,$Q$3)) | T18: =IF(P18="","",MAX(0,Q18-40))
G19: =IF(B19="","",IF(F19<>"",F19,IFERROR(VLOOKUP(B19,'Vendors & Crew'!$A$5:$D$34,3,FALSE),0))) | H19: =IF(B19="","",E19*G19*(1+Settings!$B$18)) | I19: =IF(B19="","",IFERROR(VLOOKUP(B19,'Vendors & Crew'!$A$5:$D$34,4,FALSE),0)) | J19: =IF(B19="","",E19*I19) | K19: =IF(A19="","",A19-WEEKDAY(A19,2)+7) | L19: =IF(B19="","",IF(D19="","Labor",IFERROR(VLOOKUP(D19,Settings!$E$5:$G$28,3,FALSE),"Labor"))) | M19: =IF(B19="","",IF(COUNTIF('Vendors & Crew'!$A$5:$A$34,B19)=0,"Worker not in Crew table",IF(C19="","Missing Job ID",IF(COUNTIF(Jobs!$A$5:$A$44,C19)=0,"Unknown Job ID",IF(E19="","Missing hours",IF(A19="","Missing date","")))))) | P19: =IF('Vendors & Crew'!$A$19="","",'Vendors & Crew'!$A$19) | Q19: =IF(P19="","",SUMIFS(Timesheet!$E$5:$E$1004,Timesheet!$B$5:$B$1004,P19,Timesheet!$K$5:$K$1004,$Q$3)) | R19: =IF(P19="","",SUMIFS(Timesheet!$H$5:$H$1004,Timesheet!$B$5:$B$1004,P19,Timesheet!$K$5:$K$1004,$Q$3)) | S19: =IF(P19="","",SUMIFS(Timesheet!$J$5:$J$1004,Timesheet!$B$5:$B$1004,P19,Timesheet!$K$5:$K$1004,$Q$3)) | T19: =IF(P19="","",MAX(0,Q19-40))
G20: =IF(B20="","",IF(F20<>"",F20,IFERROR(VLOOKUP(B20,'Vendors & Crew'!$A$5:$D$34,3,FALSE),0))) | H20: =IF(B20="","",E20*G20*(1+Settings!$B$18)) | I20: =IF(B20="","",IFERROR(VLOOKUP(B20,'Vendors & Crew'!$A$5:$D$34,4,FALSE),0)) | J20: =IF(B20="","",E20*I20) | K20: =IF(A20="","",A20-WEEKDAY(A20,2)+7) | L20: =IF(B20="","",IF(D20="","Labor",IFERROR(VLOOKUP(D20,Settings!$E$5:$G$28,3,FALSE),"Labor"))) | M20: =IF(B20="","",IF(COUNTIF('Vendors & Crew'!$A$5:$A$34,B20)=0,"Worker not in Crew table",IF(C20="","Missing Job ID",IF(COUNTIF(Jobs!$A$5:$A$44,C20)=0,"Unknown Job ID",IF(E20="","Missing hours",IF(A20="","Missing date","")))))) | P20: =IF('Vendors & Crew'!$A$20="","",'Vendors & Crew'!$A$20) | Q20: =IF(P20="","",SUMIFS(Timesheet!$E$5:$E$1004,Timesheet!$B$5:$B$1004,P20,Timesheet!$K$5:$K$1004,$Q$3)) | R20: =IF(P20="","",SUMIFS(Timesheet!$H$5:$H$1004,Timesheet!$B$5:$B$1004,P20,Timesheet!$K$5:$K$1004,$Q$3)) | S20: =IF(P20="","",SUMIFS(Timesheet!$J$5:$J$1004,Timesheet!$B$5:$B$1004,P20,Timesheet!$K$5:$K$1004,$Q$3)) | T20: =IF(P20="","",MAX(0,Q20-40))
G21: =IF(B21="","",IF(F21<>"",F21,IFERROR(VLOOKUP(B21,'Vendors & Crew'!$A$5:$D$34,3,FALSE),0))) | H21: =IF(B21="","",E21*G21*(1+Settings!$B$18)) | I21: =IF(B21="","",IFERROR(VLOOKUP(B21,'Vendors & Crew'!$A$5:$D$34,4,FALSE),0)) | J21: =IF(B21="","",E21*I21) | K21: =IF(A21="","",A21-WEEKDAY(A21,2)+7) | L21: =IF(B21="","",IF(D21="","Labor",IFERROR(VLOOKUP(D21,Settings!$E$5:$G$28,3,FALSE),"Labor"))) | M21: =IF(B21="","",IF(COUNTIF('Vendors & Crew'!$A$5:$A$34,B21)=0,"Worker not in Crew table",IF(C21="","Missing Job ID",IF(COUNTIF(Jobs!$A$5:$A$44,C21)=0,"Unknown Job ID",IF(E21="","Missing hours",IF(A21="","Missing date","")))))) | P21: =IF('Vendors & Crew'!$A$21="","",'Vendors & Crew'!$A$21) | Q21: =IF(P21="","",SUMIFS(Timesheet!$E$5:$E$1004,Timesheet!$B$5:$B$1004,P21,Timesheet!$K$5:$K$1004,$Q$3)) | R21: =IF(P21="","",SUMIFS(Timesheet!$H$5:$H$1004,Timesheet!$B$5:$B$1004,P21,Timesheet!$K$5:$K$1004,$Q$3)) | S21: =IF(P21="","",SUMIFS(Timesheet!$J$5:$J$1004,Timesheet!$B$5:$B$1004,P21,Timesheet!$K$5:$K$1004,$Q$3)) | T21: =IF(P21="","",MAX(0,Q21-40))
G22: =IF(B22="","",IF(F22<>"",F22,IFERROR(VLOOKUP(B22,'Vendors & Crew'!$A$5:$D$34,3,FALSE),0))) | H22: =IF(B22="","",E22*G22*(1+Settings!$B$18)) | I22: =IF(B22="","",IFERROR(VLOOKUP(B22,'Vendors & Crew'!$A$5:$D$34,4,FALSE),0)) | J22: =IF(B22="","",E22*I22) | K22: =IF(A22="","",A22-WEEKDAY(A22,2)+7) | L22: =IF(B22="","",IF(D22="","Labor",IFERROR(VLOOKUP(D22,Settings!$E$5:$G$28,3,FALSE),"Labor"))) | M22: =IF(B22="","",IF(COUNTIF('Vendors & Crew'!$A$5:$A$34,B22)=0,"Worker not in Crew table",IF(C22="","Missing Job ID",IF(COUNTIF(Jobs!$A$5:$A$44,C22)=0,"Unknown Job ID",IF(E22="","Missing hours",IF(A22="","Missing date","")))))) | P22: =IF('Vendors & Crew'!$A$22="","",'Vendors & Crew'!$A$22) | Q22: =IF(P22="","",SUMIFS(Timesheet!$E$5:$E$1004,Timesheet!$B$5:$B$1004,P22,Timesheet!$K$5:$K$1004,$Q$3)) | R22: =IF(P22="","",SUMIFS(Timesheet!$H$5:$H$1004,Timesheet!$B$5:$B$1004,P22,Timesheet!$K$5:$K$1004,$Q$3)) | S22: =IF(P22="","",SUMIFS(Timesheet!$J$5:$J$1004,Timesheet!$B$5:$B$1004,P22,Timesheet!$K$5:$K$1004,$Q$3)) | T22: =IF(P22="","",MAX(0,Q22-40))
G23: =IF(B23="","",IF(F23<>"",F23,IFERROR(VLOOKUP(B23,'Vendors & Crew'!$A$5:$D$34,3,FALSE),0))) | H23: =IF(B23="","",E23*G23*(1+Settings!$B$18)) | I23: =IF(B23="","",IFERROR(VLOOKUP(B23,'Vendors & Crew'!$A$5:$D$34,4,FALSE),0)) | J23: =IF(B23="","",E23*I23) | K23: =IF(A23="","",A23-WEEKDAY(A23,2)+7) | L23: =IF(B23="","",IF(D23="","Labor",IFERROR(VLOOKUP(D23,Settings!$E$5:$G$28,3,FALSE),"Labor"))) | M23: =IF(B23="","",IF(COUNTIF('Vendors & Crew'!$A$5:$A$34,B23)=0,"Worker not in Crew table",IF(C23="","Missing Job ID",IF(COUNTIF(Jobs!$A$5:$A$44,C23)=0,"Unknown Job ID",IF(E23="","Missing hours",IF(A23="","Missing date","")))))) | P23: =IF('Vendors & Crew'!$A$23="","",'Vendors & Crew'!$A$23) | Q23: =IF(P23="","",SUMIFS(Timesheet!$E$5:$E$1004,Timesheet!$B$5:$B$1004,P23,Timesheet!$K$5:$K$1004,$Q$3)) | R23: =IF(P23="","",SUMIFS(Timesheet!$H$5:$H$1004,Timesheet!$B$5:$B$1004,P23,Timesheet!$K$5:$K$1004,$Q$3)) | S23: =IF(P23="","",SUMIFS(Timesheet!$J$5:$J$1004,Timesheet!$B$5:$B$1004,P23,Timesheet!$K$5:$K$1004,$Q$3)) | T23: =IF(P23="","",MAX(0,Q23-40))
G24: =IF(B24="","",IF(F24<>"",F24,IFERROR(VLOOKUP(B24,'Vendors & Crew'!$A$5:$D$34,3,FALSE),0))) | H24: =IF(B24="","",E24*G24*(1+Settings!$B$18)) | I24: =IF(B24="","",IFERROR(VLOOKUP(B24,'Vendors & Crew'!$A$5:$D$34,4,FALSE),0)) | J24: =IF(B24="","",E24*I24) | K24: =IF(A24="","",A24-WEEKDAY(A24,2)+7) | L24: =IF(B24="","",IF(D24="","Labor",IFERROR(VLOOKUP(D24,Settings!$E$5:$G$28,3,FALSE),"Labor"))) | M24: =IF(B24="","",IF(COUNTIF('Vendors & Crew'!$A$5:$A$34,B24)=0,"Worker not in Crew table",IF(C24="","Missing Job ID",IF(COUNTIF(Jobs!$A$5:$A$44,C24)=0,"Unknown Job ID",IF(E24="","Missing hours",IF(A24="","Missing date","")))))) | P24: =IF('Vendors & Crew'!$A$24="","",'Vendors & Crew'!$A$24) | Q24: =IF(P24="","",SUMIFS(Timesheet!$E$5:$E$1004,Timesheet!$B$5:$B$1004,P24,Timesheet!$K$5:$K$1004,$Q$3)) | R24: =IF(P24="","",SUMIFS(Timesheet!$H$5:$H$1004,Timesheet!$B$5:$B$1004,P24,Timesheet!$K$5:$K$1004,$Q$3)) | S24: =IF(P24="","",SUMIFS(Timesheet!$J$5:$J$1004,Timesheet!$B$5:$B$1004,P24,Timesheet!$K$5:$K$1004,$Q$3)) | T24: =IF(P24="","",MAX(0,Q24-40))
G25: =IF(B25="","",IF(F25<>"",F25,IFERROR(VLOOKUP(B25,'Vendors & Crew'!$A$5:$D$34,3,FALSE),0))) | H25: =IF(B25="","",E25*G25*(1+Settings!$B$18)) | I25: =IF(B25="","",IFERROR(VLOOKUP(B25,'Vendors & Crew'!$A$5:$D$34,4,FALSE),0)) | J25: =IF(B25="","",E25*I25) | K25: =IF(A25="","",A25-WEEKDAY(A25,2)+7) | L25: =IF(B25="","",IF(D25="","Labor",IFERROR(VLOOKUP(D25,Settings!$E$5:$G$28,3,FALSE),"Labor"))) | M25: =IF(B25="","",IF(COUNTIF('Vendors & Crew'!$A$5:$A$34,B25)=0,"Worker not in Crew table",IF(C25="","Missing Job ID",IF(COUNTIF(Jobs!$A$5:$A$44,C25)=0,"Unknown Job ID",IF(E25="","Missing hours",IF(A25="","Missing date","")))))) | P25: =IF('Vendors & Crew'!$A$25="","",'Vendors & Crew'!$A$25) | Q25: =IF(P25="","",SUMIFS(Timesheet!$E$5:$E$1004,Timesheet!$B$5:$B$1004,P25,Timesheet!$K$5:$K$1004,$Q$3)) | R25: =IF(P25="","",SUMIFS(Timesheet!$H$5:$H$1004,Timesheet!$B$5:$B$1004,P25,Timesheet!$K$5:$K$1004,$Q$3)) | S25: =IF(P25="","",SUMIFS(Timesheet!$J$5:$J$1004,Timesheet!$B$5:$B$1004,P25,Timesheet!$K$5:$K$1004,$Q$3)) | T25: =IF(P25="","",MAX(0,Q25-40))
G26: =IF(B26="","",IF(F26<>"",F26,IFERROR(VLOOKUP(B26,'Vendors & Crew'!$A$5:$D$34,3,FALSE),0))) | H26: =IF(B26="","",E26*G26*(1+Settings!$B$18)) | I26: =IF(B26="","",IFERROR(VLOOKUP(B26,'Vendors & Crew'!$A$5:$D$34,4,FALSE),0)) | J26: =IF(B26="","",E26*I26) | K26: =IF(A26="","",A26-WEEKDAY(A26,2)+7) | L26: =IF(B26="","",IF(D26="","Labor",IFERROR(VLOOKUP(D26,Settings!$E$5:$G$28,3,FALSE),"Labor"))) | M26: =IF(B26="","",IF(COUNTIF('Vendors & Crew'!$A$5:$A$34,B26)=0,"Worker not in Crew table",IF(C26="","Missing Job ID",IF(COUNTIF(Jobs!$A$5:$A$44,C26)=0,"Unknown Job ID",IF(E26="","Missing hours",IF(A26="","Missing date","")))))) | P26: =IF('Vendors & Crew'!$A$26="","",'Vendors & Crew'!$A$26) | Q26: =IF(P26="","",SUMIFS(Timesheet!$E$5:$E$1004,Timesheet!$B$5:$B$1004,P26,Timesheet!$K$5:$K$1004,$Q$3)) | R26: =IF(P26="","",SUMIFS(Timesheet!$H$5:$H$1004,Timesheet!$B$5:$B$1004,P26,Timesheet!$K$5:$K$1004,$Q$3)) | S26: =IF(P26="","",SUMIFS(Timesheet!$J$5:$J$1004,Timesheet!$B$5:$B$1004,P26,Timesheet!$K$5:$K$1004,$Q$3)) | T26: =IF(P26="","",MAX(0,Q26-40))
G27: =IF(B27="","",IF(F27<>"",F27,IFERROR(VLOOKUP(B27,'Vendors & Crew'!$A$5:$D$34,3,FALSE),0))) | H27: =IF(B27="","",E27*G27*(1+Settings!$B$18)) | I27: =IF(B27="","",IFERROR(VLOOKUP(B27,'Vendors & Crew'!$A$5:$D$34,4,FALSE),0)) | J27: =IF(B27="","",E27*I27) | K27: =IF(A27="","",A27-WEEKDAY(A27,2)+7) | L27: =IF(B27="","",IF(D27="","Labor",IFERROR(VLOOKUP(D27,Settings!$E$5:$G$28,3,FALSE),"Labor"))) | M27: =IF(B27="","",IF(COUNTIF('Vendors & Crew'!$A$5:$A$34,B27)=0,"Worker not in Crew table",IF(C27="","Missing Job ID",IF(COUNTIF(Jobs!$A$5:$A$44,C27)=0,"Unknown Job ID",IF(E27="","Missing hours",IF(A27="","Missing date","")))))) | P27: =IF('Vendors & Crew'!$A$27="","",'Vendors & Crew'!$A$27) | Q27: =IF(P27="","",SUMIFS(Timesheet!$E$5:$E$1004,Timesheet!$B$5:$B$1004,P27,Timesheet!$K$5:$K$1004,$Q$3)) | R27: =IF(P27="","",SUMIFS(Timesheet!$H$5:$H$1004,Timesheet!$B$5:$B$1004,P27,Timesheet!$K$5:$K$1004,$Q$3)) | S27: =IF(P27="","",SUMIFS(Timesheet!$J$5:$J$1004,Timesheet!$B$5:$B$1004,P27,Timesheet!$K$5:$K$1004,$Q$3)) | T27: =IF(P27="","",MAX(0,Q27-40))
G28: =IF(B28="","",IF(F28<>"",F28,IFERROR(VLOOKUP(B28,'Vendors & Crew'!$A$5:$D$34,3,FALSE),0))) | H28: =IF(B28="","",E28*G28*(1+Settings!$B$18)) | I28: =IF(B28="","",IFERROR(VLOOKUP(B28,'Vendors & Crew'!$A$5:$D$34,4,FALSE),0)) | J28: =IF(B28="","",E28*I28) | K28: =IF(A28="","",A28-WEEKDAY(A28,2)+7) | L28: =IF(B28="","",IF(D28="","Labor",IFERROR(VLOOKUP(D28,Settings!$E$5:$G$28,3,FALSE),"Labor"))) | M28: =IF(B28="","",IF(COUNTIF('Vendors & Crew'!$A$5:$A$34,B28)=0,"Worker not in Crew table",IF(C28="","Missing Job ID",IF(COUNTIF(Jobs!$A$5:$A$44,C28)=0,"Unknown Job ID",IF(E28="","Missing hours",IF(A28="","Missing date","")))))) | P28: =IF('Vendors & Crew'!$A$28="","",'Vendors & Crew'!$A$28) | Q28: =IF(P28="","",SUMIFS(Timesheet!$E$5:$E$1004,Timesheet!$B$5:$B$1004,P28,Timesheet!$K$5:$K$1004,$Q$3)) | R28: =IF(P28="","",SUMIFS(Timesheet!$H$5:$H$1004,Timesheet!$B$5:$B$1004,P28,Timesheet!$K$5:$K$1004,$Q$3)) | S28: =IF(P28="","",SUMIFS(Timesheet!$J$5:$J$1004,Timesheet!$B$5:$B$1004,P28,Timesheet!$K$5:$K$1004,$Q$3)) | T28: =IF(P28="","",MAX(0,Q28-40))
G29: =IF(B29="","",IF(F29<>"",F29,IFERROR(VLOOKUP(B29,'Vendors & Crew'!$A$5:$D$34,3,FALSE),0))) | H29: =IF(B29="","",E29*G29*(1+Settings!$B$18)) | I29: =IF(B29="","",IFERROR(VLOOKUP(B29,'Vendors & Crew'!$A$5:$D$34,4,FALSE),0)) | J29: =IF(B29="","",E29*I29) | K29: =IF(A29="","",A29-WEEKDAY(A29,2)+7) | L29: =IF(B29="","",IF(D29="","Labor",IFERROR(VLOOKUP(D29,Settings!$E$5:$G$28,3,FALSE),"Labor"))) | M29: =IF(B29="","",IF(COUNTIF('Vendors & Crew'!$A$5:$A$34,B29)=0,"Worker not in Crew table",IF(C29="","Missing Job ID",IF(COUNTIF(Jobs!$A$5:$A$44,C29)=0,"Unknown Job ID",IF(E29="","Missing hours",IF(A29="","Missing date","")))))) | P29: =IF('Vendors & Crew'!$A$29="","",'Vendors & Crew'!$A$29) | Q29: =IF(P29="","",SUMIFS(Timesheet!$E$5:$E$1004,Timesheet!$B$5:$B$1004,P29,Timesheet!$K$5:$K$1004,$Q$3)) | R29: =IF(P29="","",SUMIFS(Timesheet!$H$5:$H$1004,Timesheet!$B$5:$B$1004,P29,Timesheet!$K$5:$K$1004,$Q$3)) | S29: =IF(P29="","",SUMIFS(Timesheet!$J$5:$J$1004,Timesheet!$B$5:$B$1004,P29,Timesheet!$K$5:$K$1004,$Q$3)) | T29: =IF(P29="","",MAX(0,Q29-40))
G30: =IF(B30="","",IF(F30<>"",F30,IFERROR(VLOOKUP(B30,'Vendors & Crew'!$A$5:$D$34,3,FALSE),0))) | H30: =IF(B30="","",E30*G30*(1+Settings!$B$18)) | I30: =IF(B30="","",IFERROR(VLOOKUP(B30,'Vendors & Crew'!$A$5:$D$34,4,FALSE),0)) | J30: =IF(B30="","",E30*I30) | K30: =IF(A30="","",A30-WEEKDAY(A30,2)+7) | L30: =IF(B30="","",IF(D30="","Labor",IFERROR(VLOOKUP(D30,Settings!$E$5:$G$28,3,FALSE),"Labor"))) | M30: =IF(B30="","",IF(COUNTIF('Vendors & Crew'!$A$5:$A$34,B30)=0,"Worker not in Crew table",IF(C30="","Missing Job ID",IF(COUNTIF(Jobs!$A$5:$A$44,C30)=0,"Unknown Job ID",IF(E30="","Missing hours",IF(A30="","Missing date","")))))) | P30: =IF('Vendors & Crew'!$A$30="","",'Vendors & Crew'!$A$30) | Q30: =IF(P30="","",SUMIFS(Timesheet!$E$5:$E$1004,Timesheet!$B$5:$B$1004,P30,Timesheet!$K$5:$K$1004,$Q$3)) | R30: =IF(P30="","",SUMIFS(Timesheet!$H$5:$H$1004,Timesheet!$B$5:$B$1004,P30,Timesheet!$K$5:$K$1004,$Q$3)) | S30: =IF(P30="","",SUMIFS(Timesheet!$J$5:$J$1004,Timesheet!$B$5:$B$1004,P30,Timesheet!$K$5:$K$1004,$Q$3)) | T30: =IF(P30="","",MAX(0,Q30-40))
G31: =IF(B31="","",IF(F31<>"",F31,IFERROR(VLOOKUP(B31,'Vendors & Crew'!$A$5:$D$34,3,FALSE),0))) | H31: =IF(B31="","",E31*G31*(1+Settings!$B$18)) | I31: =IF(B31="","",IFERROR(VLOOKUP(B31,'Vendors & Crew'!$A$5:$D$34,4,FALSE),0)) | J31: =IF(B31="","",E31*I31) | K31: =IF(A31="","",A31-WEEKDAY(A31,2)+7) | L31: =IF(B31="","",IF(D31="","Labor",IFERROR(VLOOKUP(D31,Settings!$E$5:$G$28,3,FALSE),"Labor"))) | M31: =IF(B31="","",IF(COUNTIF('Vendors & Crew'!$A$5:$A$34,B31)=0,"Worker not in Crew table",IF(C31="","Missing Job ID",IF(COUNTIF(Jobs!$A$5:$A$44,C31)=0,"Unknown Job ID",IF(E31="","Missing hours",IF(A31="","Missing date","")))))) | P31: =IF('Vendors & Crew'!$A$31="","",'Vendors & Crew'!$A$31) | Q31: =IF(P31="","",SUMIFS(Timesheet!$E$5:$E$1004,Timesheet!$B$5:$B$1004,P31,Timesheet!$K$5:$K$1004,$Q$3)) | R31: =IF(P31="","",SUMIFS(Timesheet!$H$5:$H$1004,Timesheet!$B$5:$B$1004,P31,Timesheet!$K$5:$K$1004,$Q$3)) | S31: =IF(P31="","",SUMIFS(Timesheet!$J$5:$J$1004,Timesheet!$B$5:$B$1004,P31,Timesheet!$K$5:$K$1004,$Q$3)) | T31: =IF(P31="","",MAX(0,Q31-40))
G32: =IF(B32="","",IF(F32<>"",F32,IFERROR(VLOOKUP(B32,'Vendors & Crew'!$A$5:$D$34,3,FALSE),0))) | H32: =IF(B32="","",E32*G32*(1+Settings!$B$18)) | I32: =IF(B32="","",IFERROR(VLOOKUP(B32,'Vendors & Crew'!$A$5:$D$34,4,FALSE),0)) | J32: =IF(B32="","",E32*I32) | K32: =IF(A32="","",A32-WEEKDAY(A32,2)+7) | L32: =IF(B32="","",IF(D32="","Labor",IFERROR(VLOOKUP(D32,Settings!$E$5:$G$28,3,FALSE),"Labor"))) | M32: =IF(B32="","",IF(COUNTIF('Vendors & Crew'!$A$5:$A$34,B32)=0,"Worker not in Crew table",IF(C32="","Missing Job ID",IF(COUNTIF(Jobs!$A$5:$A$44,C32)=0,"Unknown Job ID",IF(E32="","Missing hours",IF(A32="","Missing date","")))))) | P32: =IF('Vendors & Crew'!$A$32="","",'Vendors & Crew'!$A$32) | Q32: =IF(P32="","",SUMIFS(Timesheet!$E$5:$E$1004,Timesheet!$B$5:$B$1004,P32,Timesheet!$K$5:$K$1004,$Q$3)) | R32: =IF(P32="","",SUMIFS(Timesheet!$H$5:$H$1004,Timesheet!$B$5:$B$1004,P32,Timesheet!$K$5:$K$1004,$Q$3)) | S32: =IF(P32="","",SUMIFS(Timesheet!$J$5:$J$1004,Timesheet!$B$5:$B$1004,P32,Timesheet!$K$5:$K$1004,$Q$3)) | T32: =IF(P32="","",MAX(0,Q32-40))
G33: =IF(B33="","",IF(F33<>"",F33,IFERROR(VLOOKUP(B33,'Vendors & Crew'!$A$5:$D$34,3,FALSE),0))) | H33: =IF(B33="","",E33*G33*(1+Settings!$B$18)) | I33: =IF(B33="","",IFERROR(VLOOKUP(B33,'Vendors & Crew'!$A$5:$D$34,4,FALSE),0)) | J33: =IF(B33="","",E33*I33) | K33: =IF(A33="","",A33-WEEKDAY(A33,2)+7) | L33: =IF(B33="","",IF(D33="","Labor",IFERROR(VLOOKUP(D33,Settings!$E$5:$G$28,3,FALSE),"Labor"))) | M33: =IF(B33="","",IF(COUNTIF('Vendors & Crew'!$A$5:$A$34,B33)=0,"Worker not in Crew table",IF(C33="","Missing Job ID",IF(COUNTIF(Jobs!$A$5:$A$44,C33)=0,"Unknown Job ID",IF(E33="","Missing hours",IF(A33="","Missing date","")))))) | P33: =IF('Vendors & Crew'!$A$33="","",'Vendors & Crew'!$A$33) | Q33: =IF(P33="","",SUMIFS(Timesheet!$E$5:$E$1004,Timesheet!$B$5:$B$1004,P33,Timesheet!$K$5:$K$1004,$Q$3)) | R33: =IF(P33="","",SUMIFS(Timesheet!$H$5:$H$1004,Timesheet!$B$5:$B$1004,P33,Timesheet!$K$5:$K$1004,$Q$3)) | S33: =IF(P33="","",SUMIFS(Timesheet!$J$5:$J$1004,Timesheet!$B$5:$B$1004,P33,Timesheet!$K$5:$K$1004,$Q$3)) | T33: =IF(P33="","",MAX(0,Q33-40))
G34: =IF(B34="","",IF(F34<>"",F34,IFERROR(VLOOKUP(B34,'Vendors & Crew'!$A$5:$D$34,3,FALSE),0))) | H34: =IF(B34="","",E34*G34*(1+Settings!$B$18)) | I34: =IF(B34="","",IFERROR(VLOOKUP(B34,'Vendors & Crew'!$A$5:$D$34,4,FALSE),0)) | J34: =IF(B34="","",E34*I34) | K34: =IF(A34="","",A34-WEEKDAY(A34,2)+7) | L34: =IF(B34="","",IF(D34="","Labor",IFERROR(VLOOKUP(D34,Settings!$E$5:$G$28,3,FALSE),"Labor"))) | M34: =IF(B34="","",IF(COUNTIF('Vendors & Crew'!$A$5:$A$34,B34)=0,"Worker not in Crew table",IF(C34="","Missing Job ID",IF(COUNTIF(Jobs!$A$5:$A$44,C34)=0,"Unknown Job ID",IF(E34="","Missing hours",IF(A34="","Missing date","")))))) | P34: =IF('Vendors & Crew'!$A$34="","",'Vendors & Crew'!$A$34) | Q34: =IF(P34="","",SUMIFS(Timesheet!$E$5:$E$1004,Timesheet!$B$5:$B$1004,P34,Timesheet!$K$5:$K$1004,$Q$3)) | R34: =IF(P34="","",SUMIFS(Timesheet!$H$5:$H$1004,Timesheet!$B$5:$B$1004,P34,Timesheet!$K$5:$K$1004,$Q$3)) | S34: =IF(P34="","",SUMIFS(Timesheet!$J$5:$J$1004,Timesheet!$B$5:$B$1004,P34,Timesheet!$K$5:$K$1004,$Q$3)) | T34: =IF(P34="","",MAX(0,Q34-40))
G35: =IF(B35="","",IF(F35<>"",F35,IFERROR(VLOOKUP(B35,'Vendors & Crew'!$A$5:$D$34,3,FALSE),0))) | H35: =IF(B35="","",E35*G35*(1+Settings!$B$18)) | I35: =IF(B35="","",IFERROR(VLOOKUP(B35,'Vendors & Crew'!$A$5:$D$34,4,FALSE),0)) | J35: =IF(B35="","",E35*I35) | K35: =IF(A35="","",A35-WEEKDAY(A35,2)+7) | L35: =IF(B35="","",IF(D35="","Labor",IFERROR(VLOOKUP(D35,Settings!$E$5:$G$28,3,FALSE),"Labor"))) | M35: =IF(B35="","",IF(COUNTIF('Vendors & Crew'!$A$5:$A$34,B35)=0,"Worker not in Crew table",IF(C35="","Missing Job ID",IF(COUNTIF(Jobs!$A$5:$A$44,C35)=0,"Unknown Job ID",IF(E35="","Missing hours",IF(A35="","Missing date","")))))) | P35: TOTAL | Q35: =SUM(Q5:Q34) | R35: =SUM(R5:R34) | S35: =SUM(S5:S34) | T35: =SUM(T5:T34)
G36: =IF(B36="","",IF(F36<>"",F36,IFERROR(VLOOKUP(B36,'Vendors & Crew'!$A$5:$D$34,3,FALSE),0))) | H36: =IF(B36="","",E36*G36*(1+Settings!$B$18)) | I36: =IF(B36="","",IFERROR(VLOOKUP(B36,'Vendors & Crew'!$A$5:$D$34,4,FALSE),0)) | J36: =IF(B36="","",E36*I36) | K36: =IF(A36="","",A36-WEEKDAY(A36,2)+7) | L36: =IF(B36="","",IF(D36="","Labor",IFERROR(VLOOKUP(D36,Settings!$E$5:$G$28,3,FALSE),"Labor"))) | M36: =IF(B36="","",IF(COUNTIF('Vendors & Crew'!$A$5:$A$34,B36)=0,"Worker not in Crew table",IF(C36="","Missing Job ID",IF(COUNTIF(Jobs!$A$5:$A$44,C36)=0,"Unknown Job ID",IF(E36="","Missing hours",IF(A36="","Missing date",""))))))
G37: =IF(B37="","",IF(F37<>"",F37,IFERROR(VLOOKUP(B37,'Vendors & Crew'!$A$5:$D$34,3,FALSE),0))) | H37: =IF(B37="","",E37*G37*(1+Settings!$B$18)) | I37: =IF(B37="","",IFERROR(VLOOKUP(B37,'Vendors & Crew'!$A$5:$D$34,4,FALSE),0)) | J37: =IF(B37="","",E37*I37) | K37: =IF(A37="","",A37-WEEKDAY(A37,2)+7) | L37: =IF(B37="","",IF(D37="","Labor",IFERROR(VLOOKUP(D37,Settings!$E$5:$G$28,3,FALSE),"Labor"))) | M37: =IF(B37="","",IF(COUNTIF('Vendors & Crew'!$A$5:$A$34,B37)=0,"Worker not in Crew table",IF(C37="","Missing Job ID",IF(COUNTIF(Jobs!$A$5:$A$44,C37)=0,"Unknown Job ID",IF(E37="","Missing hours",IF(A37="","Missing date",""))))))
G38: =IF(B38="","",IF(F38<>"",F38,IFERROR(VLOOKUP(B38,'Vendors & Crew'!$A$5:$D$34,3,FALSE),0))) | H38: =IF(B38="","",E38*G38*(1+Settings!$B$18)) | I38: =IF(B38="","",IFERROR(VLOOKUP(B38,'Vendors & Crew'!$A$5:$D$34,4,FALSE),0)) | J38: =IF(B38="","",E38*I38) | K38: =IF(A38="","",A38-WEEKDAY(A38,2)+7) | L38: =IF(B38="","",IF(D38="","Labor",IFERROR(VLOOKUP(D38,Settings!$E$5:$G$28,3,FALSE),"Labor"))) | M38: =IF(B38="","",IF(COUNTIF('Vendors & Crew'!$A$5:$A$34,B38)=0,"Worker not in Crew table",IF(C38="","Missing Job ID",IF(COUNTIF(Jobs!$A$5:$A$44,C38)=0,"Unknown Job ID",IF(E38="","Missing hours",IF(A38="","Missing date",""))))))
G39: =IF(B39="","",IF(F39<>"",F39,IFERROR(VLOOKUP(B39,'Vendors & Crew'!$A$5:$D$34,3,FALSE),0))) | H39: =IF(B39="","",E39*G39*(1+Settings!$B$18)) | I39: =IF(B39="","",IFERROR(VLOOKUP(B39,'Vendors & Crew'!$A$5:$D$34,4,FALSE),0)) | J39: =IF(B39="","",E39*I39) | K39: =IF(A39="","",A39-WEEKDAY(A39,2)+7) | L39: =IF(B39="","",IF(D39="","Labor",IFERROR(VLOOKUP(D39,Settings!$E$5:$G$28,3,FALSE),"Labor"))) | M39: =IF(B39="","",IF(COUNTIF('Vendors & Crew'!$A$5:$A$34,B39)=0,"Worker not in Crew table",IF(C39="","Missing Job ID",IF(COUNTIF(Jobs!$A$5:$A$44,C39)=0,"Unknown Job ID",IF(E39="","Missing hours",IF(A39="","Missing date",""))))))
G40: =IF(B40="","",IF(F40<>"",F40,IFERROR(VLOOKUP(B40,'Vendors & Crew'!$A$5:$D$34,3,FALSE),0))) | H40: =IF(B40="","",E40*G40*(1+Settings!$B$18)) | I40: =IF(B40="","",IFERROR(VLOOKUP(B40,'Vendors & Crew'!$A$5:$D$34,4,FALSE),0)) | J40: =IF(B40="","",E40*I40) | K40: =IF(A40="","",A40-WEEKDAY(A40,2)+7) | L40: =IF(B40="","",IF(D40="","Labor",IFERROR(VLOOKUP(D40,Settings!$E$5:$G$28,3,FALSE),"Labor"))) | M40: =IF(B40="","",IF(COUNTIF('Vendors & Crew'!$A$5:$A$34,B40)=0,"Worker not in Crew table",IF(C40="","Missing Job ID",IF(COUNTIF(Jobs!$A$5:$A$44,C40)=0,"Unknown Job ID",IF(E40="","Missing hours",IF(A40="","Missing date",""))))))
G41: =IF(B41="","",IF(F41<>"",F41,IFERROR(VLOOKUP(B41,'Vendors & Crew'!$A$5:$D$34,3,FALSE),0))) | H41: =IF(B41="","",E41*G41*(1+Settings!$B$18)) | I41: =IF(B41="","",IFERROR(VLOOKUP(B41,'Vendors & Crew'!$A$5:$D$34,4,FALSE),0)) | J41: =IF(B41="","",E41*I41) | K41: =IF(A41="","",A41-WEEKDAY(A41,2)+7) | L41: =IF(B41="","",IF(D41="","Labor",IFERROR(VLOOKUP(D41,Settings!$E$5:$G$28,3,FALSE),"Labor"))) | M41: =IF(B41="","",IF(COUNTIF('Vendors & Crew'!$A$5:$A$34,B41)=0,"Worker not in Crew table",IF(C41="","Missing Job ID",IF(COUNTIF(Jobs!$A$5:$A$44,C41)=0,"Unknown Job ID",IF(E41="","Missing hours",IF(A41="","Missing date",""))))))
G42: =IF(B42="","",IF(F42<>"",F42,IFERROR(VLOOKUP(B42,'Vendors & Crew'!$A$5:$D$34,3,FALSE),0))) | H42: =IF(B42="","",E42*G42*(1+Settings!$B$18)) | I42: =IF(B42="","",IFERROR(VLOOKUP(B42,'Vendors & Crew'!$A$5:$D$34,4,FALSE),0)) | J42: =IF(B42="","",E42*I42) | K42: =IF(A42="","",A42-WEEKDAY(A42,2)+7) | L42: =IF(B42="","",IF(D42="","Labor",IFERROR(VLOOKUP(D42,Settings!$E$5:$G$28,3,FALSE),"Labor"))) | M42: =IF(B42="","",IF(COUNTIF('Vendors & Crew'!$A$5:$A$34,B42)=0,"Worker not in Crew table",IF(C42="","Missing Job ID",IF(COUNTIF(Jobs!$A$5:$A$44,C42)=0,"Unknown Job ID",IF(E42="","Missing hours",IF(A42="","Missing date",""))))))
G43: =IF(B43="","",IF(F43<>"",F43,IFERROR(VLOOKUP(B43,'Vendors & Crew'!$A$5:$D$34,3,FALSE),0))) | H43: =IF(B43="","",E43*G43*(1+Settings!$B$18)) | I43: =IF(B43="","",IFERROR(VLOOKUP(B43,'Vendors & Crew'!$A$5:$D$34,4,FALSE),0)) | J43: =IF(B43="","",E43*I43) | K43: =IF(A43="","",A43-WEEKDAY(A43,2)+7) | L43: =IF(B43="","",IF(D43="","Labor",IFERROR(VLOOKUP(D43,Settings!$E$5:$G$28,3,FALSE),"Labor"))) | M43: =IF(B43="","",IF(COUNTIF('Vendors & Crew'!$A$5:$A$34,B43)=0,"Worker not in Crew table",IF(C43="","Missing Job ID",IF(COUNTIF(Jobs!$A$5:$A$44,C43)=0,"Unknown Job ID",IF(E43="","Missing hours",IF(A43="","Missing date",""))))))
G44: =IF(B44="","",IF(F44<>"",F44,IFERROR(VLOOKUP(B44,'Vendors & Crew'!$A$5:$D$34,3,FALSE),0))) | H44: =IF(B44="","",E44*G44*(1+Settings!$B$18)) | I44: =IF(B44="","",IFERROR(VLOOKUP(B44,'Vendors & Crew'!$A$5:$D$34,4,FALSE),0)) | J44: =IF(B44="","",E44*I44) | K44: =IF(A44="","",A44-WEEKDAY(A44,2)+7) | L44: =IF(B44="","",IF(D44="","Labor",IFERROR(VLOOKUP(D44,Settings!$E$5:$G$28,3,FALSE),"Labor"))) | M44: =IF(B44="","",IF(COUNTIF('Vendors & Crew'!$A$5:$A$34,B44)=0,"Worker not in Crew table",IF(C44="","Missing Job ID",IF(COUNTIF(Jobs!$A$5:$A$44,C44)=0,"Unknown Job ID",IF(E44="","Missing hours",IF(A44="","Missing date",""))))))
G45: =IF(B45="","",IF(F45<>"",F45,IFERROR(VLOOKUP(B45,'Vendors & Crew'!$A$5:$D$34,3,FALSE),0))) | H45: =IF(B45="","",E45*G45*(1+Settings!$B$18)) | I45: =IF(B45="","",IFERROR(VLOOKUP(B45,'Vendors & Crew'!$A$5:$D$34,4,FALSE),0)) | J45: =IF(B45="","",E45*I45) | K45: =IF(A45="","",A45-WEEKDAY(A45,2)+7) | L45: =IF(B45="","",IF(D45="","Labor",IFERROR(VLOOKUP(D45,Settings!$E$5:$G$28,3,FALSE),"Labor"))) | M45: =IF(B45="","",IF(COUNTIF('Vendors & Crew'!$A$5:$A$34,B45)=0,"Worker not in Crew table",IF(C45="","Missing Job ID",IF(COUNTIF(Jobs!$A$5:$A$44,C45)=0,"Unknown Job ID",IF(E45="","Missing hours",IF(A45="","Missing date",""))))))
G46: =IF(B46="","",IF(F46<>"",F46,IFERROR(VLOOKUP(B46,'Vendors & Crew'!$A$5:$D$34,3,FALSE),0))) | H46: =IF(B46="","",E46*G46*(1+Settings!$B$18)) | I46: =IF(B46="","",IFERROR(VLOOKUP(B46,'Vendors & Crew'!$A$5:$D$34,4,FALSE),0)) | J46: =IF(B46="","",E46*I46) | K46: =IF(A46="","",A46-WEEKDAY(A46,2)+7) | L46: =IF(B46="","",IF(D46="","Labor",IFERROR(VLOOKUP(D46,Settings!$E$5:$G$28,3,FALSE),"Labor"))) | M46: =IF(B46="","",IF(COUNTIF('Vendors & Crew'!$A$5:$A$34,B46)=0,"Worker not in Crew table",IF(C46="","Missing Job ID",IF(COUNTIF(Jobs!$A$5:$A$44,C46)=0,"Unknown Job ID",IF(E46="","Missing hours",IF(A46="","Missing date",""))))))
G47: =IF(B47="","",IF(F47<>"",F47,IFERROR(VLOOKUP(B47,'Vendors & Crew'!$A$5:$D$34,3,FALSE),0))) | H47: =IF(B47="","",E47*G47*(1+Settings!$B$18)) | I47: =IF(B47="","",IFERROR(VLOOKUP(B47,'Vendors & Crew'!$A$5:$D$34,4,FALSE),0)) | J47: =IF(B47="","",E47*I47) | K47: =IF(A47="","",A47-WEEKDAY(A47,2)+7) | L47: =IF(B47="","",IF(D47="","Labor",IFERROR(VLOOKUP(D47,Settings!$E$5:$G$28,3,FALSE),"Labor"))) | M47: =IF(B47="","",IF(COUNTIF('Vendors & Crew'!$A$5:$A$34,B47)=0,"Worker not in Crew table",IF(C47="","Missing Job ID",IF(COUNTIF(Jobs!$A$5:$A$44,C47)=0,"Unknown Job ID",IF(E47="","Missing hours",IF(A47="","Missing date",""))))))
... G1004: =IF(B1004="","",IF(F1004<>"",F1004,IFERROR(VLOOKUP(B1004,'Vendors & Crew'!$A$5:$D$34,3,FALSE),0))) | H1004: =IF(B1004="","",E1004*G1004*(1+Settings!$B$18)) | I1004: =IF(B1004="","",IFERROR(VLOOKUP(B1004,'Vendors & Crew'!$A$5:$D$34,4,FALSE),0)) | J1004: =IF(B1004="","",E1004*I1004) | K1004: =IF(A1004="","",A1004-WEEKDAY(A1004,2)+7) | L1004: =IF(B1004="","",IF(D1004="","Labor",IFERROR(VLOOKUP(D1004,Settings!$E$5:$G$28,3,FALSE),"Labor"))) | M1004: =IF(B1004="","",IF(COUNTIF('Vendors & Crew'!$A$5:$A$34,B1004)=0,"Worker not in Crew table",IF(C1004="","Missing Job ID",IF(COUNTIF(Jobs!$A$5:$A$44,C1004)=0,"Unknown Job ID",IF(E1004="","Missing hours",IF(A1004="","Missing date",""))))))
A1005: TOTAL | E1005: =SUM(E5:E1004) | H1005: =SUM(H5:H1004) | J1005: =SUM(J5:J1004)

Sheet Job Costs
A1: Job Costs (actuals)
A2: Materials, subcontractors, equipment, permits and other real costs. Qty × Unit Cost = Amount. Category comes from the cost code. Crew hours belong on the Timesheet.
A4: Date | B4: Job ID | C4: Cost Code | D4: Category | E4: Vendor | F4: Description | G4: Qty or Hours | H4: Unit Cost / Rate | I4: Amount | J4: Paid? | K4: Payment Method | L4: Receipt / Invoice # | M4: Check | N4: Notes
D5: =IF(C5="","",IFERROR(VLOOKUP(C5,Settings!$E$5:$G$28,3,FALSE),"Other")) | I5: =IF(B5="","",G5*H5) | M5: =IF(B5="","",IF(COUNTIF(Jobs!$A$5:$A$44,B5)=0,"Unknown Job ID",IF(C5="","Missing cost code",IF(COUNTIF(Settings!$E$5:$E$28,C5)=0,"Unknown cost code",IF(A5="","Missing date",IF(OR(G5="",H5=""),"Missing qty or cost",""))))))
D6: =IF(C6="","",IFERROR(VLOOKUP(C6,Settings!$E$5:$G$28,3,FALSE),"Other")) | I6: =IF(B6="","",G6*H6) | M6: =IF(B6="","",IF(COUNTIF(Jobs!$A$5:$A$44,B6)=0,"Unknown Job ID",IF(C6="","Missing cost code",IF(COUNTIF(Settings!$E$5:$E$28,C6)=0,"Unknown cost code",IF(A6="","Missing date",IF(OR(G6="",H6=""),"Missing qty or cost",""))))))
D7: =IF(C7="","",IFERROR(VLOOKUP(C7,Settings!$E$5:$G$28,3,FALSE),"Other")) | I7: =IF(B7="","",G7*H7) | M7: =IF(B7="","",IF(COUNTIF(Jobs!$A$5:$A$44,B7)=0,"Unknown Job ID",IF(C7="","Missing cost code",IF(COUNTIF(Settings!$E$5:$E$28,C7)=0,"Unknown cost code",IF(A7="","Missing date",IF(OR(G7="",H7=""),"Missing qty or cost",""))))))
D8: =IF(C8="","",IFERROR(VLOOKUP(C8,Settings!$E$5:$G$28,3,FALSE),"Other")) | I8: =IF(B8="","",G8*H8) | M8: =IF(B8="","",IF(COUNTIF(Jobs!$A$5:$A$44,B8)=0,"Unknown Job ID",IF(C8="","Missing cost code",IF(COUNTIF(Settings!$E$5:$E$28,C8)=0,"Unknown cost code",IF(A8="","Missing date",IF(OR(G8="",H8=""),"Missing qty or cost",""))))))
D9: =IF(C9="","",IFERROR(VLOOKUP(C9,Settings!$E$5:$G$28,3,FALSE),"Other")) | I9: =IF(B9="","",G9*H9) | M9: =IF(B9="","",IF(COUNTIF(Jobs!$A$5:$A$44,B9)=0,"Unknown Job ID",IF(C9="","Missing cost code",IF(COUNTIF(Settings!$E$5:$E$28,C9)=0,"Unknown cost code",IF(A9="","Missing date",IF(OR(G9="",H9=""),"Missing qty or cost",""))))))
D10: =IF(C10="","",IFERROR(VLOOKUP(C10,Settings!$E$5:$G$28,3,FALSE),"Other")) | I10: =IF(B10="","",G10*H10) | M10: =IF(B10="","",IF(COUNTIF(Jobs!$A$5:$A$44,B10)=0,"Unknown Job ID",IF(C10="","Missing cost code",IF(COUNTIF(Settings!$E$5:$E$28,C10)=0,"Unknown cost code",IF(A10="","Missing date",IF(OR(G10="",H10=""),"Missing qty or cost",""))))))
D11: =IF(C11="","",IFERROR(VLOOKUP(C11,Settings!$E$5:$G$28,3,FALSE),"Other")) | I11: =IF(B11="","",G11*H11) | M11: =IF(B11="","",IF(COUNTIF(Jobs!$A$5:$A$44,B11)=0,"Unknown Job ID",IF(C11="","Missing cost code",IF(COUNTIF(Settings!$E$5:$E$28,C11)=0,"Unknown cost code",IF(A11="","Missing date",IF(OR(G11="",H11=""),"Missing qty or cost",""))))))
D12: =IF(C12="","",IFERROR(VLOOKUP(C12,Settings!$E$5:$G$28,3,FALSE),"Other")) | I12: =IF(B12="","",G12*H12) | M12: =IF(B12="","",IF(COUNTIF(Jobs!$A$5:$A$44,B12)=0,"Unknown Job ID",IF(C12="","Missing cost code",IF(COUNTIF(Settings!$E$5:$E$28,C12)=0,"Unknown cost code",IF(A12="","Missing date",IF(OR(G12="",H12=""),"Missing qty or cost",""))))))
D13: =IF(C13="","",IFERROR(VLOOKUP(C13,Settings!$E$5:$G$28,3,FALSE),"Other")) | I13: =IF(B13="","",G13*H13) | M13: =IF(B13="","",IF(COUNTIF(Jobs!$A$5:$A$44,B13)=0,"Unknown Job ID",IF(C13="","Missing cost code",IF(COUNTIF(Settings!$E$5:$E$28,C13)=0,"Unknown cost code",IF(A13="","Missing date",IF(OR(G13="",H13=""),"Missing qty or cost",""))))))
D14: =IF(C14="","",IFERROR(VLOOKUP(C14,Settings!$E$5:$G$28,3,FALSE),"Other")) | I14: =IF(B14="","",G14*H14) | M14: =IF(B14="","",IF(COUNTIF(Jobs!$A$5:$A$44,B14)=0,"Unknown Job ID",IF(C14="","Missing cost code",IF(COUNTIF(Settings!$E$5:$E$28,C14)=0,"Unknown cost code",IF(A14="","Missing date",IF(OR(G14="",H14=""),"Missing qty or cost",""))))))
D15: =IF(C15="","",IFERROR(VLOOKUP(C15,Settings!$E$5:$G$28,3,FALSE),"Other")) | I15: =IF(B15="","",G15*H15) | M15: =IF(B15="","",IF(COUNTIF(Jobs!$A$5:$A$44,B15)=0,"Unknown Job ID",IF(C15="","Missing cost code",IF(COUNTIF(Settings!$E$5:$E$28,C15)=0,"Unknown cost code",IF(A15="","Missing date",IF(OR(G15="",H15=""),"Missing qty or cost",""))))))
D16: =IF(C16="","",IFERROR(VLOOKUP(C16,Settings!$E$5:$G$28,3,FALSE),"Other")) | I16: =IF(B16="","",G16*H16) | M16: =IF(B16="","",IF(COUNTIF(Jobs!$A$5:$A$44,B16)=0,"Unknown Job ID",IF(C16="","Missing cost code",IF(COUNTIF(Settings!$E$5:$E$28,C16)=0,"Unknown cost code",IF(A16="","Missing date",IF(OR(G16="",H16=""),"Missing qty or cost",""))))))
... D1004: =IF(C1004="","",IFERROR(VLOOKUP(C1004,Settings!$E$5:$G$28,3,FALSE),"Other")) | I1004: =IF(B1004="","",G1004*H1004) | M1004: =IF(B1004="","",IF(COUNTIF(Jobs!$A$5:$A$44,B1004)=0,"Unknown Job ID",IF(C1004="","Missing cost code",IF(COUNTIF(Settings!$E$5:$E$28,C1004)=0,"Unknown cost code",IF(A1004="","Missing date",IF(OR(G1004="",H1004=""),"Missing qty or cost",""))))))
F1005: TOTAL | I1005: =SUM(I5:I1004)

Sheet Mileage
A1: Mileage log
A2: Job-related driving. Rate comes from Settings. Amount counts toward the job's actual cost under the cost code you pick (default 22 Fuel & mileage).
A4: Date | B4: Job ID | C4: Cost Code | D4: From | E4: To | F4: Purpose | G4: Miles | H4: Rate | I4: Amount | J4: Category | K4: Check | L4: Notes
H5: =IF(B5="","",Settings!$B$15) | I5: =IF(B5="","",G5*H5) | J5: =IF(B5="","",IF(C5="","Other",IFERROR(VLOOKUP(C5,Settings!$E$5:$G$28,3,FALSE),"Other"))) | K5: =IF(B5="","",IF(COUNTIF(Jobs!$A$5:$A$44,B5)=0,"Unknown Job ID",IF(G5="","Missing miles",IF(A5="","Missing date",""))))
H6: =IF(B6="","",Settings!$B$15) | I6: =IF(B6="","",G6*H6) | J6: =IF(B6="","",IF(C6="","Other",IFERROR(VLOOKUP(C6,Settings!$E$5:$G$28,3,FALSE),"Other"))) | K6: =IF(B6="","",IF(COUNTIF(Jobs!$A$5:$A$44,B6)=0,"Unknown Job ID",IF(G6="","Missing miles",IF(A6="","Missing date",""))))
H7: =IF(B7="","",Settings!$B$15) | I7: =IF(B7="","",G7*H7) | J7: =IF(B7="","",IF(C7="","Other",IFERROR(VLOOKUP(C7,Settings!$E$5:$G$28,3,FALSE),"Other"))) | K7: =IF(B7="","",IF(COUNTIF(Jobs!$A$5:$A$44,B7)=0,"Unknown Job ID",IF(G7="","Missing miles",IF(A7="","Missing date",""))))
H8: =IF(B8="","",Settings!$B$15) | I8: =IF(B8="","",G8*H8) | J8: =IF(B8="","",IF(C8="","Other",IFERROR(VLOOKUP(C8,Settings!$E$5:$G$28,3,FALSE),"Other"))) | K8: =IF(B8="","",IF(COUNTIF(Jobs!$A$5:$A$44,B8)=0,"Unknown Job ID",IF(G8="","Missing miles",IF(A8="","Missing date",""))))
H9: =IF(B9="","",Settings!$B$15) | I9: =IF(B9="","",G9*H9) | J9: =IF(B9="","",IF(C9="","Other",IFERROR(VLOOKUP(C9,Settings!$E$5:$G$28,3,FALSE),"Other"))) | K9: =IF(B9="","",IF(COUNTIF(Jobs!$A$5:$A$44,B9)=0,"Unknown Job ID",IF(G9="","Missing miles",IF(A9="","Missing date",""))))
H10: =IF(B10="","",Settings!$B$15) | I10: =IF(B10="","",G10*H10) | J10: =IF(B10="","",IF(C10="","Other",IFERROR(VLOOKUP(C10,Settings!$E$5:$G$28,3,FALSE),"Other"))) | K10: =IF(B10="","",IF(COUNTIF(Jobs!$A$5:$A$44,B10)=0,"Unknown Job ID",IF(G10="","Missing miles",IF(A10="","Missing date",""))))
H11: =IF(B11="","",Settings!$B$15) | I11: =IF(B11="","",G11*H11) | J11: =IF(B11="","",IF(C11="","Other",IFERROR(VLOOKUP(C11,Settings!$E$5:$G$28,3,FALSE),"Other"))) | K11: =IF(B11="","",IF(COUNTIF(Jobs!$A$5:$A$44,B11)=0,"Unknown Job ID",IF(G11="","Missing miles",IF(A11="","Missing date",""))))
H12: =IF(B12="","",Settings!$B$15) | I12: =IF(B12="","",G12*H12) | J12: =IF(B12="","",IF(C12="","Other",IFERROR(VLOOKUP(C12,Settings!$E$5:$G$28,3,FALSE),"Other"))) | K12: =IF(B12="","",IF(COUNTIF(Jobs!$A$5:$A$44,B12)=0,"Unknown Job ID",IF(G12="","Missing miles",IF(A12="","Missing date",""))))
H13: =IF(B13="","",Settings!$B$15) | I13: =IF(B13="","",G13*H13) | J13: =IF(B13="","",IF(C13="","Other",IFERROR(VLOOKUP(C13,Settings!$E$5:$G$28,3,FALSE),"Other"))) | K13: =IF(B13="","",IF(COUNTIF(Jobs!$A$5:$A$44,B13)=0,"Unknown Job ID",IF(G13="","Missing miles",IF(A13="","Missing date",""))))
H14: =IF(B14="","",Settings!$B$15) | I14: =IF(B14="","",G14*H14) | J14: =IF(B14="","",IF(C14="","Other",IFERROR(VLOOKUP(C14,Settings!$E$5:$G$28,3,FALSE),"Other"))) | K14: =IF(B14="","",IF(COUNTIF(Jobs!$A$5:$A$44,B14)=0,"Unknown Job ID",IF(G14="","Missing miles",IF(A14="","Missing date",""))))
H15: =IF(B15="","",Settings!$B$15) | I15: =IF(B15="","",G15*H15) | J15: =IF(B15="","",IF(C15="","Other",IFERROR(VLOOKUP(C15,Settings!$E$5:$G$28,3,FALSE),"Other"))) | K15: =IF(B15="","",IF(COUNTIF(Jobs!$A$5:$A$44,B15)=0,"Unknown Job ID",IF(G15="","Missing miles",IF(A15="","Missing date",""))))
H16: =IF(B16="","",Settings!$B$15) | I16: =IF(B16="","",G16*H16) | J16: =IF(B16="","",IF(C16="","Other",IFERROR(VLOOKUP(C16,Settings!$E$5:$G$28,3,FALSE),"Other"))) | K16: =IF(B16="","",IF(COUNTIF(Jobs!$A$5:$A$44,B16)=0,"Unknown Job ID",IF(G16="","Missing miles",IF(A16="","Missing date",""))))
... H304: =IF(B304="","",Settings!$B$15) | I304: =IF(B304="","",G304*H304) | J304: =IF(B304="","",IF(C304="","Other",IFERROR(VLOOKUP(C304,Settings!$E$5:$G$28,3,FALSE),"Other"))) | K304: =IF(B304="","",IF(COUNTIF(Jobs!$A$5:$A$44,B304)=0,"Unknown Job ID",IF(G304="","Missing miles",IF(A304="","Missing date",""))))
A305: TOTAL | G305: =SUM(G5:G304) | I305: =SUM(I5:I304)

Sheet Daily Log
A1: Daily Log
A2: A dated record per job: weather, crew, work done, problems, inspections. Hours pull from the Timesheet for that date and job. Useful for change-order and delay disputes.
A4: Date | B4: Job ID | C4: Weather | D4: Crew on site | E4: Hours logged (Timesheet) | F4: Work performed | G4: Issues / delays | H4: Inspections / visitors | I4: Check
E5: =IF(OR(B5="",A5=""),"",SUMIFS(Timesheet!$E$5:$E$1004,Timesheet!$C$5:$C$1004,B5,Timesheet!$A$5:$A$1004,A5)) | I5: =IF(B5="","",IF(COUNTIF(Jobs!$A$5:$A$44,B5)=0,"Unknown Job ID",IF(A5="","Missing date","")))
E6: =IF(OR(B6="",A6=""),"",SUMIFS(Timesheet!$E$5:$E$1004,Timesheet!$C$5:$C$1004,B6,Timesheet!$A$5:$A$1004,A6)) | I6: =IF(B6="","",IF(COUNTIF(Jobs!$A$5:$A$44,B6)=0,"Unknown Job ID",IF(A6="","Missing date","")))
E7: =IF(OR(B7="",A7=""),"",SUMIFS(Timesheet!$E$5:$E$1004,Timesheet!$C$5:$C$1004,B7,Timesheet!$A$5:$A$1004,A7)) | I7: =IF(B7="","",IF(COUNTIF(Jobs!$A$5:$A$44,B7)=0,"Unknown Job ID",IF(A7="","Missing date","")))
E8: =IF(OR(B8="",A8=""),"",SUMIFS(Timesheet!$E$5:$E$1004,Timesheet!$C$5:$C$1004,B8,Timesheet!$A$5:$A$1004,A8)) | I8: =IF(B8="","",IF(COUNTIF(Jobs!$A$5:$A$44,B8)=0,"Unknown Job ID",IF(A8="","Missing date","")))
E9: =IF(OR(B9="",A9=""),"",SUMIFS(Timesheet!$E$5:$E$1004,Timesheet!$C$5:$C$1004,B9,Timesheet!$A$5:$A$1004,A9)) | I9: =IF(B9="","",IF(COUNTIF(Jobs!$A$5:$A$44,B9)=0,"Unknown Job ID",IF(A9="","Missing date","")))
E10: =IF(OR(B10="",A10=""),"",SUMIFS(Timesheet!$E$5:$E$1004,Timesheet!$C$5:$C$1004,B10,Timesheet!$A$5:$A$1004,A10)) | I10: =IF(B10="","",IF(COUNTIF(Jobs!$A$5:$A$44,B10)=0,"Unknown Job ID",IF(A10="","Missing date","")))
E11: =IF(OR(B11="",A11=""),"",SUMIFS(Timesheet!$E$5:$E$1004,Timesheet!$C$5:$C$1004,B11,Timesheet!$A$5:$A$1004,A11)) | I11: =IF(B11="","",IF(COUNTIF(Jobs!$A$5:$A$44,B11)=0,"Unknown Job ID",IF(A11="","Missing date","")))
E12: =IF(OR(B12="",A12=""),"",SUMIFS(Timesheet!$E$5:$E$1004,Timesheet!$C$5:$C$1004,B12,Timesheet!$A$5:$A$1004,A12)) | I12: =IF(B12="","",IF(COUNTIF(Jobs!$A$5:$A$44,B12)=0,"Unknown Job ID",IF(A12="","Missing date","")))
E13: =IF(OR(B13="",A13=""),"",SUMIFS(Timesheet!$E$5:$E$1004,Timesheet!$C$5:$C$1004,B13,Timesheet!$A$5:$A$1004,A13)) | I13: =IF(B13="","",IF(COUNTIF(Jobs!$A$5:$A$44,B13)=0,"Unknown Job ID",IF(A13="","Missing date","")))
E14: =IF(OR(B14="",A14=""),"",SUMIFS(Timesheet!$E$5:$E$1004,Timesheet!$C$5:$C$1004,B14,Timesheet!$A$5:$A$1004,A14)) | I14: =IF(B14="","",IF(COUNTIF(Jobs!$A$5:$A$44,B14)=0,"Unknown Job ID",IF(A14="","Missing date","")))
E15: =IF(OR(B15="",A15=""),"",SUMIFS(Timesheet!$E$5:$E$1004,Timesheet!$C$5:$C$1004,B15,Timesheet!$A$5:$A$1004,A15)) | I15: =IF(B15="","",IF(COUNTIF(Jobs!$A$5:$A$44,B15)=0,"Unknown Job ID",IF(A15="","Missing date","")))
E16: =IF(OR(B16="",A16=""),"",SUMIFS(Timesheet!$E$5:$E$1004,Timesheet!$C$5:$C$1004,B16,Timesheet!$A$5:$A$1004,A16)) | I16: =IF(B16="","",IF(COUNTIF(Jobs!$A$5:$A$44,B16)=0,"Unknown Job ID",IF(A16="","Missing date","")))
... E304: =IF(OR(B304="",A304=""),"",SUMIFS(Timesheet!$E$5:$E$1004,Timesheet!$C$5:$C$1004,B304,Timesheet!$A$5:$A$1004,A304)) | I304: =IF(B304="","",IF(COUNTIF(Jobs!$A$5:$A$44,B304)=0,"Unknown Job ID",IF(A304="","Missing date","")))

Sheet Change Orders
A1: Change Orders
A2: Approved change orders add to the Revised Contract and the job budget. Pending and Rejected are ignored. Print a signature-ready form on the CO Form sheet.
A3: ="Suggested next CO #: "&(MAX(A5:A104)+1)
A4: CO # | B4: Job ID | C4: Date | D4: Description | E4: Status | F4: Markup % | G4: Added Cost (budget) | H4: Price to Client | I4: Added Profit | J4: Schedule impact (days) | K4: Client approved date | L4: Check | M4: Notes
H5: =IF(B5="","",G5*(1+IF(F5="",Settings!$B$27,F5))) | I5: =IF(B5="","",H5-G5) | L5: =IF(B5="","",IF(COUNTIF(Jobs!$A$5:$A$44,B5)=0,"Unknown Job ID",IF(COUNTIF('Change Orders'!$A$5:$A$104,A5)>1,"Duplicate CO #",IF(E5="","Missing status",IF(AND(E5="Approved",K5=""),"Approved without client date","")))))
H6: =IF(B6="","",G6*(1+IF(F6="",Settings!$B$27,F6))) | I6: =IF(B6="","",H6-G6) | L6: =IF(B6="","",IF(COUNTIF(Jobs!$A$5:$A$44,B6)=0,"Unknown Job ID",IF(COUNTIF('Change Orders'!$A$5:$A$104,A6)>1,"Duplicate CO #",IF(E6="","Missing status",IF(AND(E6="Approved",K6=""),"Approved without client date","")))))
H7: =IF(B7="","",G7*(1+IF(F7="",Settings!$B$27,F7))) | I7: =IF(B7="","",H7-G7) | L7: =IF(B7="","",IF(COUNTIF(Jobs!$A$5:$A$44,B7)=0,"Unknown Job ID",IF(COUNTIF('Change Orders'!$A$5:$A$104,A7)>1,"Duplicate CO #",IF(E7="","Missing status",IF(AND(E7="Approved",K7=""),"Approved without client date","")))))
H8: =IF(B8="","",G8*(1+IF(F8="",Settings!$B$27,F8))) | I8: =IF(B8="","",H8-G8) | L8: =IF(B8="","",IF(COUNTIF(Jobs!$A$5:$A$44,B8)=0,"Unknown Job ID",IF(COUNTIF('Change Orders'!$A$5:$A$104,A8)>1,"Duplicate CO #",IF(E8="","Missing status",IF(AND(E8="Approved",K8=""),"Approved without client date","")))))
H9: =IF(B9="","",G9*(1+IF(F9="",Settings!$B$27,F9))) | I9: =IF(B9="","",H9-G9) | L9: =IF(B9="","",IF(COUNTIF(Jobs!$A$5:$A$44,B9)=0,"Unknown Job ID",IF(COUNTIF('Change Orders'!$A$5:$A$104,A9)>1,"Duplicate CO #",IF(E9="","Missing status",IF(AND(E9="Approved",K9=""),"Approved without client date","")))))
H10: =IF(B10="","",G10*(1+IF(F10="",Settings!$B$27,F10))) | I10: =IF(B10="","",H10-G10) | L10: =IF(B10="","",IF(COUNTIF(Jobs!$A$5:$A$44,B10)=0,"Unknown Job ID",IF(COUNTIF('Change Orders'!$A$5:$A$104,A10)>1,"Duplicate CO #",IF(E10="","Missing status",IF(AND(E10="Approved",K10=""),"Approved without client date","")))))
H11: =IF(B11="","",G11*(1+IF(F11="",Settings!$B$27,F11))) | I11: =IF(B11="","",H11-G11) | L11: =IF(B11="","",IF(COUNTIF(Jobs!$A$5:$A$44,B11)=0,"Unknown Job ID",IF(COUNTIF('Change Orders'!$A$5:$A$104,A11)>1,"Duplicate CO #",IF(E11="","Missing status",IF(AND(E11="Approved",K11=""),"Approved without client date","")))))
H12: =IF(B12="","",G12*(1+IF(F12="",Settings!$B$27,F12))) | I12: =IF(B12="","",H12-G12) | L12: =IF(B12="","",IF(COUNTIF(Jobs!$A$5:$A$44,B12)=0,"Unknown Job ID",IF(COUNTIF('Change Orders'!$A$5:$A$104,A12)>1,"Duplicate CO #",IF(E12="","Missing status",IF(AND(E12="Approved",K12=""),"Approved without client date","")))))
H13: =IF(B13="","",G13*(1+IF(F13="",Settings!$B$27,F13))) | I13: =IF(B13="","",H13-G13) | L13: =IF(B13="","",IF(COUNTIF(Jobs!$A$5:$A$44,B13)=0,"Unknown Job ID",IF(COUNTIF('Change Orders'!$A$5:$A$104,A13)>1,"Duplicate CO #",IF(E13="","Missing status",IF(AND(E13="Approved",K13=""),"Approved without client date","")))))
H14: =IF(B14="","",G14*(1+IF(F14="",Settings!$B$27,F14))) | I14: =IF(B14="","",H14-G14) | L14: =IF(B14="","",IF(COUNTIF(Jobs!$A$5:$A$44,B14)=0,"Unknown Job ID",IF(COUNTIF('Change Orders'!$A$5:$A$104,A14)>1,"Duplicate CO #",IF(E14="","Missing status",IF(AND(E14="Approved",K14=""),"Approved without client date","")))))
H15: =IF(B15="","",G15*(1+IF(F15="",Settings!$B$27,F15))) | I15: =IF(B15="","",H15-G15) | L15: =IF(B15="","",IF(COUNTIF(Jobs!$A$5:$A$44,B15)=0,"Unknown Job ID",IF(COUNTIF('Change Orders'!$A$5:$A$104,A15)>1,"Duplicate CO #",IF(E15="","Missing status",IF(AND(E15="Approved",K15=""),"Approved without client date","")))))
H16: =IF(B16="","",G16*(1+IF(F16="",Settings!$B$27,F16))) | I16: =IF(B16="","",H16-G16) | L16: =IF(B16="","",IF(COUNTIF(Jobs!$A$5:$A$44,B16)=0,"Unknown Job ID",IF(COUNTIF('Change Orders'!$A$5:$A$104,A16)>1,"Duplicate CO #",IF(E16="","Missing status",IF(AND(E16="Approved",K16=""),"Approved without client date","")))))
... H104: =IF(B104="","",G104*(1+IF(F104="",Settings!$B$27,F104))) | I104: =IF(B104="","",H104-G104) | L104: =IF(B104="","",IF(COUNTIF(Jobs!$A$5:$A$44,B104)=0,"Unknown Job ID",IF(COUNTIF('Change Orders'!$A$5:$A$104,A104)>1,"Duplicate CO #",IF(E104="","Missing status",IF(AND(E104="Approved",K104=""),"Approved without client date","")))))

Sheet CO Form
A1: CHANGE ORDER
H2: CO #
H3: ← pick a change order; the form at left fills in. Columns H–I never print.
B4: CONTRACTOR | E4: CLIENT
B5: =Settings!$B$5&"" | E5: =IFERROR(INDEX(Jobs!$B$5:$B$44,MATCH(IFERROR(INDEX('Change Orders'!$B$5:$B$104,MATCH($I$2,'Change Orders'!$A$5:$A$104,0)),""),Jobs!$A$5:$A$44,0)),"")
B6: =Settings!$B$6&"" | E6: =IFERROR(INDEX(Clients!$B$5:$B$104,MATCH(IFERROR(INDEX(Jobs!$B$5:$B$44,MATCH(IFERROR(INDEX('Change Orders'!$B$5:$B$104,MATCH($I$2,'Change Orders'!$A$5:$A$104,0)),""),Jobs!$A$5:$A$44,0)),""),Clients!$A$5:$A$104,0)),"")
B7: =Settings!$B$7&"" | E7: =IFERROR(INDEX(Clients!$E$5:$E$104,MATCH(IFERROR(INDEX(Jobs!$B$5:$B$44,MATCH(IFERROR(INDEX('Change Orders'!$B$5:$B$104,MATCH($I$2,'Change Orders'!$A$5:$A$104,0)),""),Jobs!$A$5:$A$44,0)),""),Clients!$A$5:$A$104,0)),"")
B9: Job | E9: =IF($I$2="","",IFERROR(INDEX('Change Orders'!$B$5:$B$104,MATCH($I$2,'Change Orders'!$A$5:$A$104,0)),"")&" — "&IFERROR(INDEX(Jobs!$C$5:$C$44,MATCH(IFERROR(INDEX('Change Orders'!$B$5:$B$104,MATCH($I$2,'Change Orders'!$A$5:$A$104,0)),""),Jobs!$A$5:$A$44,0)),""))
B10: Change order date | E10: =IFERROR(INDEX('Change Orders'!$C$5:$C$104,MATCH($I$2,'Change Orders'!$A$5:$A$104,0)),"")
B11: Description of change | E11: =IFERROR(INDEX('Change Orders'!$D$5:$D$104,MATCH($I$2,'Change Orders'!$A$5:$A$104,0)),"")
B12: Schedule impact (days) | E12: =IFERROR(INDEX('Change Orders'!$J$5:$J$104,MATCH($I$2,'Change Orders'!$A$5:$A$104,0)),"")
B13: Revised target completion | E13: =IF(OR($I$2="",IFERROR(INDEX(Jobs!$F$5:$F$44,MATCH(IFERROR(INDEX('Change Orders'!$B$5:$B$104,MATCH($I$2,'Change Orders'!$A$5:$A$104,0)),""),Jobs!$A$5:$A$44,0)),"")=""),"",IFERROR(INDEX(Jobs!$F$5:$F$44,MATCH(IFERROR(INDEX('Change Orders'!$B$5:$B$104,MATCH($I$2,'Change Orders'!$A$5:$A$104,0)),""),Jobs!$A$5:$A$44,0)),"")+IF(IFERROR(INDEX('Change Orders'!$J$5:$J$104,MATCH($I$2,'Change Orders'!$A$5:$A$104,0)),"")="",0,IFERROR(INDEX('Change Orders'!$J$5:$J$104,MATCH($I$2,'Change Orders'!$A$5:$A$104,0)),"")))
B14: Price of this change | E14: =IFERROR(INDEX('Change Orders'!$H$5:$H$104,MATCH($I$2,'Change Orders'!$A$5:$A$104,0)),"")
B15: Original contract value | E15: =IF(IFERROR(INDEX(Jobs!$I$5:$I$44,MATCH(IFERROR(INDEX('Change Orders'!$B$5:$B$104,MATCH($I$2,'Change Orders'!$A$5:$A$104,0)),""),Jobs!$A$5:$A$44,0)),"")="",IFERROR(INDEX(Jobs!$H$5:$H$44,MATCH(IFERROR(INDEX('Change Orders'!$B$5:$B$104,MATCH($I$2,'Change Orders'!$A$5:$A$104,0)),""),Jobs!$A$5:$A$44,0)),""),IFERROR(INDEX(Jobs!$I$5:$I$44,MATCH(IFERROR(INDEX('Change Orders'!$B$5:$B$104,MATCH($I$2,'Change Orders'!$A$5:$A$104,0)),""),Jobs!$A$5:$A$44,0)),""))
B16: Previously approved change orders | E16: =SUMIFS('Change Orders'!$H$5:$H$104,'Change Orders'!$B$5:$B$104,IFERROR(INDEX('Change Orders'!$B$5:$B$104,MATCH($I$2,'Change Orders'!$A$5:$A$104,0)),""),'Change Orders'!$E$5:$E$104,"Approved")-IF(IFERROR(INDEX('Change Orders'!$E$5:$E$104,MATCH($I$2,'Change Orders'!$A$5:$A$104,0)),"")="Approved",IFERROR(INDEX('Change Orders'!$H$5:$H$104,MATCH($I$2,'Change Orders'!$A$5:$A$104,0)),""),0)
B17: Revised contract total after this change | E17: =IF($I$2="","",E15+E16+E14)
B18: Status | E18: =IFERROR(INDEX('Change Orders'!$E$5:$E$104,MATCH($I$2,'Change Orders'!$A$5:$A$104,0)),"")
B20: Terms
B21: =Settings!$B$33
B23: Client signature: ______________________________ Date: ____________
B24: Contractor signature: __________________________ Date: ____________

Sheet Invoices
A1: Invoices
A2: One row per invoice sent. Paid to Date pulls from Payments by Invoice #. Status and aging use today's date and the grace days in Settings.
A3: ="Suggested next: INV-"&Settings!$B$14&"-"&TEXT(COUNTA(A5:A204)+1,"000")
A4: Invoice # | B4: Job ID | C4: Invoice Date | D4: Due Date | E4: Amount | F4: Description | G4: Paid to Date | H4: Balance | I4: Status | J4: Days Overdue | K4: Aging Bucket | L4: Check | M4: Client | N4: Stmt Line # | O4: Notes
G5: =IF(A5="","",SUMIFS(Payments!$D$5:$D$304,Payments!$C$5:$C$304,A5)) | H5: =IF(A5="","",E5-G5) | I5: =IF(A5="","",IF(H5<=0,"Paid",IF(AND(D5<>"",TODAY()>D5+Settings!$B$13),"Overdue",IF(G5>0,"Partial","Open")))) | J5: =IF(A5="","",IF(I5="Overdue",TODAY()-D5,0)) | K5: =IF(A5="","",IF(H5<=0,"Paid",IF(OR(D5="",TODAY()<=D5),"Current",IF(TODAY()-D5<=30,"1-30",IF(TODAY()-D5<=60,"31-60",IF(TODAY()-D5<=90,"61-90","90+")))))) | L5: =IF(A5="","",IF(COUNTIF(Invoices!$A$5:$A$204,A5)>1,"Duplicate invoice #",IF(B5="","Missing Job ID",IF(COUNTIF(Jobs!$A$5:$A$44,B5)=0,"Unknown Job ID",IF(D5="","Missing due date",IF(E5="","Missing amount","")))))) | M5: =IF(A5="","",IFERROR(INDEX(Jobs!$B$5:$B$44,MATCH(B5,Jobs!$A$5:$A$44,0)),"")) | N5: =IF(AND(A5<>"",M5<>"",M5='Client Statement'!$L$2),COUNTIF(M$5:M5,'Client Statement'!$L$2),"")
G6: =IF(A6="","",SUMIFS(Payments!$D$5:$D$304,Payments!$C$5:$C$304,A6)) | H6: =IF(A6="","",E6-G6) | I6: =IF(A6="","",IF(H6<=0,"Paid",IF(AND(D6<>"",TODAY()>D6+Settings!$B$13),"Overdue",IF(G6>0,"Partial","Open")))) | J6: =IF(A6="","",IF(I6="Overdue",TODAY()-D6,0)) | K6: =IF(A6="","",IF(H6<=0,"Paid",IF(OR(D6="",TODAY()<=D6),"Current",IF(TODAY()-D6<=30,"1-30",IF(TODAY()-D6<=60,"31-60",IF(TODAY()-D6<=90,"61-90","90+")))))) | L6: =IF(A6="","",IF(COUNTIF(Invoices!$A$5:$A$204,A6)>1,"Duplicate invoice #",IF(B6="","Missing Job ID",IF(COUNTIF(Jobs!$A$5:$A$44,B6)=0,"Unknown Job ID",IF(D6="","Missing due date",IF(E6="","Missing amount","")))))) | M6: =IF(A6="","",IFERROR(INDEX(Jobs!$B$5:$B$44,MATCH(B6,Jobs!$A$5:$A$44,0)),"")) | N6: =IF(AND(A6<>"",M6<>"",M6='Client Statement'!$L$2),COUNTIF(M$5:M6,'Client Statement'!$L$2),"")
G7: =IF(A7="","",SUMIFS(Payments!$D$5:$D$304,Payments!$C$5:$C$304,A7)) | H7: =IF(A7="","",E7-G7) | I7: =IF(A7="","",IF(H7<=0,"Paid",IF(AND(D7<>"",TODAY()>D7+Settings!$B$13),"Overdue",IF(G7>0,"Partial","Open")))) | J7: =IF(A7="","",IF(I7="Overdue",TODAY()-D7,0)) | K7: =IF(A7="","",IF(H7<=0,"Paid",IF(OR(D7="",TODAY()<=D7),"Current",IF(TODAY()-D7<=30,"1-30",IF(TODAY()-D7<=60,"31-60",IF(TODAY()-D7<=90,"61-90","90+")))))) | L7: =IF(A7="","",IF(COUNTIF(Invoices!$A$5:$A$204,A7)>1,"Duplicate invoice #",IF(B7="","Missing Job ID",IF(COUNTIF(Jobs!$A$5:$A$44,B7)=0,"Unknown Job ID",IF(D7="","Missing due date",IF(E7="","Missing amount","")))))) | M7: =IF(A7="","",IFERROR(INDEX(Jobs!$B$5:$B$44,MATCH(B7,Jobs!$A$5:$A$44,0)),"")) | N7: =IF(AND(A7<>"",M7<>"",M7='Client Statement'!$L$2),COUNTIF(M$5:M7,'Client Statement'!$L$2),"")
G8: =IF(A8="","",SUMIFS(Payments!$D$5:$D$304,Payments!$C$5:$C$304,A8)) | H8: =IF(A8="","",E8-G8) | I8: =IF(A8="","",IF(H8<=0,"Paid",IF(AND(D8<>"",TODAY()>D8+Settings!$B$13),"Overdue",IF(G8>0,"Partial","Open")))) | J8: =IF(A8="","",IF(I8="Overdue",TODAY()-D8,0)) | K8: =IF(A8="","",IF(H8<=0,"Paid",IF(OR(D8="",TODAY()<=D8),"Current",IF(TODAY()-D8<=30,"1-30",IF(TODAY()-D8<=60,"31-60",IF(TODAY()-D8<=90,"61-90","90+")))))) | L8: =IF(A8="","",IF(COUNTIF(Invoices!$A$5:$A$204,A8)>1,"Duplicate invoice #",IF(B8="","Missing Job ID",IF(COUNTIF(Jobs!$A$5:$A$44,B8)=0,"Unknown Job ID",IF(D8="","Missing due date",IF(E8="","Missing amount","")))))) | M8: =IF(A8="","",IFERROR(INDEX(Jobs!$B$5:$B$44,MATCH(B8,Jobs!$A$5:$A$44,0)),"")) | N8: =IF(AND(A8<>"",M8<>"",M8='Client Statement'!$L$2),COUNTIF(M$5:M8,'Client Statement'!$L$2),"")
G9: =IF(A9="","",SUMIFS(Payments!$D$5:$D$304,Payments!$C$5:$C$304,A9)) | H9: =IF(A9="","",E9-G9) | I9: =IF(A9="","",IF(H9<=0,"Paid",IF(AND(D9<>"",TODAY()>D9+Settings!$B$13),"Overdue",IF(G9>0,"Partial","Open")))) | J9: =IF(A9="","",IF(I9="Overdue",TODAY()-D9,0)) | K9: =IF(A9="","",IF(H9<=0,"Paid",IF(OR(D9="",TODAY()<=D9),"Current",IF(TODAY()-D9<=30,"1-30",IF(TODAY()-D9<=60,"31-60",IF(TODAY()-D9<=90,"61-90","90+")))))) | L9: =IF(A9="","",IF(COUNTIF(Invoices!$A$5:$A$204,A9)>1,"Duplicate invoice #",IF(B9="","Missing Job ID",IF(COUNTIF(Jobs!$A$5:$A$44,B9)=0,"Unknown Job ID",IF(D9="","Missing due date",IF(E9="","Missing amount","")))))) | M9: =IF(A9="","",IFERROR(INDEX(Jobs!$B$5:$B$44,MATCH(B9,Jobs!$A$5:$A$44,0)),"")) | N9: =IF(AND(A9<>"",M9<>"",M9='Client Statement'!$L$2),COUNTIF(M$5:M9,'Client Statement'!$L$2),"")
G10: =IF(A10="","",SUMIFS(Payments!$D$5:$D$304,Payments!$C$5:$C$304,A10)) | H10: =IF(A10="","",E10-G10) | I10: =IF(A10="","",IF(H10<=0,"Paid",IF(AND(D10<>"",TODAY()>D10+Settings!$B$13),"Overdue",IF(G10>0,"Partial","Open")))) | J10: =IF(A10="","",IF(I10="Overdue",TODAY()-D10,0)) | K10: =IF(A10="","",IF(H10<=0,"Paid",IF(OR(D10="",TODAY()<=D10),"Current",IF(TODAY()-D10<=30,"1-30",IF(TODAY()-D10<=60,"31-60",IF(TODAY()-D10<=90,"61-90","90+")))))) | L10: =IF(A10="","",IF(COUNTIF(Invoices!$A$5:$A$204,A10)>1,"Duplicate invoice #",IF(B10="","Missing Job ID",IF(COUNTIF(Jobs!$A$5:$A$44,B10)=0,"Unknown Job ID",IF(D10="","Missing due date",IF(E10="","Missing amount","")))))) | M10: =IF(A10="","",IFERROR(INDEX(Jobs!$B$5:$B$44,MATCH(B10,Jobs!$A$5:$A$44,0)),"")) | N10: =IF(AND(A10<>"",M10<>"",M10='Client Statement'!$L$2),COUNTIF(M$5:M10,'Client Statement'!$L$2),"")
G11: =IF(A11="","",SUMIFS(Payments!$D$5:$D$304,Payments!$C$5:$C$304,A11)) | H11: =IF(A11="","",E11-G11) | I11: =IF(A11="","",IF(H11<=0,"Paid",IF(AND(D11<>"",TODAY()>D11+Settings!$B$13),"Overdue",IF(G11>0,"Partial","Open")))) | J11: =IF(A11="","",IF(I11="Overdue",TODAY()-D11,0)) | K11: =IF(A11="","",IF(H11<=0,"Paid",IF(OR(D11="",TODAY()<=D11),"Current",IF(TODAY()-D11<=30,"1-30",IF(TODAY()-D11<=60,"31-60",IF(TODAY()-D11<=90,"61-90","90+")))))) | L11: =IF(A11="","",IF(COUNTIF(Invoices!$A$5:$A$204,A11)>1,"Duplicate invoice #",IF(B11="","Missing Job ID",IF(COUNTIF(Jobs!$A$5:$A$44,B11)=0,"Unknown Job ID",IF(D11="","Missing due date",IF(E11="","Missing amount","")))))) | M11: =IF(A11="","",IFERROR(INDEX(Jobs!$B$5:$B$44,MATCH(B11,Jobs!$A$5:$A$44,0)),"")) | N11: =IF(AND(A11<>"",M11<>"",M11='Client Statement'!$L$2),COUNTIF(M$5:M11,'Client Statement'!$L$2),"")
G12: =IF(A12="","",SUMIFS(Payments!$D$5:$D$304,Payments!$C$5:$C$304,A12)) | H12: =IF(A12="","",E12-G12) | I12: =IF(A12="","",IF(H12<=0,"Paid",IF(AND(D12<>"",TODAY()>D12+Settings!$B$13),"Overdue",IF(G12>0,"Partial","Open")))) | J12: =IF(A12="","",IF(I12="Overdue",TODAY()-D12,0)) | K12: =IF(A12="","",IF(H12<=0,"Paid",IF(OR(D12="",TODAY()<=D12),"Current",IF(TODAY()-D12<=30,"1-30",IF(TODAY()-D12<=60,"31-60",IF(TODAY()-D12<=90,"61-90","90+")))))) | L12: =IF(A12="","",IF(COUNTIF(Invoices!$A$5:$A$204,A12)>1,"Duplicate invoice #",IF(B12="","Missing Job ID",IF(COUNTIF(Jobs!$A$5:$A$44,B12)=0,"Unknown Job ID",IF(D12="","Missing due date",IF(E12="","Missing amount","")))))) | M12: =IF(A12="","",IFERROR(INDEX(Jobs!$B$5:$B$44,MATCH(B12,Jobs!$A$5:$A$44,0)),"")) | N12: =IF(AND(A12<>"",M12<>"",M12='Client Statement'!$L$2),COUNTIF(M$5:M12,'Client Statement'!$L$2),"")
G13: =IF(A13="","",SUMIFS(Payments!$D$5:$D$304,Payments!$C$5:$C$304,A13)) | H13: =IF(A13="","",E13-G13) | I13: =IF(A13="","",IF(H13<=0,"Paid",IF(AND(D13<>"",TODAY()>D13+Settings!$B$13),"Overdue",IF(G13>0,"Partial","Open")))) | J13: =IF(A13="","",IF(I13="Overdue",TODAY()-D13,0)) | K13: =IF(A13="","",IF(H13<=0,"Paid",IF(OR(D13="",TODAY()<=D13),"Current",IF(TODAY()-D13<=30,"1-30",IF(TODAY()-D13<=60,"31-60",IF(TODAY()-D13<=90,"61-90","90+")))))) | L13: =IF(A13="","",IF(COUNTIF(Invoices!$A$5:$A$204,A13)>1,"Duplicate invoice #",IF(B13="","Missing Job ID",IF(COUNTIF(Jobs!$A$5:$A$44,B13)=0,"Unknown Job ID",IF(D13="","Missing due date",IF(E13="","Missing amount","")))))) | M13: =IF(A13="","",IFERROR(INDEX(Jobs!$B$5:$B$44,MATCH(B13,Jobs!$A$5:$A$44,0)),"")) | N13: =IF(AND(A13<>"",M13<>"",M13='Client Statement'!$L$2),COUNTIF(M$5:M13,'Client Statement'!$L$2),"")
G14: =IF(A14="","",SUMIFS(Payments!$D$5:$D$304,Payments!$C$5:$C$304,A14)) | H14: =IF(A14="","",E14-G14) | I14: =IF(A14="","",IF(H14<=0,"Paid",IF(AND(D14<>"",TODAY()>D14+Settings!$B$13),"Overdue",IF(G14>0,"Partial","Open")))) | J14: =IF(A14="","",IF(I14="Overdue",TODAY()-D14,0)) | K14: =IF(A14="","",IF(H14<=0,"Paid",IF(OR(D14="",TODAY()<=D14),"Current",IF(TODAY()-D14<=30,"1-30",IF(TODAY()-D14<=60,"31-60",IF(TODAY()-D14<=90,"61-90","90+")))))) | L14: =IF(A14="","",IF(COUNTIF(Invoices!$A$5:$A$204,A14)>1,"Duplicate invoice #",IF(B14="","Missing Job ID",IF(COUNTIF(Jobs!$A$5:$A$44,B14)=0,"Unknown Job ID",IF(D14="","Missing due date",IF(E14="","Missing amount","")))))) | M14: =IF(A14="","",IFERROR(INDEX(Jobs!$B$5:$B$44,MATCH(B14,Jobs!$A$5:$A$44,0)),"")) | N14: =IF(AND(A14<>"",M14<>"",M14='Client Statement'!$L$2),COUNTIF(M$5:M14,'Client Statement'!$L$2),"")
G15: =IF(A15="","",SUMIFS(Payments!$D$5:$D$304,Payments!$C$5:$C$304,A15)) | H15: =IF(A15="","",E15-G15) | I15: =IF(A15="","",IF(H15<=0,"Paid",IF(AND(D15<>"",TODAY()>D15+Settings!$B$13),"Overdue",IF(G15>0,"Partial","Open")))) | J15: =IF(A15="","",IF(I15="Overdue",TODAY()-D15,0)) | K15: =IF(A15="","",IF(H15<=0,"Paid",IF(OR(D15="",TODAY()<=D15),"Current",IF(TODAY()-D15<=30,"1-30",IF(TODAY()-D15<=60,"31-60",IF(TODAY()-D15<=90,"61-90","90+")))))) | L15: =IF(A15="","",IF(COUNTIF(Invoices!$A$5:$A$204,A15)>1,"Duplicate invoice #",IF(B15="","Missing Job ID",IF(COUNTIF(Jobs!$A$5:$A$44,B15)=0,"Unknown Job ID",IF(D15="","Missing due date",IF(E15="","Missing amount","")))))) | M15: =IF(A15="","",IFERROR(INDEX(Jobs!$B$5:$B$44,MATCH(B15,Jobs!$A$5:$A$44,0)),"")) | N15: =IF(AND(A15<>"",M15<>"",M15='Client Statement'!$L$2),COUNTIF(M$5:M15,'Client Statement'!$L$2),"")
G16: =IF(A16="","",SUMIFS(Payments!$D$5:$D$304,Payments!$C$5:$C$304,A16)) | H16: =IF(A16="","",E16-G16) | I16: =IF(A16="","",IF(H16<=0,"Paid",IF(AND(D16<>"",TODAY()>D16+Settings!$B$13),"Overdue",IF(G16>0,"Partial","Open")))) | J16: =IF(A16="","",IF(I16="Overdue",TODAY()-D16,0)) | K16: =IF(A16="","",IF(H16<=0,"Paid",IF(OR(D16="",TODAY()<=D16),"Current",IF(TODAY()-D16<=30,"1-30",IF(TODAY()-D16<=60,"31-60",IF(TODAY()-D16<=90,"61-90","90+")))))) | L16: =IF(A16="","",IF(COUNTIF(Invoices!$A$5:$A$204,A16)>1,"Duplicate invoice #",IF(B16="","Missing Job ID",IF(COUNTIF(Jobs!$A$5:$A$44,B16)=0,"Unknown Job ID",IF(D16="","Missing due date",IF(E16="","Missing amount","")))))) | M16: =IF(A16="","",IFERROR(INDEX(Jobs!$B$5:$B$44,MATCH(B16,Jobs!$A$5:$A$44,0)),"")) | N16: =IF(AND(A16<>"",M16<>"",M16='Client Statement'!$L$2),COUNTIF(M$5:M16,'Client Statement'!$L$2),"")
... G204: =IF(A204="","",SUMIFS(Payments!$D$5:$D$304,Payments!$C$5:$C$304,A204)) | H204: =IF(A204="","",E204-G204) | I204: =IF(A204="","",IF(H204<=0,"Paid",IF(AND(D204<>"",TODAY()>D204+Settings!$B$13),"Overdue",IF(G204>0,"Partial","Open")))) | J204: =IF(A204="","",IF(I204="Overdue",TODAY()-D204,0)) | K204: =IF(A204="","",IF(H204<=0,"Paid",IF(OR(D204="",TODAY()<=D204),"Current",IF(TODAY()-D204<=30,"1-30",IF(TODAY()-D204<=60,"31-60",IF(TODAY()-D204<=90,"61-90","90+")))))) | L204: =IF(A204="","",IF(COUNTIF(Invoices!$A$5:$A$204,A204)>1,"Duplicate invoice #",IF(B204="","Missing Job ID",IF(COUNTIF(Jobs!$A$5:$A$44,B204)=0,"Unknown Job ID",IF(D204="","Missing due date",IF(E204="","Missing amount","")))))) | M204: =IF(A204="","",IFERROR(INDEX(Jobs!$B$5:$B$44,MATCH(B204,Jobs!$A$5:$A$44,0)),"")) | N204: =IF(AND(A204<>"",M204<>"",M204='Client Statement'!$L$2),COUNTIF(M$5:M204,'Client Statement'!$L$2),"")
A205: TOTAL | E205: =SUM(E5:E204) | G205: =SUM(G5:G204) | H205: =SUM(H5:H204)

Sheet Invoice Print
A1: INVOICE
H2: Invoice #
H3: ← pick an invoice; print or save as PDF. Columns H–I never print.
B4: FROM | E4: BILL TO
B5: =Settings!$B$5&"" | E5: =IFERROR(INDEX(Jobs!$B$5:$B$44,MATCH(IFERROR(INDEX(Invoices!$B$5:$B$204,MATCH($I$2,Invoices!$A$5:$A$204,0)),""),Jobs!$A$5:$A$44,0)),"")
B6: =Settings!$B$6&"" | E6: =IFERROR(INDEX(Clients!$B$5:$B$104,MATCH(IFERROR(INDEX(Jobs!$B$5:$B$44,MATCH(IFERROR(INDEX(Invoices!$B$5:$B$204,MATCH($I$2,Invoices!$A$5:$A$204,0)),""),Jobs!$A$5:$A$44,0)),""),Clients!$A$5:$A$104,0)),"")
B7: =Settings!$B$7&"" | E7: =IFERROR(INDEX(Clients!$E$5:$E$104,MATCH(IFERROR(INDEX(Jobs!$B$5:$B$44,MATCH(IFERROR(INDEX(Invoices!$B$5:$B$204,MATCH($I$2,Invoices!$A$5:$A$204,0)),""),Jobs!$A$5:$A$44,0)),""),Clients!$A$5:$A$104,0)),"")
B8: =IF(Settings!$B$8="","","License # "&Settings!$B$8) | E8: =IFERROR(INDEX(Clients!$D$5:$D$104,MATCH(IFERROR(INDEX(Jobs!$B$5:$B$44,MATCH(IFERROR(INDEX(Invoices!$B$5:$B$204,MATCH($I$2,Invoices!$A$5:$A$204,0)),""),Jobs!$A$5:$A$44,0)),""),Clients!$A$5:$A$104,0)),"")
B10: Invoice number | E10: =$I$2&""
B11: Invoice date | E11: =IFERROR(INDEX(Invoices!$C$5:$C$204,MATCH($I$2,Invoices!$A$5:$A$204,0)),"")
B12: Due date | E12: =IFERROR(INDEX(Invoices!$D$5:$D$204,MATCH($I$2,Invoices!$A$5:$A$204,0)),"")
B13: Job | E13: =IF($I$2="","",IFERROR(INDEX(Invoices!$B$5:$B$204,MATCH($I$2,Invoices!$A$5:$A$204,0)),"")&" — "&IFERROR(INDEX(Jobs!$C$5:$C$44,MATCH(IFERROR(INDEX(Invoices!$B$5:$B$204,MATCH($I$2,Invoices!$A$5:$A$204,0)),""),Jobs!$A$5:$A$44,0)),""))
B15: Description | E15: Amount
B16: =IF(IFERROR(INDEX(Invoices!$F$5:$F$204,MATCH($I$2,Invoices!$A$5:$A$204,0)),"")="","Services per contract",IFERROR(INDEX(Invoices!$F$5:$F$204,MATCH($I$2,Invoices!$A$5:$A$204,0)),"")) | E16: =IFERROR(INDEX(Invoices!$E$5:$E$204,MATCH($I$2,Invoices!$A$5:$A$204,0)),"")
B17: Less: payments received on this invoice | E17: =IF($I$2="","",-IFERROR(INDEX(Invoices!$G$5:$G$204,MATCH($I$2,Invoices!$A$5:$A$204,0)),""))
B18: BALANCE DUE | E18: =IFERROR(INDEX(Invoices!$H$5:$H$204,MATCH($I$2,Invoices!$A$5:$A$204,0)),"")
B19: =IF(AND($I$2<>"",E16<>"",E16>0,E18=0),"PAID IN FULL — thank you","")
B20: Contract summary
B21: Revised contract value | E21: =IFERROR(INDEX(Jobs!$K$5:$K$44,MATCH(IFERROR(INDEX(Invoices!$B$5:$B$204,MATCH($I$2,Invoices!$A$5:$A$204,0)),""),Jobs!$A$5:$A$44,0)),"")
B22: Invoiced to date (all invoices) | E22: =IFERROR(INDEX(Jobs!$Q$5:$Q$44,MATCH(IFERROR(INDEX(Invoices!$B$5:$B$204,MATCH($I$2,Invoices!$A$5:$A$204,0)),""),Jobs!$A$5:$A$44,0)),"")
B23: Paid to date (all invoices) | E23: =IFERROR(INDEX(Jobs!$R$5:$R$44,MATCH(IFERROR(INDEX(Invoices!$B$5:$B$204,MATCH($I$2,Invoices!$A$5:$A$204,0)),""),Jobs!$A$5:$A$44,0)),"")
B24: Remaining to invoice | E24: =IF($I$2="","",IFERROR(INDEX(Jobs!$K$5:$K$44,MATCH(IFERROR(INDEX(Invoices!$B$5:$B$204,MATCH($I$2,Invoices!$A$5:$A$204,0)),""),Jobs!$A$5:$A$44,0)),"")-IFERROR(INDEX(Jobs!$Q$5:$Q$44,MATCH(IFERROR(INDEX(Invoices!$B$5:$B$204,MATCH($I$2,Invoices!$A$5:$A$204,0)),""),Jobs!$A$5:$A$44,0)),""))
B26: Payment instructions
B27: =Settings!$B$31
B29: =Settings!$B$32
B31: REMITTANCE — detach and return with payment
B32: Payable to | E32: =Settings!$B$5&""
B33: Invoice number | E33: =$I$2&""
B34: Balance due | E34: =IFERROR(INDEX(Invoices!$H$5:$H$204,MATCH($I$2,Invoices!$A$5:$A$204,0)),"")
B35: Amount enclosed | E35: $ ______________

Sheet Payments
A1: Payments received
A2: Every client payment. Invoice # links it to an invoice; Job ID drives the job's Collected total and the cash P&L.
A4: Date | B4: Job ID | C4: Invoice # | D4: Amount | E4: Method | F4: Reference / Check # | G4: Check | H4: Notes
G5: =IF(AND(B5="",D5=""),"",IF(B5="","Missing Job ID",IF(COUNTIF(Jobs!$A$5:$A$44,B5)=0,"Unknown Job ID",IF(AND(C5<>"",COUNTIF(Invoices!$A$5:$A$204,C5)=0),"Invoice # not in Invoices",IF(A5="","Missing date","")))))
G6: =IF(AND(B6="",D6=""),"",IF(B6="","Missing Job ID",IF(COUNTIF(Jobs!$A$5:$A$44,B6)=0,"Unknown Job ID",IF(AND(C6<>"",COUNTIF(Invoices!$A$5:$A$204,C6)=0),"Invoice # not in Invoices",IF(A6="","Missing date","")))))
G7: =IF(AND(B7="",D7=""),"",IF(B7="","Missing Job ID",IF(COUNTIF(Jobs!$A$5:$A$44,B7)=0,"Unknown Job ID",IF(AND(C7<>"",COUNTIF(Invoices!$A$5:$A$204,C7)=0),"Invoice # not in Invoices",IF(A7="","Missing date","")))))
G8: =IF(AND(B8="",D8=""),"",IF(B8="","Missing Job ID",IF(COUNTIF(Jobs!$A$5:$A$44,B8)=0,"Unknown Job ID",IF(AND(C8<>"",COUNTIF(Invoices!$A$5:$A$204,C8)=0),"Invoice # not in Invoices",IF(A8="","Missing date","")))))
G9: =IF(AND(B9="",D9=""),"",IF(B9="","Missing Job ID",IF(COUNTIF(Jobs!$A$5:$A$44,B9)=0,"Unknown Job ID",IF(AND(C9<>"",COUNTIF(Invoices!$A$5:$A$204,C9)=0),"Invoice # not in Invoices",IF(A9="","Missing date","")))))
G10: =IF(AND(B10="",D10=""),"",IF(B10="","Missing Job ID",IF(COUNTIF(Jobs!$A$5:$A$44,B10)=0,"Unknown Job ID",IF(AND(C10<>"",COUNTIF(Invoices!$A$5:$A$204,C10)=0),"Invoice # not in Invoices",IF(A10="","Missing date","")))))
G11: =IF(AND(B11="",D11=""),"",IF(B11="","Missing Job ID",IF(COUNTIF(Jobs!$A$5:$A$44,B11)=0,"Unknown Job ID",IF(AND(C11<>"",COUNTIF(Invoices!$A$5:$A$204,C11)=0),"Invoice # not in Invoices",IF(A11="","Missing date","")))))
G12: =IF(AND(B12="",D12=""),"",IF(B12="","Missing Job ID",IF(COUNTIF(Jobs!$A$5:$A$44,B12)=0,"Unknown Job ID",IF(AND(C12<>"",COUNTIF(Invoices!$A$5:$A$204,C12)=0),"Invoice # not in Invoices",IF(A12="","Missing date","")))))
G13: =IF(AND(B13="",D13=""),"",IF(B13="","Missing Job ID",IF(COUNTIF(Jobs!$A$5:$A$44,B13)=0,"Unknown Job ID",IF(AND(C13<>"",COUNTIF(Invoices!$A$5:$A$204,C13)=0),"Invoice # not in Invoices",IF(A13="","Missing date","")))))
G14: =IF(AND(B14="",D14=""),"",IF(B14="","Missing Job ID",IF(COUNTIF(Jobs!$A$5:$A$44,B14)=0,"Unknown Job ID",IF(AND(C14<>"",COUNTIF(Invoices!$A$5:$A$204,C14)=0),"Invoice # not in Invoices",IF(A14="","Missing date","")))))
G15: =IF(AND(B15="",D15=""),"",IF(B15="","Missing Job ID",IF(COUNTIF(Jobs!$A$5:$A$44,B15)=0,"Unknown Job ID",IF(AND(C15<>"",COUNTIF(Invoices!$A$5:$A$204,C15)=0),"Invoice # not in Invoices",IF(A15="","Missing date","")))))
G16: =IF(AND(B16="",D16=""),"",IF(B16="","Missing Job ID",IF(COUNTIF(Jobs!$A$5:$A$44,B16)=0,"Unknown Job ID",IF(AND(C16<>"",COUNTIF(Invoices!$A$5:$A$204,C16)=0),"Invoice # not in Invoices",IF(A16="","Missing date","")))))
... G304: =IF(AND(B304="",D304=""),"",IF(B304="","Missing Job ID",IF(COUNTIF(Jobs!$A$5:$A$44,B304)=0,"Unknown Job ID",IF(AND(C304<>"",COUNTIF(Invoices!$A$5:$A$204,C304)=0),"Invoice # not in Invoices",IF(A304="","Missing date","")))))
A305: TOTAL | D305: =SUM(D5:D304)

Sheet Client Statement
A1: STATEMENT
K2: Client
K3: ← pick a client; print or save as PDF. Columns K–L never print.
B4: FROM | F4: TO
B5: =Settings!$B$5&"" | F5: =$L$2&""
B6: =Settings!$B$6&"" | F6: =IFERROR(INDEX(Clients!$B$5:$B$104,MATCH($L$2,Clients!$A$5:$A$104,0)),"")
B7: =Settings!$B$7&"" | F7: =IFERROR(INDEX(Clients!$E$5:$E$104,MATCH($L$2,Clients!$A$5:$A$104,0)),"")
B8: =IF(Settings!$B$8="","","License # "&Settings!$B$8) | F8: =IFERROR(INDEX(Clients!$D$5:$D$104,MATCH($L$2,Clients!$A$5:$A$104,0)),"")
B10: Statement date | D10: =TODAY() | F10: TOTAL BALANCE DUE | H10: =SUMIFS(Invoices!$H$5:$H$204,Invoices!$M$5:$M$204,$L$2)
B12: Invoice # | C12: Job | D12: Invoice date | E12: Due date | F12: Amount | G12: Paid | H12: Balance | I12: Status
B13: =IFERROR(INDEX(Invoices!$A$5:$A$204,MATCH(1,Invoices!$N$5:$N$204,0)),"") | C13: =IFERROR(INDEX(Invoices!$B$5:$B$204,MATCH(1,Invoices!$N$5:$N$204,0))&" "&INDEX(Invoices!$F$5:$F$204,MATCH(1,Invoices!$N$5:$N$204,0)),"") | D13: =IFERROR(INDEX(Invoices!$C$5:$C$204,MATCH(1,Invoices!$N$5:$N$204,0)),"") | E13: =IFERROR(INDEX(Invoices!$D$5:$D$204,MATCH(1,Invoices!$N$5:$N$204,0)),"") | F13: =IFERROR(INDEX(Invoices!$E$5:$E$204,MATCH(1,Invoices!$N$5:$N$204,0)),"") | G13: =IFERROR(INDEX(Invoices!$G$5:$G$204,MATCH(1,Invoices!$N$5:$N$204,0)),"") | H13: =IFERROR(INDEX(Invoices!$H$5:$H$204,MATCH(1,Invoices!$N$5:$N$204,0)),"") | I13: =IFERROR(INDEX(Invoices!$I$5:$I$204,MATCH(1,Invoices!$N$5:$N$204,0)),"")
B14: =IFERROR(INDEX(Invoices!$A$5:$A$204,MATCH(2,Invoices!$N$5:$N$204,0)),"") | C14: =IFERROR(INDEX(Invoices!$B$5:$B$204,MATCH(2,Invoices!$N$5:$N$204,0))&" "&INDEX(Invoices!$F$5:$F$204,MATCH(2,Invoices!$N$5:$N$204,0)),"") | D14: =IFERROR(INDEX(Invoices!$C$5:$C$204,MATCH(2,Invoices!$N$5:$N$204,0)),"") | E14: =IFERROR(INDEX(Invoices!$D$5:$D$204,MATCH(2,Invoices!$N$5:$N$204,0)),"") | F14: =IFERROR(INDEX(Invoices!$E$5:$E$204,MATCH(2,Invoices!$N$5:$N$204,0)),"") | G14: =IFERROR(INDEX(Invoices!$G$5:$G$204,MATCH(2,Invoices!$N$5:$N$204,0)),"") | H14: =IFERROR(INDEX(Invoices!$H$5:$H$204,MATCH(2,Invoices!$N$5:$N$204,0)),"") | I14: =IFERROR(INDEX(Invoices!$I$5:$I$204,MATCH(2,Invoices!$N$5:$N$204,0)),"")
B15: =IFERROR(INDEX(Invoices!$A$5:$A$204,MATCH(3,Invoices!$N$5:$N$204,0)),"") | C15: =IFERROR(INDEX(Invoices!$B$5:$B$204,MATCH(3,Invoices!$N$5:$N$204,0))&" "&INDEX(Invoices!$F$5:$F$204,MATCH(3,Invoices!$N$5:$N$204,0)),"") | D15: =IFERROR(INDEX(Invoices!$C$5:$C$204,MATCH(3,Invoices!$N$5:$N$204,0)),"") | E15: =IFERROR(INDEX(Invoices!$D$5:$D$204,MATCH(3,Invoices!$N$5:$N$204,0)),"") | F15: =IFERROR(INDEX(Invoices!$E$5:$E$204,MATCH(3,Invoices!$N$5:$N$204,0)),"") | G15: =IFERROR(INDEX(Invoices!$G$5:$G$204,MATCH(3,Invoices!$N$5:$N$204,0)),"") | H15: =IFERROR(INDEX(Invoices!$H$5:$H$204,MATCH(3,Invoices!$N$5:$N$204,0)),"") | I15: =IFERROR(INDEX(Invoices!$I$5:$I$204,MATCH(3,Invoices!$N$5:$N$204,0)),"")
B16: =IFERROR(INDEX(Invoices!$A$5:$A$204,MATCH(4,Invoices!$N$5:$N$204,0)),"") | C16: =IFERROR(INDEX(Invoices!$B$5:$B$204,MATCH(4,Invoices!$N$5:$N$204,0))&" "&INDEX(Invoices!$F$5:$F$204,MATCH(4,Invoices!$N$5:$N$204,0)),"") | D16: =IFERROR(INDEX(Invoices!$C$5:$C$204,MATCH(4,Invoices!$N$5:$N$204,0)),"") | E16: =IFERROR(INDEX(Invoices!$D$5:$D$204,MATCH(4,Invoices!$N$5:$N$204,0)),"") | F16: =IFERROR(INDEX(Invoices!$E$5:$E$204,MATCH(4,Invoices!$N$5:$N$204,0)),"") | G16: =IFERROR(INDEX(Invoices!$G$5:$G$204,MATCH(4,Invoices!$N$5:$N$204,0)),"") | H16: =IFERROR(INDEX(Invoices!$H$5:$H$204,MATCH(4,Invoices!$N$5:$N$204,0)),"") | I16: =IFERROR(INDEX(Invoices!$I$5:$I$204,MATCH(4,Invoices!$N$5:$N$204,0)),"")
B17: =IFERROR(INDEX(Invoices!$A$5:$A$204,MATCH(5,Invoices!$N$5:$N$204,0)),"") | C17: =IFERROR(INDEX(Invoices!$B$5:$B$204,MATCH(5,Invoices!$N$5:$N$204,0))&" "&INDEX(Invoices!$F$5:$F$204,MATCH(5,Invoices!$N$5:$N$204,0)),"") | D17: =IFERROR(INDEX(Invoices!$C$5:$C$204,MATCH(5,Invoices!$N$5:$N$204,0)),"") | E17: =IFERROR(INDEX(Invoices!$D$5:$D$204,MATCH(5,Invoices!$N$5:$N$204,0)),"") | F17: =IFERROR(INDEX(Invoices!$E$5:$E$204,MATCH(5,Invoices!$N$5:$N$204,0)),"") | G17: =IFERROR(INDEX(Invoices!$G$5:$G$204,MATCH(5,Invoices!$N$5:$N$204,0)),"") | H17: =IFERROR(INDEX(Invoices!$H$5:$H$204,MATCH(5,Invoices!$N$5:$N$204,0)),"") | I17: =IFERROR(INDEX(Invoices!$I$5:$I$204,MATCH(5,Invoices!$N$5:$N$204,0)),"")
B18: =IFERROR(INDEX(Invoices!$A$5:$A$204,MATCH(6,Invoices!$N$5:$N$204,0)),"") | C18: =IFERROR(INDEX(Invoices!$B$5:$B$204,MATCH(6,Invoices!$N$5:$N$204,0))&" "&INDEX(Invoices!$F$5:$F$204,MATCH(6,Invoices!$N$5:$N$204,0)),"") | D18: =IFERROR(INDEX(Invoices!$C$5:$C$204,MATCH(6,Invoices!$N$5:$N$204,0)),"") | E18: =IFERROR(INDEX(Invoices!$D$5:$D$204,MATCH(6,Invoices!$N$5:$N$204,0)),"") | F18: =IFERROR(INDEX(Invoices!$E$5:$E$204,MATCH(6,Invoices!$N$5:$N$204,0)),"") | G18: =IFERROR(INDEX(Invoices!$G$5:$G$204,MATCH(6,Invoices!$N$5:$N$204,0)),"") | H18: =IFERROR(INDEX(Invoices!$H$5:$H$204,MATCH(6,Invoices!$N$5:$N$204,0)),"") | I18: =IFERROR(INDEX(Invoices!$I$5:$I$204,MATCH(6,Invoices!$N$5:$N$204,0)),"")
B19: =IFERROR(INDEX(Invoices!$A$5:$A$204,MATCH(7,Invoices!$N$5:$N$204,0)),"") | C19: =IFERROR(INDEX(Invoices!$B$5:$B$204,MATCH(7,Invoices!$N$5:$N$204,0))&" "&INDEX(Invoices!$F$5:$F$204,MATCH(7,Invoices!$N$5:$N$204,0)),"") | D19: =IFERROR(INDEX(Invoices!$C$5:$C$204,MATCH(7,Invoices!$N$5:$N$204,0)),"") | E19: =IFERROR(INDEX(Invoices!$D$5:$D$204,MATCH(7,Invoices!$N$5:$N$204,0)),"") | F19: =IFERROR(INDEX(Invoices!$E$5:$E$204,MATCH(7,Invoices!$N$5:$N$204,0)),"") | G19: =IFERROR(INDEX(Invoices!$G$5:$G$204,MATCH(7,Invoices!$N$5:$N$204,0)),"") | H19: =IFERROR(INDEX(Invoices!$H$5:$H$204,MATCH(7,Invoices!$N$5:$N$204,0)),"") | I19: =IFERROR(INDEX(Invoices!$I$5:$I$204,MATCH(7,Invoices!$N$5:$N$204,0)),"")
B20: =IFERROR(INDEX(Invoices!$A$5:$A$204,MATCH(8,Invoices!$N$5:$N$204,0)),"") | C20: =IFERROR(INDEX(Invoices!$B$5:$B$204,MATCH(8,Invoices!$N$5:$N$204,0))&" "&INDEX(Invoices!$F$5:$F$204,MATCH(8,Invoices!$N$5:$N$204,0)),"") | D20: =IFERROR(INDEX(Invoices!$C$5:$C$204,MATCH(8,Invoices!$N$5:$N$204,0)),"") | E20: =IFERROR(INDEX(Invoices!$D$5:$D$204,MATCH(8,Invoices!$N$5:$N$204,0)),"") | F20: =IFERROR(INDEX(Invoices!$E$5:$E$204,MATCH(8,Invoices!$N$5:$N$204,0)),"") | G20: =IFERROR(INDEX(Invoices!$G$5:$G$204,MATCH(8,Invoices!$N$5:$N$204,0)),"") | H20: =IFERROR(INDEX(Invoices!$H$5:$H$204,MATCH(8,Invoices!$N$5:$N$204,0)),"") | I20: =IFERROR(INDEX(Invoices!$I$5:$I$204,MATCH(8,Invoices!$N$5:$N$204,0)),"")
B21: =IFERROR(INDEX(Invoices!$A$5:$A$204,MATCH(9,Invoices!$N$5:$N$204,0)),"") | C21: =IFERROR(INDEX(Invoices!$B$5:$B$204,MATCH(9,Invoices!$N$5:$N$204,0))&" "&INDEX(Invoices!$F$5:$F$204,MATCH(9,Invoices!$N$5:$N$204,0)),"") | D21: =IFERROR(INDEX(Invoices!$C$5:$C$204,MATCH(9,Invoices!$N$5:$N$204,0)),"") | E21: =IFERROR(INDEX(Invoices!$D$5:$D$204,MATCH(9,Invoices!$N$5:$N$204,0)),"") | F21: =IFERROR(INDEX(Invoices!$E$5:$E$204,MATCH(9,Invoices!$N$5:$N$204,0)),"") | G21: =IFERROR(INDEX(Invoices!$G$5:$G$204,MATCH(9,Invoices!$N$5:$N$204,0)),"") | H21: =IFERROR(INDEX(Invoices!$H$5:$H$204,MATCH(9,Invoices!$N$5:$N$204,0)),"") | I21: =IFERROR(INDEX(Invoices!$I$5:$I$204,MATCH(9,Invoices!$N$5:$N$204,0)),"")
B22: =IFERROR(INDEX(Invoices!$A$5:$A$204,MATCH(10,Invoices!$N$5:$N$204,0)),"") | C22: =IFERROR(INDEX(Invoices!$B$5:$B$204,MATCH(10,Invoices!$N$5:$N$204,0))&" "&INDEX(Invoices!$F$5:$F$204,MATCH(10,Invoices!$N$5:$N$204,0)),"") | D22: =IFERROR(INDEX(Invoices!$C$5:$C$204,MATCH(10,Invoices!$N$5:$N$204,0)),"") | E22: =IFERROR(INDEX(Invoices!$D$5:$D$204,MATCH(10,Invoices!$N$5:$N$204,0)),"") | F22: =IFERROR(INDEX(Invoices!$E$5:$E$204,MATCH(10,Invoices!$N$5:$N$204,0)),"") | G22: =IFERROR(INDEX(Invoices!$G$5:$G$204,MATCH(10,Invoices!$N$5:$N$204,0)),"") | H22: =IFERROR(INDEX(Invoices!$H$5:$H$204,MATCH(10,Invoices!$N$5:$N$204,0)),"") | I22: =IFERROR(INDEX(Invoices!$I$5:$I$204,MATCH(10,Invoices!$N$5:$N$204,0)),"")
